Workbook
Name Account_Management_fee: '[1]Master data Input'!$C$39
Name Account_Management_fee: '[1]Master data Input'!$C$39
Name Account_Management_fee: 'Master data Input'!$C$40
Name Address: '[1]Master data Input'!$C$7
Name Address: '[1]Master data Input'!$C$7
Name Address: 'Master data Input'!$C$8
Name Advanced_Payment: '[1]Master data Input'!$F$11
Name Advanced_Payment: '[1]Master data Input'!$F$11
Name Advanced_Payment: 'Master data Input'!$C$22
Name Agent: [1]Agent!$A$1:$A$29
Name Agent: [1]Agent!$A$1:$A$29
Name Agent: Agent!$A$1:$A$30
Name Agents: '[1]Master data Input'!$F$13
Name Agents: '[1]Master data Input'!$F$13
Name Agents: 'Master data Input'!$F$14
Name Amount_of_Loan: '48 payments (computation)semi'!$B$42
Name Amount_of_Loan: '[1]Computation Sheet'!$B$43
Name Amount_of_Loan: 'Monthly -client copy'!$A$41
Name Amount_of_Loan: '[1]Computation Sheet'!$B$43
Name Amount_of_Loan: 'Semi Monthly'!$B$43
Name Amount_of_Loan: 'Semi Monthly -client copy'!$A$41
Name Amount_of_Loan: 'Semi Monthly 3 SL'!$B$43
Name Cash_Advance: '[1]Master data Input'!$E$11
Name Cash_Advance: '[1]Master data Input'!$E$11
Name Cash_Advance: 'Master data Input'!$B$22
Name choice: 'Parameter (2)'!$J$2:$J$3
Name Client_Name: '[1]Master data Input'!$C$5
Name Client_Name: '[1]Master data Input'!$C$5
Name Client_Name: 'Master data Input'!$C$6
Name Contractual_Rate: '[1](New)Amort. Sched-Diminishing'!$C$27
Name Contractual_Rate: '[1](New)Amort. Sched-Diminishing'!$C$27
Name Contractual_Rate: 'computation sheet'!$C$27
Name Date_Released: '[1]Master data Input'!$C$27
Name Date_Released: '[1]Master data Input'!$C$27
Name Date_Released: 'Master data Input'!$C$28
Name Date_Released_SM: 'Master data Input'!$K$6
Name Date_released2: '48 payments (computation)semi'!$M$13
Name Date_released2: '[1]Computation Sheet'!$M$14
Name Date_released2: 'Monthly -client copy'!$M$10
Name Date_released2: '[1]Computation Sheet'!$M$14
Name Date_released2: 'Semi Monthly'!$M$14
Name Date_released2: 'Semi Monthly -client copy'!$M$10
Name Date_released2: 'Semi Monthly 3 SL'!$M$14
Name Doc_fee: '48 payments (computation)semi'!$E$31
Name Doc_fee: 'Monthly -client copy'!#REF!
Name Doc_fee: 'Semi Monthly'!$E$32
Name Doc_fee: 'Semi Monthly -client copy'!#REF!
Name Doc_fee: 'Semi Monthly 3 SL'!$E$32
Name Docfee_Yes_or_No: '[1]Master data Input'!$C$43
Name Docfee_Yes_or_No: '[1]Master data Input'!$C$43
Name Docfee_Yes_or_No: 'Master data Input'!$C$44
Name EIR: '[1](New)Amort. Sched-Diminishing'!$C$34
Name EIR: '[1](New)Amort. Sched-Diminishing'!$C$34
Name EIR: 'Semi Monthly SL'!$C$34
Name EIR: 'computation sheet'!$C$34
Name Express: '[1]Master data Input'!$C$15
Name Express: '[1]Master data Input'!$C$15
Name Express: 'Master data Input'!$C$16
Name get_gross_amount: #REF!
Name get_gross_amount: #REF!

Sheet MENU

Sheet Master data Input
B2: LOAN COMPUTATION SHEET ver2 | I2: Semi-Monthly
B6: Name | C6: ** | D6: or | E6: ** | I6: Date Released | K6: 43265
B8: Address | C8: ** | I8: 1st payment | K8: 43317
K9: 2
B10: GROSS AMOUNT | C10: 80953.71 | E10: PN no. | F10: . | I10: Term | K10: 12
K11: 6
B12: Outstanding Balance from previous loan | C12: 0 | I12: # of Amortization | K12: 12
B14: Type of Loan | C14: SML | E14: Agent | I14: Maturity Date | K14: 43651
B16: EXPRESS | C16: NO | E16: Referal fee % | I16: Mode of Payment | K16: Monthly
B18: New | C18: No | E18: Nth Loan
B20: Mode of Payment | C20: Monthly | I20: Business Loan
B22: Cash Advance | C22: 0 | I22: Interest deduct upfront | K22: NO
B24: Add On Rate | C24: 0.03 | J24: AMOUNT | K24: 9473.68
B26: Processing Fee in Percentage | C26: 0.075
B28: Date Released | C28: 46083 | E28: =C36 -> 46342 | F28: =C36 -> 46342
B30: 1st payment | C30: 46128 | E30: 46342 | F30: 46342
B32: Term | C32: 8
B34: # of Amortization | C34: 8 | E34: Letter Signatory | G34: =IF($C$20="Semi-Monthly","<= INPUT MATURITY DATE HERE","")
B36: Maturity Date | C36: 46342 | E36: Position
B38: Notarial Fee | C38: 500 | E38: Branch
B40: Account Management fee | C40: Auto compute** | E40: Bank
B42: MLRI -Insurance | C42: Auto compute** | E42: Mode of Payment
B44: Doc Fee | C44: 500
B45: Miscellaneous | C45: 500

Sheet computation sheet
A3: COMPUTATION OF NET PROCEEDS | M3: 42632
E4: from | F4: =Date_Released -> 46083 | G4: to | H4: =MaturityDate_data_input -> 46342 | M4: 42643
A5: Loan Amount | D5: =Loan_Amount -> 80953.71 | E5: Terms in Month: | F5: =Term_masterdatainput -> 8 | G5: No. of Payments: | H5: =Monthly_Inst -> 8 | M5: =DATEDIF(M3,M4,"d") -> 11
A7: Less: Deduction: | E7: New | G7: =Renewal -> No
A8: Loan Term Adjustment | E8: Renewal Nth loan | G8: ='Master data Input'!F18 -> 0 | K8: =IF(Type_of_Loan="BL-SA",ROUND(Principal_Amount*(((Total_InterestRate/Loan_Amount)/Monthly_Inst)/30)*DATEDIF(Date_Released,MaturityDate_data_input,"d"),0),ROUND(Principal_Amount*(((Total_InterestRate/Loan_Amount)/Monthly_Inst)/30)*DATEDIF(Date_Released,Date_released2,"d"),0)) -> 0 | L8: loan term adjustment | N8: =ROUND(((((Total_InterestRate/Principal_Amount)/Monthly_Inst)*100)),2)& "% from"&TEXT(Date_Released," mm/dd/yyyy")&" to "&TEXT(Date_released2," mm/dd/yyyy") -> 2.17% from 03/02/2026 to 03/02/2026
A9: =(ROUND(Interest,4)*100&"% from"&TEXT(Date_Released," mm/dd/yyyy")&" to "&TEXT('Monthly -client copy'!Date_released2," mm/dd/yyyy")) -> 3% from 03/02/2026 to 03/17/2026 | C9: =IF(upfront="YES",'Master data Input'!K24,IF(Type_of_Loan="BL-SA",0,ROUND(Loan_Amount*(Interest/30)*DATEDIF(Date_Released,'Monthly -client copy'!Date_released2,"d"),2))) -> 1214.31 | K9: =IF(Type_of_Loan="BL-SA",ROUND(Principal_Amount*(Interest/30)*DATEDIF(Date_Released,MaturityDate_data_input,"d"),0),ROUND(Principal_Amount*(Interest/30)*DATEDIF(Date_Released,Date_released2,"d"),0)) -> 0 | L9: Advance Interest | N9: =(Interest*100) & "% from"&TEXT(Date_Released," mm/dd/yyyy")&" to "&TEXT(Date_released2," mm/dd/yyyy") -> 3% from 03/02/2026 to 03/02/2026
A10: Processing Fee | B10: =Processing_Fee_in_Percentage -> 0.075 | C10: =D5*B10 -> 6071.5283 | E10: Installment Type | G10: =Installment_Type -> Monthly
A11: Account Management Fee | C11: 0 | E11: PN. No. | G11: =PN_no. -> .
A12: Doc Fee | C12: =Docfee_Yes_or_No -> 500
A13: Notarial Fee | C13: =Notarial_Fee -> 500 | E13: MODE OF PAYMENT: | K13: =Total_UII -> 14049.306 | L13: =Interest -> 0.03 | M13: UII (old computation sheet)
A14: ='Master data Input'!B42 -> MLRI -Insurance | C14: 0 | G14: ='Master data Input'!F42 -> 0 | K14: =Total_InterestRate -> 14049.306 | L14: =((((Total_InterestRate/C26)/Monthly_Inst))) -> 0.021693426 | M14: Total Interest (deminishing)
A15: =Cash_Advance -> Cash Advance | C15: =Advanced_Payment -> 0
A16: ='Master data Input'!B45 -> Miscellaneous | C16: ='Master data Input'!C45 -> 500 | E16: Branch: | G16: ='Master data Input'!F38 -> 0 | K16: =K13-K14 -> 0 | L16: difference
A17: Previous Loan Balance | C17: =Outstanding_Balance_from_previous_loan -> 0
A18: Total Deduction | D18: =SUM(C9:C17) -> 8785.8383 | E18: Release Date: | G18: =Date_Released -> 46083
A19: Net Proceeds | D19: =D5-D18 -> 72167.872 | E19: Agent: | F19: =Agents -> 0
D22: Name | K22: Payment Frequency Options
A23: Loan Information | D23: =IF(OR_NAME<>"",Client_Name &" or " & OR_NAME,Client_Name) -> ** or ** | K23: Frequency | L23: Payments/yr | M23: Months
K24: Annual | L24: 1 | M24: 12
A25: Loan Type | C25: =Type_of_Loan -> SML | K25: Semi-Annual | L25: 2 | M25: 6
A26: Principal Amount | C26: =D5 -> 80953.71 | D26: Address | K26: Quarterly | L26: 4 | M26: 3
A27: Contractual Rate (Monthly) | C27: 0.037 | D27: =Address -> ** | K27: Bi-Monthly | L27: 6 | M27: 2
A28: No. of Monthly Installment | C28: =Number_of_Amortization -> 8 | K28: Monthly | L28: 12 | M28: 1
A29: Monthly Payment | C29: =PMT(C$27,C28,-C26)*-1 -> -11875.377 | K29: Semi-Monthly | L29: 24 | M29: 0.5
A30: Other Charges | C30: =D18 -> 8785.8383 | K30: Bi-Weekly | L30: 26 | M30: n/a
K31: Weekly | L31: 52 | M31: n/a
A32: Summary | D32: Remarks | K32: Chosen: | L32: =INDEX(L24:L31,MATCH(Installment_Type,K24:K31,0)) -> 12 | M32: =INDEX(M24:M31,MATCH(Installment_Type,K24:K31,0)) -> 1
A34: Effective Annual Interest Rate (EIR) | C34: =(1+IRR($G$41:$G$59))^Monthly_Inst-1 -> 0.661088
A35: Effective Monthly Interest Rate (MIR) | C35: =IRR($G$41:$G$59) -> 0.065489269
A36: Total Payments | C36: =SUM($G$42:$G$59) -> -95003.016
A37: Total Interest | C37: =SUM($E$40:$E$59) -> 14049.306
A39: Inst. Period | B39: Due Date | C39: Gross Loan | D39: Principal | E39: Interest | F39: Other Charges | G39: Cash Flows | H39: Balance
C40: =C26 -> 80953.71 | H40: =C26 -> 80953.71
A41: 0 | F41: =C30 -> 8785.8383 | G41: =H40-F41 -> 72167.872 | H41: =C26 -> 80953.71
A42: 1 | B42: =IF(A42="","",IF($L$32=26,(A42-1)*14+Start_Payment,IF($L$32=52,(A42-1)*7+Start_Payment,DATE(YEAR(Start_Payment),MONTH(Start_Payment)+(A42-1)*$M$32,IF($L$32=24,IF((MOD(A42-1,2))=1,DAY(Start_Payment)+15,DAY(Start_Payment)),DAY(Start_Payment)))))) -> 46128 | D42: =IF(period2<>"",E42+G42,"") -> -8880.0898 | E42: =IF(upfront="YES",0,IF(period2<>"",IF(G42<0,(H41*$C$27),0),"")) -> 2995.2873 | G42: =IF(period2<>"",IF(ROUND(H41,5)>0,C$29,0),"") -> -11875.377 | H42: =IF(period2<>"",IF(ROUND(H40,5)>0,(D42-(-H41)),0),"") -> 72073.62
A43: =IF(A42<$C$28,A42+1,"") -> 2 | B43: =IF(A43="","",IF($L$32=26,(A43-1)*14+Start_Payment,IF($L$32=52,(A43-1)*7+Start_Payment,DATE(YEAR(Start_Payment),MONTH(Start_Payment)+(A43-1)*$M$32,IF($L$32=24,IF((MOD(A43-1,2))=1,DAY(Start_Payment)+15,DAY(Start_Payment)),DAY(Start_Payment)))))) -> 46158 | D43: =IF(period2<>"",E43+G43,"") -> -9208.6531 | E43: =IF(upfront="YES",0,IF(period2<>"",IF(G43<0,(H42*$C$27),0),"")) -> 2666.7239 | G43: =IF(period2<>"",IF(ROUND(H42,5)>0,C$29,0),"") -> -11875.377 | H43: =IF(period2<>"",IF(ROUND(H41,5)>0,(D43-(-H42)),0),"") -> 62864.967
A44: =IF(A43<$C$28,A43+1,"") -> 3 | B44: =IF(A44="","",IF($L$32=26,(A44-1)*14+Start_Payment,IF($L$32=52,(A44-1)*7+Start_Payment,DATE(YEAR(Start_Payment),MONTH(Start_Payment)+(A44-1)*$M$32,IF($L$32=24,IF((MOD(A44-1,2))=1,DAY(Start_Payment)+15,DAY(Start_Payment)),DAY(Start_Payment)))))) -> 46189 | D44: =IF(period2<>"",E44+G44,"") -> -9549.3733 | E44: =IF(upfront="YES",0,IF(period2<>"",IF(G44<0,(H43*$C$27),0),"")) -> 2326.0038 | G44: =IF(period2<>"",IF(ROUND(H43,5)>0,C$29,0),"") -> -11875.377 | H44: =IF(period2<>"",IF(ROUND(H42,5)>0,(D44-(-H43)),0),"") -> 53315.594
A45: =IF(A44<$C$28,A44+1,"") -> 4 | B45: =IF(A45="","",IF($L$32=26,(A45-1)*14+Start_Payment,IF($L$32=52,(A45-1)*7+Start_Payment,DATE(YEAR(Start_Payment),MONTH(Start_Payment)+(A45-1)*$M$32,IF($L$32=24,IF((MOD(A45-1,2))=1,DAY(Start_Payment)+15,DAY(Start_Payment)),DAY(Start_Payment)))))) -> 46219 | D45: =IF(period2<>"",E45+G45,"") -> -9902.7001 | E45: =IF(upfront="YES",0,IF(period2<>"",IF(G45<0,(H44*$C$27),0),"")) -> 1972.677 | G45: =IF(period2<>"",IF(ROUND(H44,5)>0,C$29,0),"") -> -11875.377 | H45: =IF(period2<>"",IF(ROUND(H43,5)>0,(D45-(-H44)),0),"") -> 43412.894
A46: =IF(A45<$C$28,A45+1,"") -> 5 | B46: =IF(A46="","",IF($L$32=26,(A46-1)*14+Start_Payment,IF($L$32=52,(A46-1)*7+Start_Payment,DATE(YEAR(Start_Payment),MONTH(Start_Payment)+(A46-1)*$M$32,IF($L$32=24,IF((MOD(A46-1,2))=1,DAY(Start_Payment)+15,DAY(Start_Payment)),DAY(Start_Payment)))))) -> 46250 | D46: =IF(period2<>"",E46+G46,"") -> -10269.1 | E46: =IF(upfront="YES",0,IF(period2<>"",IF(G46<0,(H45*$C$27),0),"")) -> 1606.2771 | G46: =IF(period2<>"",IF(ROUND(H45,5)>0,C$29,0),"") -> -11875.377 | H46: =IF(period2<>"",IF(ROUND(H44,5)>0,(D46-(-H45)),0),"") -> 33143.794
A47: =IF(A46<$C$28,A46+1,"") -> 6 | B47: =IF(A47="","",IF($L$32=26,(A47-1)*14+Start_Payment,IF($L$32=52,(A47-1)*7+Start_Payment,DATE(YEAR(Start_Payment),MONTH(Start_Payment)+(A47-1)*$M$32,IF($L$32=24,IF((MOD(A47-1,2))=1,DAY(Start_Payment)+15,DAY(Start_Payment)),DAY(Start_Payment)))))) -> 46281 | D47: =IF(period2<>"",E47+G47,"") -> -10649.057 | E47: =IF(upfront="YES",0,IF(period2<>"",IF(G47<0,(H46*$C$27),0),"")) -> 1226.3204 | G47: =IF(period2<>"",IF(ROUND(H46,5)>0,C$29,0),"") -> -11875.377 | H47: =IF(period2<>"",IF(ROUND(H45,5)>0,(D47-(-H46)),0),"") -> 22494.737
A48: =IF(A47<$C$28,A47+1,"") -> 7 | B48: =IF(A48="","",IF($L$32=26,(A48-1)*14+Start_Payment,IF($L$32=52,(A48-1)*7+Start_Payment,DATE(YEAR(Start_Payment),MONTH(Start_Payment)+(A48-1)*$M$32,IF($L$32=24,IF((MOD(A48-1,2))=1,DAY(Start_Payment)+15,DAY(Start_Payment)),DAY(Start_Payment)))))) -> 46311 | D48: =IF(period2<>"",E48+G48,"") -> -11043.072 | E48: =IF(upfront="YES",0,IF(period2<>"",IF(G48<0,(H47*$C$27),0),"")) -> 832.30528 | G48: =IF(period2<>"",IF(ROUND(H47,5)>0,C$29,0),"") -> -11875.377 | H48: =IF(period2<>"",IF(ROUND(H46,5)>0,(D48-(-H47)),0),"") -> 11451.665
A49: =IF(A48<$C$28,A48+1,"") -> 8 | B49: =IF(A49="","",IF($L$32=26,(A49-1)*14+Start_Payment,IF($L$32=52,(A49-1)*7+Start_Payment,DATE(YEAR(Start_Payment),MONTH(Start_Payment)+(A49-1)*$M$32,IF($L$32=24,IF((MOD(A49-1,2))=1,DAY(Start_Payment)+15,DAY(Start_Payment)),DAY(Start_Payment)))))) -> 46342 | D49: =IF(period2<>"",E49+G49,"") -> -11451.665 | E49: =IF(upfront="YES",0,IF(period2<>"",IF(G49<0,(H48*$C$27),0),"")) -> 423.71162 | G49: =IF(period2<>"",IF(ROUND(H48,5)>0,C$29,0),"") -> -11875.377 | H49: =IF(period2<>"",IF(ROUND(H47,5)>0,(D49-(-H48)),0),"") -> 9.094947e-12
A50: =IF(A49<$C$28,A49+1,"") | B50: =IF(A50="","",IF($L$32=26,(A50-1)*14+Start_Payment,IF($L$32=52,(A50-1)*7+Start_Payment,DATE(YEAR(Start_Payment),MONTH(Start_Payment)+(A50-1)*$M$32,IF($L$32=24,IF((MOD(A50-1,2))=1,DAY(Start_Payment)+15,DAY(Start_Payment)),DAY(Start_Payment)))))) | D50: =IF(period2<>"",E50+G50,"") | E50: =IF(upfront="YES",0,IF(period2<>"",IF(G50<0,(H49*$C$27),0),"")) | G50: =IF(period2<>"",IF(ROUND(H49,5)>0,C$29,0),"") | H50: =IF(period2<>"",IF(ROUND(H48,5)>0,(D50-(-H49)),0),"")
A51: =IF(A50<$C$28,A50+1,"") | B51: =IF(A51="","",IF($L$32=26,(A51-1)*14+Start_Payment,IF($L$32=52,(A51-1)*7+Start_Payment,DATE(YEAR(Start_Payment),MONTH(Start_Payment)+(A51-1)*$M$32,IF($L$32=24,IF((MOD(A51-1,2))=1,DAY(Start_Payment)+15,DAY(Start_Payment)),DAY(Start_Payment)))))) | D51: =IF(period2<>"",E51+G51,"") | E51: =IF(upfront="YES",0,IF(period2<>"",IF(G51<0,(H50*$C$27),0),"")) | G51: =IF(period2<>"",IF(ROUND(H50,5)>0,C$29,0),"") | H51: =IF(period2<>"",IF(ROUND(H49,5)>0,(D51-(-H50)),0),"")
A52: =IF(A51<$C$28,A51+1,"") | B52: =IF(A52="","",IF($L$32=26,(A52-1)*14+Start_Payment,IF($L$32=52,(A52-1)*7+Start_Payment,DATE(YEAR(Start_Payment),MONTH(Start_Payment)+(A52-1)*$M$32,IF($L$32=24,IF((MOD(A52-1,2))=1,DAY(Start_Payment)+15,DAY(Start_Payment)),DAY(Start_Payment)))))) | D52: =IF(period2<>"",E52+G52,"") | E52: =IF(upfront="YES",0,IF(period2<>"",IF(G52<0,(H51*$C$27),0),"")) | G52: =IF(period2<>"",IF(ROUND(H51,5)>0,C$29,0),"") | H52: =IF(period2<>"",IF(ROUND(H50,5)>0,(D52-(-H51)),0),"")
A53: =IF(A52<$C$28,A52+1,"") | B53: =IF(A53="","",IF($L$32=26,(A53-1)*14+Start_Payment,IF($L$32=52,(A53-1)*7+Start_Payment,DATE(YEAR(Start_Payment),MONTH(Start_Payment)+(A53-1)*$M$32,IF($L$32=24,IF((MOD(A53-1,2))=1,DAY(Start_Payment)+15,DAY(Start_Payment)),DAY(Start_Payment)))))) | D53: =IF(period2<>"",E53+G53,"") | E53: =IF(upfront="YES",0,IF(period2<>"",IF(G53<0,(H52*$C$27),0),"")) | G53: =IF(period2<>"",IF(ROUND(H52,5)>0,C$29,0),"") | H53: =IF(period2<>"",IF(ROUND(H51,5)>0,(D53-(-H52)),0),"")
A54: =IF(A53<$C$28,A53+1,"") | B54: =IF(A54="","",IF($L$32=26,(A54-1)*14+Start_Payment,IF($L$32=52,(A54-1)*7+Start_Payment,DATE(YEAR(Start_Payment),MONTH(Start_Payment)+(A54-1)*$M$32,IF($L$32=24,IF((MOD(A54-1,2))=1,DAY(Start_Payment)+15,DAY(Start_Payment)),DAY(Start_Payment)))))) | D54: =IF(period2<>"",E54+G54,"") | E54: =IF(upfront="YES",0,IF(period2<>"",IF(G54<0,(H53*$C$27),0),"")) | G54: =IF(period2<>"",IF(ROUND(H53,5)>0,C$29,0),"") | H54: =IF(period2<>"",IF(ROUND(H52,5)>0,(D54-(-H53)),0),"")
... A59: =IF(A58<$C$28,A58+1,"") | B59: =IF(A59="","",IF($L$32=26,(A59-1)*14+Start_Payment,IF($L$32=52,(A59-1)*7+Start_Payment,DATE(YEAR(Start_Payment),MONTH(Start_Payment)+(A59-1)*$M$32,IF($L$32=24,IF((MOD(A59-1,2))=1,DAY(Start_Payment)+15,DAY(Start_Payment)),DAY(Start_Payment)))))) | D59: =IF(period2<>"",E59+G59,"") | E59: =IF(upfront="YES",0,IF(period2<>"",IF(G59<0,(H58*$C$27),0),"")) | G59: =IF(period2<>"",IF(ROUND(H58,5)>0,C$29,0),"") | H59: =IF(period2<>"",IF(ROUND(H57,5)>0,(D59-(-H58)),0),"")
A61: ="Interest Rate of " & (Contractual_Rate*100) &"% is equivalent to the Add On Rate of " & ROUND((((((Total_InterestRate/C26)/Monthly_Inst))))*100,2) & "% per Month" -> Interest Rate of 3.7% is equivalent to the Add On Rate of 2.17% per Month
A63: Prepared / Verified by: | E63: Noted by:
A66: Released by: | E66: Received Copy:

Sheet Monthly -client copy
A4: =UPPER("Computation Sheet and Payment Schedule") -> COMPUTATION SHEET AND PAYMENT SCHEDULE
A5: NAME | C5: ADDRESS | E5: TYPE OF LOAN | H5: TERMS
A6: =IF(OR_NAME<>"",Client_Name &" or " & OR_NAME,Client_Name) -> ** or ** | C6: =PROPER('Master data Input'!C8) -> ** | F6: =Type_of_Loan&TEXT(IF(Express="YES","-EXPRESS",""),"") -> SML | H6: In months | I6: =Term_masterdatainput -> 8 | J6: =Terms -> 8
H7: from | I7: to
H8: =Date_Released -> 46083 | I8: =MaturityDate_data_input -> 46342 | M8: ='Master data Input'!F30 -> 46342 | N8: end of term | O8: =I6 -> 8
F9: # of payments | H9: =Number_of_Amortization -> 8
M10: =IF(U23<H8,H8,U23) -> 46098
A11: COMPUTATION OF NET PROCEEDS
W12: 7
A13: Principal/ Amount Financed | F13: ='computation sheet'!D5 -> 80953.71
A14: Less: Deduction
A15: Interest | G15: New | I15: =Renewal -> No
B16: =Interest -> 0.03 | C16: ="from"&TEXT(Date_Released," mm/dd/yyyy")&" to "&TEXT(Date_released2," mm/dd/yyyy") -> from 03/02/2026 to 03/17/2026 | E16: ='computation sheet'!C9 -> 1214.31 | G16: Renewal Nth loan | I16: ='Master data Input'!F18 -> 0 | J16: =E16+C41/A41-(360/DATEDIF(H8,I8,"d")) -> 1213.0936 | L16: =DATEDIF(H8,B46,"d") -> 45 | M16: days from loan release and 1st payment
A17: Processing Fee | C17: =Processing_Fee_in_Percentage -> 0.075 | E17: =Principal_Amount*Percent_processingfee -> 6071.5283 | G17: Installment Type | I17: =Installment_Type -> Monthly | L17: =DATEDIF(H8,M10,"D") -> 15
A18: Account Management Fee | E18: ='computation sheet'!C11 -> 0
A19: Doc fee | E19: =Docfee_Yes_or_No -> 500
A20: Notarial fee | E20: =Notarial_Fee -> 500 | G20: Check No.
A21: ='Master data Input'!B42 -> MLRI -Insurance | E21: ='computation sheet'!C14 -> 0
A22: ='Master data Input'!B45 -> Miscellaneous | E22: ='Master data Input'!C45 -> 500 | L22: =DATEDIF(M10,M8,"D") -> 244
A23: Total Finance charge | E23: =SUM(E16:E22) -> 8785.8383 | G23: PN no. | H23: ="PN-"&TEXT('Master data Input'!F10,"0000- ")&TEXT(" "," ")&'Master data Input'!C14 -> PN-. SML | L23: =DATEDIF(H8,M8,"D") -> 259 | U23: =DATE(YEAR(B46),MONTH(B46),DAY(B46)-30) -> 46098
A25: Others: | G25: Branch: | H25: ='Master data Input'!F38 -> 0 | P25: =TEXT($L$16,"0")&"/"&TEXT($L$17,"0")&"/"&TEXT($L$22,"0")&"/"&TEXT($L$23,"0") -> 45/15/244/259 | X25: =45000*0.15*(305/360) -> 5718.75
A26: =Cash_Advance -> Cash Advance | E26: =Advanced_Payment -> 0 | L26: =DATEDIF(M10,B46,"d") -> 30
A27: ='Master data Input'!B12 -> Outstanding Balance from previous loan | E27: =Outstanding_Balance_from_previous_loan -> 0
F28: =Total_Finance_Charge+SUM($E$26:$E$28) -> 8785.8383
G29: MODE OF PAYMENT: | I29: ='Master data Input'!F42 -> 0
A30: Net Proceeds | F30: =Principal_Amount-Total_Deduction -> 72167.872
M31: IF('Master data Input'!B35="YES",ROUNDUP(F16*0.0015,0),"0") | U31: DATEDIF(H11,I11,"D")
A32: % of Finance charges to Total Amount Financed | F32: =Total_Finance_Charge/Principal_Amount -> 0.10852916
A33: Contractual Interest Rate per Month | F33: =Contractual_Rate -> 0.037
A34: Equivalent Add-on Interest Rate per Month | F34: =Interest -> 0.03
A35: Effective Annual Rate (EIR) | F35: =EIR -> 0.661088 | M35: IF(1200>O27,1200,O27)
A36: Effective Monthly Interest Rate (MIR) | F36: =MIR -> 0.065489269 | G36: Release Date: | I36: =Date_Released -> 46083
G37: Agent: | H37: =UPPER(Agents)
A38: SCHEDULE OF PAYMENT
N39: =C41+E16 -> 15263.616 | O39: 11667
A40: Principal / Amount of Loan | C40: Interest Due on Loans | E40: Total Amount Payable | X40: =DATE(YEAR(U17),MONTH(U17)+1,DAY(U17)) -> 31
A41: =Principal_Amount -> 80953.71 | C41: ='computation sheet'!C37 -> 14049.306 | E41: =IF(Type_of_Loan="BL-SA",Amount_of_Loan,Loan_Amount+Total_UII) -> 95003.016 | J41: =DATE(YEAR($B$46),MONTH($B$46)+($H$9-1),DAY($B$46)) -> 46342 | K41: w/out adjustment
A43: Period | B43: Due Date | C43: Gross Loan | D43: Amortization | E43: Interest | F43: Principal | G43: Other Charges | I43: Balance
C44: =Loan_Amount -> 80953.71 | I44: =Loan_Amount -> 80953.71
A45: 0 | G45: ='Monthly -client copy'!Total_Deduction -> 8785.8383 | I45: =Loan_Amount -> 80953.71
A46: 1 | B46: =IF(A46="","",IF('computation sheet'!$L$32=26,(A46-1)*14+Start_Payment,IF('computation sheet'!$L$32=52,(A46-1)*7+Start_Payment,DATE(YEAR(Start_Payment),MONTH(Start_Payment)+(A46-1)*'computation sheet'!$M$32,IF('computation sheet'!$L$32=24,IF((MOD(A46-1,2))=1,DAY(Start_Payment)+15,DAY(Start_Payment)),DAY(Start_Payment)))))) -> 46128 | D46: =IF(PERIOD<>"",PMT($F$33,$A$67,-Principal_Amount),"") -> 11875.377 | E46: ='computation sheet'!E42 -> 2995.2873 | F46: =IF(NOT(A46=AA24),D46-E46,"") -> 8880.0898 | I46: =IF(PERIOD<>"",(I45-F46),"") -> 72073.62 | K46: =IF(WEEKDAY(L46,2)=1,"Monday",IF(WEEKDAY(L46,2)=2,"Tuesday",IF(WEEKDAY(L46,2)=3,"Wednesday",IF(WEEKDAY(L46,2)=4,"Thursday",IF(WEEKDAY(L46,2)=5,"Friday",IF(WEEKDAY(L46,2)=6,"Saturday",IF(WEEKDAY(L46,2)=7,"Sunday"))))))) -> Thursday | L46: ='Master data Input'!C30 -> 46128
A47: =IF(A46<$H$9,A46+1,"") -> 2 | B47: =IF(A47="","",IF('computation sheet'!$L$32=26,(A47-1)*14+Start_Payment,IF('computation sheet'!$L$32=52,(A47-1)*7+Start_Payment,DATE(YEAR(Start_Payment),MONTH(Start_Payment)+(A47-1)*'computation sheet'!$M$32,IF('computation sheet'!$L$32=24,IF((MOD(A47-1,2))=1,DAY(Start_Payment)+15,DAY(Start_Payment)),DAY(Start_Payment)))))) -> 46158 | D47: =IF(PERIOD<>"",PMT($F$33,$A$67,-Principal_Amount),"") -> 11875.377 | E47: ='computation sheet'!E43 -> 2666.7239 | F47: =IF(NOT(A47=AA27),D47-E47,"") -> 9208.6531 | I47: =IF(PERIOD<>"",(I46-F47),"") -> 62864.967 | K47: =IF(WEEKDAY(L47,2)=1,"Monday",IF(WEEKDAY(L47,2)=2,"Tuesday",IF(WEEKDAY(L47,2)=3,"Wednesday",IF(WEEKDAY(L47,2)=4,"Thursday",IF(WEEKDAY(L47,2)=5,"Friday",IF(WEEKDAY(L47,2)=6,"Saturday",IF(WEEKDAY(L47,2)=7,"Sunday"))))))) -> Saturday | L47: =IF(PERIOD<>"",IF(DATE(YEAR(L46),MONTH(L46),DAY(L46))<=$J$41,DATE(YEAR(L46),MONTH(L46)+1,DAY(L46)),""),"") -> 46158
A48: =IF(A47<$H$9,A47+1,"") -> 3 | B48: =IF(A48="","",IF('computation sheet'!$L$32=26,(A48-1)*14+Start_Payment,IF('computation sheet'!$L$32=52,(A48-1)*7+Start_Payment,DATE(YEAR(Start_Payment),MONTH(Start_Payment)+(A48-1)*'computation sheet'!$M$32,IF('computation sheet'!$L$32=24,IF((MOD(A48-1,2))=1,DAY(Start_Payment)+15,DAY(Start_Payment)),DAY(Start_Payment)))))) -> 46189 | D48: =IF(PERIOD<>"",PMT($F$33,$A$67,-Principal_Amount),"") -> 11875.377 | E48: ='computation sheet'!E44 -> 2326.0038 | F48: =IF(NOT(A48=AA29),D48-E48,"") -> 9549.3733 | I48: =IF(PERIOD<>"",(I47-F48),"") -> 53315.594 | K48: =IF(WEEKDAY(L48,2)=1,"Monday",IF(WEEKDAY(L48,2)=2,"Tuesday",IF(WEEKDAY(L48,2)=3,"Wednesday",IF(WEEKDAY(L48,2)=4,"Thursday",IF(WEEKDAY(L48,2)=5,"Friday",IF(WEEKDAY(L48,2)=6,"Saturday",IF(WEEKDAY(L48,2)=7,"Sunday"))))))) -> Tuesday | L48: =IF(PERIOD<>"",IF(DATE(YEAR(L47),MONTH(L47),DAY(L47))<=$J$41,DATE(YEAR(L47),MONTH(L47)+1,DAY(L47)),""),"") -> 46189
A49: =IF(A48<$H$9,A48+1,"") -> 4 | B49: =IF(A49="","",IF('computation sheet'!$L$32=26,(A49-1)*14+Start_Payment,IF('computation sheet'!$L$32=52,(A49-1)*7+Start_Payment,DATE(YEAR(Start_Payment),MONTH(Start_Payment)+(A49-1)*'computation sheet'!$M$32,IF('computation sheet'!$L$32=24,IF((MOD(A49-1,2))=1,DAY(Start_Payment)+15,DAY(Start_Payment)),DAY(Start_Payment)))))) -> 46219 | D49: =IF(PERIOD<>"",PMT($F$33,$A$67,-Principal_Amount),"") -> 11875.377 | E49: ='computation sheet'!E45 -> 1972.677 | F49: =IF(NOT(A49=AA30),D49-E49,"") -> 9902.7001 | I49: =IF(PERIOD<>"",(I48-F49),"") -> 43412.894 | K49: =IF(WEEKDAY(L49,2)=1,"Monday",IF(WEEKDAY(L49,2)=2,"Tuesday",IF(WEEKDAY(L49,2)=3,"Wednesday",IF(WEEKDAY(L49,2)=4,"Thursday",IF(WEEKDAY(L49,2)=5,"Friday",IF(WEEKDAY(L49,2)=6,"Saturday",IF(WEEKDAY(L49,2)=7,"Sunday"))))))) -> Thursday | L49: =IF(PERIOD<>"",IF(DATE(YEAR(L48),MONTH(L48),DAY(L48))<=$J$41,DATE(YEAR(L48),MONTH(L48)+1,DAY(L48)),""),"") -> 46219
A50: =IF(A49<$H$9,A49+1,"") -> 5 | B50: =IF(A50="","",IF('computation sheet'!$L$32=26,(A50-1)*14+Start_Payment,IF('computation sheet'!$L$32=52,(A50-1)*7+Start_Payment,DATE(YEAR(Start_Payment),MONTH(Start_Payment)+(A50-1)*'computation sheet'!$M$32,IF('computation sheet'!$L$32=24,IF((MOD(A50-1,2))=1,DAY(Start_Payment)+15,DAY(Start_Payment)),DAY(Start_Payment)))))) -> 46250 | D50: =IF(PERIOD<>"",PMT($F$33,$A$67,-Principal_Amount),"") -> 11875.377 | E50: ='computation sheet'!E46 -> 1606.2771 | F50: =IF(NOT(A50=AA31),D50-E50,"") -> 10269.1 | I50: =IF(PERIOD<>"",(I49-F50),"") -> 33143.794 | K50: =IF(WEEKDAY(L50,2)=1,"Monday",IF(WEEKDAY(L50,2)=2,"Tuesday",IF(WEEKDAY(L50,2)=3,"Wednesday",IF(WEEKDAY(L50,2)=4,"Thursday",IF(WEEKDAY(L50,2)=5,"Friday",IF(WEEKDAY(L50,2)=6,"Saturday",IF(WEEKDAY(L50,2)=7,"Sunday"))))))) -> Sunday | L50: =IF(PERIOD<>"",IF(DATE(YEAR(L49),MONTH(L49),DAY(L49))<=$J$41,DATE(YEAR(L49),MONTH(L49)+1,DAY(L49)),""),"") -> 46250
A51: =IF(A50<$H$9,A50+1,"") -> 6 | B51: =IF(A51="","",IF('computation sheet'!$L$32=26,(A51-1)*14+Start_Payment,IF('computation sheet'!$L$32=52,(A51-1)*7+Start_Payment,DATE(YEAR(Start_Payment),MONTH(Start_Payment)+(A51-1)*'computation sheet'!$M$32,IF('computation sheet'!$L$32=24,IF((MOD(A51-1,2))=1,DAY(Start_Payment)+15,DAY(Start_Payment)),DAY(Start_Payment)))))) -> 46281 | D51: =IF(PERIOD<>"",PMT($F$33,$A$67,-Principal_Amount),"") -> 11875.377 | E51: ='computation sheet'!E47 -> 1226.3204 | F51: =IF(NOT(A51=AA32),D51-E51,"") -> 10649.057 | I51: =IF(PERIOD<>"",(I50-F51),"") -> 22494.737 | K51: =IF(WEEKDAY(L51,2)=1,"Monday",IF(WEEKDAY(L51,2)=2,"Tuesday",IF(WEEKDAY(L51,2)=3,"Wednesday",IF(WEEKDAY(L51,2)=4,"Thursday",IF(WEEKDAY(L51,2)=5,"Friday",IF(WEEKDAY(L51,2)=6,"Saturday",IF(WEEKDAY(L51,2)=7,"Sunday"))))))) -> Wednesday | L51: =IF(PERIOD<>"",IF(DATE(YEAR(L50),MONTH(L50),DAY(L50))<=$J$41,DATE(YEAR(L50),MONTH(L50)+1,DAY(L50)),""),"") -> 46281
A52: =IF(A51<$H$9,A51+1,"") -> 7 | B52: =IF(A52="","",IF('computation sheet'!$L$32=26,(A52-1)*14+Start_Payment,IF('computation sheet'!$L$32=52,(A52-1)*7+Start_Payment,DATE(YEAR(Start_Payment),MONTH(Start_Payment)+(A52-1)*'computation sheet'!$M$32,IF('computation sheet'!$L$32=24,IF((MOD(A52-1,2))=1,DAY(Start_Payment)+15,DAY(Start_Payment)),DAY(Start_Payment)))))) -> 46311 | D52: =IF(PERIOD<>"",PMT($F$33,$A$67,-Principal_Amount),"") -> 11875.377 | E52: ='computation sheet'!E48 -> 832.30528 | F52: =IF(NOT(A52=AA35),D52-E52,"") -> 11043.072 | I52: =IF(PERIOD<>"",(I51-F52),"") -> 11451.665 | K52: =IF(WEEKDAY(L52,2)=1,"Monday",IF(WEEKDAY(L52,2)=2,"Tuesday",IF(WEEKDAY(L52,2)=3,"Wednesday",IF(WEEKDAY(L52,2)=4,"Thursday",IF(WEEKDAY(L52,2)=5,"Friday",IF(WEEKDAY(L52,2)=6,"Saturday",IF(WEEKDAY(L52,2)=7,"Sunday"))))))) -> Friday | L52: =IF(PERIOD<>"",IF(DATE(YEAR(L51),MONTH(L51),DAY(L51))<=$J$41,DATE(YEAR(L51),MONTH(L51)+1,DAY(L51)),""),"") -> 46311
A53: =IF(A52<$H$9,A52+1,"") -> 8 | B53: =IF(A53="","",IF('computation sheet'!$L$32=26,(A53-1)*14+Start_Payment,IF('computation sheet'!$L$32=52,(A53-1)*7+Start_Payment,DATE(YEAR(Start_Payment),MONTH(Start_Payment)+(A53-1)*'computation sheet'!$M$32,IF('computation sheet'!$L$32=24,IF((MOD(A53-1,2))=1,DAY(Start_Payment)+15,DAY(Start_Payment)),DAY(Start_Payment)))))) -> 46342 | D53: =IF(PERIOD<>"",PMT($F$33,$A$67,-Principal_Amount),"") -> 11875.377 | E53: ='computation sheet'!E49 -> 423.71162 | F53: =IF(NOT(A53=AA36),D53-E53,"") -> 11451.665 | I53: =IF(PERIOD<>"",(I52-F53),"") -> 9.094947e-12 | K53: =IF(WEEKDAY(L53,2)=1,"Monday",IF(WEEKDAY(L53,2)=2,"Tuesday",IF(WEEKDAY(L53,2)=3,"Wednesday",IF(WEEKDAY(L53,2)=4,"Thursday",IF(WEEKDAY(L53,2)=5,"Friday",IF(WEEKDAY(L53,2)=6,"Saturday",IF(WEEKDAY(L53,2)=7,"Sunday"))))))) -> Monday | L53: =IF(PERIOD<>"",IF(DATE(YEAR(L52),MONTH(L52),DAY(L52))<=$J$41,DATE(YEAR(L52),MONTH(L52)+1,DAY(L52)),""),"") -> 46342
A54: =IF(A53<$H$9,A53+1,"") | B54: =IF(A54="","",IF('computation sheet'!$L$32=26,(A54-1)*14+Start_Payment,IF('computation sheet'!$L$32=52,(A54-1)*7+Start_Payment,DATE(YEAR(Start_Payment),MONTH(Start_Payment)+(A54-1)*'computation sheet'!$M$32,IF('computation sheet'!$L$32=24,IF((MOD(A54-1,2))=1,DAY(Start_Payment)+15,DAY(Start_Payment)),DAY(Start_Payment)))))) | D54: =IF(PERIOD<>"",PMT($F$33,$A$67,-Principal_Amount),"") | E54: ='computation sheet'!E50 | F54: =IF(NOT(A54=AA37),D54-E54,"") | I54: =IF(PERIOD<>"",(I53-F54),"") | K54: =IF(WEEKDAY(L54,2)=1,"Monday",IF(WEEKDAY(L54,2)=2,"Tuesday",IF(WEEKDAY(L54,2)=3,"Wednesday",IF(WEEKDAY(L54,2)=4,"Thursday",IF(WEEKDAY(L54,2)=5,"Friday",IF(WEEKDAY(L54,2)=6,"Saturday",IF(WEEKDAY(L54,2)=7,"Sunday"))))))) -> #VALUE! | L54: =IF(PERIOD<>"",IF(DATE(YEAR(L53),MONTH(L53),DAY(L53))<=$J$41,DATE(YEAR(L53),MONTH(L53)+1,DAY(L53)),""),"")
A55: =IF(A54<$H$9,A54+1,"") | B55: =IF(A55="","",IF('computation sheet'!$L$32=26,(A55-1)*14+Start_Payment,IF('computation sheet'!$L$32=52,(A55-1)*7+Start_Payment,DATE(YEAR(Start_Payment),MONTH(Start_Payment)+(A55-1)*'computation sheet'!$M$32,IF('computation sheet'!$L$32=24,IF((MOD(A55-1,2))=1,DAY(Start_Payment)+15,DAY(Start_Payment)),DAY(Start_Payment)))))) | D55: =IF(PERIOD<>"",PMT($F$33,$A$67,-Principal_Amount),"") | E55: ='computation sheet'!E51 | F55: =IF(NOT(A55=AA38),D55-E55,"") | I55: =IF(PERIOD<>"",(I54-F55),"") | K55: =IF(WEEKDAY(L55,2)=1,"Monday",IF(WEEKDAY(L55,2)=2,"Tuesday",IF(WEEKDAY(L55,2)=3,"Wednesday",IF(WEEKDAY(L55,2)=4,"Thursday",IF(WEEKDAY(L55,2)=5,"Friday",IF(WEEKDAY(L55,2)=6,"Saturday",IF(WEEKDAY(L55,2)=7,"Sunday"))))))) -> #VALUE! | L55: =IF(PERIOD<>"",IF(DATE(YEAR(L54),MONTH(L54),DAY(L54))<=$J$41,DATE(YEAR(L54),MONTH(L54)+1,DAY(L54)),""),"")
A56: =IF(A55<$H$9,A55+1,"") | B56: =IF(A56="","",IF('computation sheet'!$L$32=26,(A56-1)*14+Start_Payment,IF('computation sheet'!$L$32=52,(A56-1)*7+Start_Payment,DATE(YEAR(Start_Payment),MONTH(Start_Payment)+(A56-1)*'computation sheet'!$M$32,IF('computation sheet'!$L$32=24,IF((MOD(A56-1,2))=1,DAY(Start_Payment)+15,DAY(Start_Payment)),DAY(Start_Payment)))))) | D56: =IF(PERIOD<>"",PMT($F$33,$A$67,-Principal_Amount),"") | E56: ='computation sheet'!E52 | F56: =IF(NOT(A56=AA39),D56-E56,"") | I56: =IF(PERIOD<>"",(I55-F56),"") | K56: =IF(WEEKDAY(L56,2)=1,"Monday",IF(WEEKDAY(L56,2)=2,"Tuesday",IF(WEEKDAY(L56,2)=3,"Wednesday",IF(WEEKDAY(L56,2)=4,"Thursday",IF(WEEKDAY(L56,2)=5,"Friday",IF(WEEKDAY(L56,2)=6,"Saturday",IF(WEEKDAY(L56,2)=7,"Sunday"))))))) -> #VALUE! | L56: =IF(PERIOD<>"",IF(DATE(YEAR(L55),MONTH(L55),DAY(L55))<=$J$41,DATE(YEAR(L55),MONTH(L55)+1,DAY(L55)),""),"")
A57: =IF(A56<$H$9,A56+1,"") | B57: =IF(A57="","",IF('computation sheet'!$L$32=26,(A57-1)*14+Start_Payment,IF('computation sheet'!$L$32=52,(A57-1)*7+Start_Payment,DATE(YEAR(Start_Payment),MONTH(Start_Payment)+(A57-1)*'computation sheet'!$M$32,IF('computation sheet'!$L$32=24,IF((MOD(A57-1,2))=1,DAY(Start_Payment)+15,DAY(Start_Payment)),DAY(Start_Payment)))))) | D57: =IF(PERIOD<>"",PMT($F$33,$A$67,-Principal_Amount),"") | E57: ='computation sheet'!E53 | F57: =IF(NOT(A57=AA40),D57-E57,"") | I57: =IF(PERIOD<>"",(I56-F57),"") | K57: =IF(WEEKDAY(L57,2)=1,"Monday",IF(WEEKDAY(L57,2)=2,"Tuesday",IF(WEEKDAY(L57,2)=3,"Wednesday",IF(WEEKDAY(L57,2)=4,"Thursday",IF(WEEKDAY(L57,2)=5,"Friday",IF(WEEKDAY(L57,2)=6,"Saturday",IF(WEEKDAY(L57,2)=7,"Sunday"))))))) -> #VALUE! | L57: =IF(PERIOD<>"",IF(DATE(YEAR(L56),MONTH(L56),DAY(L56))<=$J$41,DATE(YEAR(L56),MONTH(L56)+1,DAY(L56)),""),"")
A58: =IF(A57<$H$9,A57+1,"") | B58: =IF(A58="","",IF('computation sheet'!$L$32=26,(A58-1)*14+Start_Payment,IF('computation sheet'!$L$32=52,(A58-1)*7+Start_Payment,DATE(YEAR(Start_Payment),MONTH(Start_Payment)+(A58-1)*'computation sheet'!$M$32,IF('computation sheet'!$L$32=24,IF((MOD(A58-1,2))=1,DAY(Start_Payment)+15,DAY(Start_Payment)),DAY(Start_Payment)))))) | D58: =IF(PERIOD<>"",PMT($F$33,$A$67,-Principal_Amount),"") | E58: ='computation sheet'!E54 | F58: =IF(NOT(A58=AA41),D58-E58,"") | I58: =IF(PERIOD<>"",(I57-F58),"") | K58: =IF(WEEKDAY(L58,2)=1,"Monday",IF(WEEKDAY(L58,2)=2,"Tuesday",IF(WEEKDAY(L58,2)=3,"Wednesday",IF(WEEKDAY(L58,2)=4,"Thursday",IF(WEEKDAY(L58,2)=5,"Friday",IF(WEEKDAY(L58,2)=6,"Saturday",IF(WEEKDAY(L58,2)=7,"Sunday"))))))) -> #VALUE! | L58: =IF(PERIOD<>"",IF(DATE(YEAR(L57),MONTH(L57),DAY(L57))<=$J$41,DATE(YEAR(L57),MONTH(L57)+1,DAY(L57)),""),"")
A59: =IF(A58<$H$9,A58+1,"") | B59: =IF(A59="","",IF('computation sheet'!$L$32=26,(A59-1)*14+Start_Payment,IF('computation sheet'!$L$32=52,(A59-1)*7+Start_Payment,DATE(YEAR(Start_Payment),MONTH(Start_Payment)+(A59-1)*'computation sheet'!$M$32,IF('computation sheet'!$L$32=24,IF((MOD(A59-1,2))=1,DAY(Start_Payment)+15,DAY(Start_Payment)),DAY(Start_Payment)))))) | D59: =IF(PERIOD<>"",PMT($F$33,$A$67,-Principal_Amount),"") | E59: ='computation sheet'!E55 | F59: =IF(NOT(A59=AA42),D59-E59,"") | I59: =IF(PERIOD<>"",(I58-F59),"") | K59: =IF(WEEKDAY(L59,2)=1,"Monday",IF(WEEKDAY(L59,2)=2,"Tuesday",IF(WEEKDAY(L59,2)=3,"Wednesday",IF(WEEKDAY(L59,2)=4,"Thursday",IF(WEEKDAY(L59,2)=5,"Friday",IF(WEEKDAY(L59,2)=6,"Saturday",IF(WEEKDAY(L59,2)=7,"Sunday"))))))) -> #VALUE! | L59: =IF(PERIOD<>"",IF(DATE(YEAR(L58),MONTH(L58),DAY(L58))<=$J$41,DATE(YEAR(L58),MONTH(L58)+1,DAY(L58)),""),"")
A60: =IF(A59<$H$9,A59+1,"") | B60: =IF(A60="","",IF('computation sheet'!$L$32=26,(A60-1)*14+Start_Payment,IF('computation sheet'!$L$32=52,(A60-1)*7+Start_Payment,DATE(YEAR(Start_Payment),MONTH(Start_Payment)+(A60-1)*'computation sheet'!$M$32,IF('computation sheet'!$L$32=24,IF((MOD(A60-1,2))=1,DAY(Start_Payment)+15,DAY(Start_Payment)),DAY(Start_Payment)))))) | D60: =IF(PERIOD<>"",PMT($F$33,$A$67,-Principal_Amount),"") | E60: ='computation sheet'!E56 | F60: =IF(NOT(A60=AA43),D60-E60,"") | I60: =IF(PERIOD<>"",(I59-F60),"")
A61: =IF(A60<$H$9,A60+1,"") | B61: =IF(A61="","",IF('computation sheet'!$L$32=26,(A61-1)*14+Start_Payment,IF('computation sheet'!$L$32=52,(A61-1)*7+Start_Payment,DATE(YEAR(Start_Payment),MONTH(Start_Payment)+(A61-1)*'computation sheet'!$M$32,IF('computation sheet'!$L$32=24,IF((MOD(A61-1,2))=1,DAY(Start_Payment)+15,DAY(Start_Payment)),DAY(Start_Payment)))))) | D61: =IF(PERIOD<>"",PMT($F$33,$A$67,-Principal_Amount),"") | E61: ='computation sheet'!E57 | F61: =IF(NOT(A61=AA44),D61-E61,"") | I61: =IF(PERIOD<>"",(I60-F61),"")
A62: =IF(A61<$H$9,A61+1,"") | B62: =IF(A62="","",IF('computation sheet'!$L$32=26,(A62-1)*14+Start_Payment,IF('computation sheet'!$L$32=52,(A62-1)*7+Start_Payment,DATE(YEAR(Start_Payment),MONTH(Start_Payment)+(A62-1)*'computation sheet'!$M$32,IF('computation sheet'!$L$32=24,IF((MOD(A62-1,2))=1,DAY(Start_Payment)+15,DAY(Start_Payment)),DAY(Start_Payment)))))) | D62: =IF(PERIOD<>"",PMT($F$33,$A$67,-Principal_Amount),"") | E62: ='computation sheet'!E58 | F62: =IF(NOT(A62=AA45),D62-E62,"") | I62: =IF(PERIOD<>"",(I61-F62),"")
A63: =IF(A62<$H$9,A62+1,"") | B63: =IF(A63="","",IF('computation sheet'!$L$32=26,(A63-1)*14+Start_Payment,IF('computation sheet'!$L$32=52,(A63-1)*7+Start_Payment,DATE(YEAR(Start_Payment),MONTH(Start_Payment)+(A63-1)*'computation sheet'!$M$32,IF('computation sheet'!$L$32=24,IF((MOD(A63-1,2))=1,DAY(Start_Payment)+15,DAY(Start_Payment)),DAY(Start_Payment)))))) | D63: =IF(PERIOD<>"",PMT($F$33,$A$67,-Principal_Amount),"") | E63: ='computation sheet'!E59 | F63: =IF(NOT(A63=AA46),D63-E63,"") | I63: =IF(PERIOD<>"",(I62-F63),"")
K66: =IF(WEEKDAY(L66,2)=1,"Monday",IF(WEEKDAY(L66,2)=2,"Tuesday",IF(WEEKDAY(L66,2)=3,"Wednesday",IF(WEEKDAY(L66,2)=4,"Thursday",IF(WEEKDAY(L66,2)=5,"Friday",IF(WEEKDAY(L66,2)=6,"Saturday",IF(WEEKDAY(L66,2)=7,"Sunday"))))))) -> #VALUE! | L66: =IF(PERIOD<>"",IF(DATE(YEAR(L59),MONTH(L59),DAY(L59))<=$J$41,DATE(YEAR(L59),MONTH(L59)+1,DAY(L59)),""),"")
A67: =H9 -> 8 | D67: =SUM(D46:D66) -> 95003.016 | E67: =SUM(E46:E66) -> 14049.306 | F67: =SUM(F46:F66) -> 80953.71
A69: ="Interest Rate of " & (Contractual_Rate*100) &"% is equivalent to the Add On Rate of " & ROUND((((((Total_InterestRate/Principal_Amount)/Monthly_Inst))))*100,2) & "% per Month" -> Interest Rate of 3.7% is equivalent to the Add On Rate of 2.17% per Month
A71: Prepared / Verified by: | E71: Noted by:
A74: Released by: | E74: Received Copy:
A78: IMPORTANT REMINDERS:

Sheet Semi Monthly SL
A3: COMPUTATION OF NET PROCEEDS
E4: from | F4: =Date_Released_SM -> 43265 | G4: to | H4: =Maturitydate_SM -> 43651
A5: Loan Amount | D5: =IF(get_loan_amount="NET AMOUNT",get_gross_amount,Loan_Amount) -> 80953.71 | E5: Terms in Month: | F5: =DATEDIF(Date_Released,Maturitydate_SM,"d")/30 -> #NUM! | G5: No. of Payments: | H5: =Monthly_Inst -> 12
A7: Less: Deduction: | E7: New | G7: =IF(G8>=0,"NO", "YES") -> NO
A8: Loan Term Adjustment | E8: Renewal Nth loan | G8: =Renewal -> No | K8: =IF(Type_of_Loan="BL-SA",ROUND(Principal_Amount*(((Total_InterestRate/Loan_Amount)/Monthly_Inst)/30)*DATEDIF(Date_Released,MaturityDate_data_input,"d"),0),ROUND(Principal_Amount*(((Total_InterestRate/Loan_Amount)/Monthly_Inst)/30)*DATEDIF(Date_Released,Date_released2,"d"),0)) -> 0 | L8: loan term adjustment | N8: =ROUND(((((Total_InterestRate/Principal_Amount)/Monthly_Inst)*100)),2)& "% from"&TEXT(Date_Released," mm/dd/yyyy")&" to "&TEXT(Date_released2," mm/dd/yyyy") -> 1.45% from 03/02/2026 to 03/02/2026
A9: =(ROUND(Interest,3)*100&"% from"&TEXT(Date_Released," mm/dd/yyyy")&" to "&TEXT(Date_released2," mm/dd/yyyy")) -> 3% from 03/02/2026 to 03/02/2026 | C9: =IF(Type_of_Loan="SL",0,ROUND(Principal_Amount*(Interest/30)*DATEDIF(Date_Released,Date_released2,"d"),2)) -> 0 | K9: =IF(Type_of_Loan="BL-SA",ROUND(Principal_Amount*(Interest/30)*DATEDIF(Date_Released,MaturityDate_data_input,"d"),0),ROUND(Principal_Amount*(Interest/30)*DATEDIF(Date_Released,Date_released2,"d"),0)) -> 0 | L9: Advance Interest | N9: =(Interest*100) & "% from"&TEXT(Date_Released," mm/dd/yyyy")&" to "&TEXT(Date_released2," mm/dd/yyyy") -> 3% from 03/02/2026 to 03/02/2026
A10: Processing Fee | B10: =Processing_Fee_in_Percentage -> 0.075 | C10: =D5*B10 -> 6071.5283 | E10: Installment Type | G10: Semi Monthly
A11: Account Management Fee | C11: =Account_Management_fee -> Auto compute** | E11: PN. No. | G11: =PN_no. -> .
A12: Doc Fee | C12: =Docfee_Yes_or_No -> 500
A13: Notarial Fee | C13: =Notarial_Fee -> 500 | E13: MODE OF PAYMENT: | K13: =Total_UII -> 14049.306 | L13: =Interest -> 0.03 | M13: UII (old computation sheet)
A14: ='Master data Input'!B42 -> MLRI -Insurance | C14: =Insurance -> Auto compute** | G14: ='Master data Input'!F42 -> 0 | K14: =Total_InterestRate -> 14049.306 | L14: =((((Total_InterestRate/C26)/Monthly_Inst))) -> 0.014462284 | M14: Total Interest (deminishing)
A15: =Cash_Advance -> Cash Advance | C15: =Advanced_Payment -> 0
A16: ='Master data Input'!B45 -> Miscellaneous | C16: ='Master data Input'!C45 -> 500 | E16: Branch: | G16: ='Master data Input'!F38 -> 0 | K16: =K13-K14 -> 0 | L16: difference
A17: Previous Loan Balance | C17: =Outstanding_Balance_from_previous_loan -> 0
A18: Total Deduction | D18: =SUM(C9:C17) -> 7571.5283 | E18: Release Date: | G18: =Date_Released -> 46083
A19: Net Proceeds | D19: =D5-D18 -> 73382.182 | E19: Agent: | F19: =Agents -> 0
D22: Name | K22: Payment Frequency Options
A23: Loan Information | D23: =IF(OR_NAME<>"",Client_Name &" or " & OR_NAME,Client_Name) -> ** or ** | K23: Frequency | L23: Payments/yr | M23: Months
K24: Annual | L24: 1 | M24: 12
A25: Loan Type | C25: =Type_of_Loan -> SML | K25: Semi-Annual | L25: 2 | M25: 6
A26: Principal Amount | C26: =D5 -> 80953.71 | D26: Address | K26: Quarterly | L26: 4 | M26: 3
A27: Contractual Rate (Monthly) | C27: =Contractual_Rate -> 0.037 | D27: =Address -> ** | K27: Bi-Monthly | L27: 6 | M27: 2
A28: No. of Monthly Installment | C28: ='Master data Input'!K12 -> 12 | K28: Monthly | L28: 12 | M28: 1
A29: Monthly Payment | C29: ='Monthly -client copy'!D67/'Semi Monthly -client copy'!H9 -> 7916.918 | K29: Semi-Monthly | L29: 24 | M29: 0.5
A30: Other Charges | C30: =D18 -> 7571.5283 | K30: Bi-Weekly | L30: 26 | M30: n/a
K31: Weekly | L31: 52 | M31: n/a
A32: Summary | D32: Remarks | K32: Chosen: | L32: =INDEX(L24:L31,MATCH(Installment_Type_SM,K24:K31,0)) -> 24 | M32: =INDEX(M24:M31,MATCH(Installment_Type_SM,K24:K31,0)) -> 0.5
A34: Effective Annual Interest Rate (EIR) | C34: =(1+IRR($G$41:$G$59))^12-1 -> #NUM!
A35: Effective Monthly Interest Rate (MIR) | C35: =IRR($G$41:$G$59) -> #NUM!
A36: Total Payments | C36: =SUM($G$42:$G$59) -> 95003.016
A37: Total Interest | C37: =Total_InterestRate -> 14049.306
A39: Inst. Period | B39: Due Date | C39: Gross Loan | D39: Principal | E39: Interest | F39: Other Charges | G39: Cash Flows | H39: Balance
C40: =C26 -> 80953.71 | H40: =C26 -> 80953.71
A41: 0 | F41: =C30 -> 7571.5283 | G41: =H40-F41 -> 73382.182 | H41: =C26 -> 80953.71
A42: 1 | B42: =IF(A42="","",IF($L$32=26,(A42-1)*14+Start_Payment_SM,IF($L$32=52,(A42-1)*7+Start_Payment_SM,DATE(YEAR(Start_Payment_SM),MONTH(Start_Payment_SM)+(A42-1)*$M$32,IF($L$32=24,IF((MOD(A42-1,2))=1,DAY(Start_Payment_SM)+15,DAY(Start_Payment_SM)),DAY(Start_Payment_SM)))))) -> 43317 | D42: =IF(period2<>"",E42+G42,"") -> 7916.918 | E42: =IF(period2<>"",IF(G42<0,(H41*$C$27),0),"") -> 0 | G42: =IF(period2<>"",IF(ROUND(H41,5)>0,C$29,0),"") -> 7916.918 | H42: =IF(period2<>"",IF(ROUND(H40,5)>0,(D42-(-H41)),0),"") -> 88870.628
A43: =IF(A42<$C$28,A42+1,"") -> 2 | B43: =IF(A43="","",IF($L$32=26,(A43-1)*14+Start_Payment_SM,IF($L$32=52,(A43-1)*7+Start_Payment_SM,DATE(YEAR(Start_Payment_SM),MONTH(Start_Payment_SM)+(A43-1)*$M$32,IF($L$32=24,IF((MOD(A43-1,2))=1,DAY(Start_Payment_SM)+15,DAY(Start_Payment_SM)),DAY(Start_Payment_SM)))))) -> 43332 | D43: =IF(period2<>"",E43+G43,"") -> 7916.918 | E43: =IF(period2<>"",IF(G43<0,(H42*$C$27),0),"") -> 0 | G43: =IF(period2<>"",IF(ROUND(H42,5)>0,C$29,0),"") -> 7916.918 | H43: =IF(period2<>"",IF(ROUND(H41,5)>0,(D43-(-H42)),0),"") -> 96787.546
A44: =IF(A43<$C$28,A43+1,"") -> 3 | B44: =IF(A44="","",IF($L$32=26,(A44-1)*14+Start_Payment_SM,IF($L$32=52,(A44-1)*7+Start_Payment_SM,DATE(YEAR(Start_Payment_SM),MONTH(Start_Payment_SM)+(A44-1)*$M$32,IF($L$32=24,IF((MOD(A44-1,2))=1,DAY(Start_Payment_SM)+15,DAY(Start_Payment_SM)),DAY(Start_Payment_SM)))))) -> 43348 | D44: =IF(period2<>"",E44+G44,"") -> 7916.918 | E44: =IF(period2<>"",IF(G44<0,(H43*$C$27),0),"") -> 0 | G44: =IF(period2<>"",IF(ROUND(H43,5)>0,C$29,0),"") -> 7916.918 | H44: =IF(period2<>"",IF(ROUND(H42,5)>0,(D44-(-H43)),0),"") -> 104704.46
A45: =IF(A44<$C$28,A44+1,"") -> 4 | B45: =IF(A45="","",IF($L$32=26,(A45-1)*14+Start_Payment_SM,IF($L$32=52,(A45-1)*7+Start_Payment_SM,DATE(YEAR(Start_Payment_SM),MONTH(Start_Payment_SM)+(A45-1)*$M$32,IF($L$32=24,IF((MOD(A45-1,2))=1,DAY(Start_Payment_SM)+15,DAY(Start_Payment_SM)),DAY(Start_Payment_SM)))))) -> 43363 | D45: =IF(period2<>"",E45+G45,"") -> 7916.918 | E45: =IF(period2<>"",IF(G45<0,(H44*$C$27),0),"") -> 0 | G45: =IF(period2<>"",IF(ROUND(H44,5)>0,C$29,0),"") -> 7916.918 | H45: =IF(period2<>"",IF(ROUND(H43,5)>0,(D45-(-H44)),0),"") -> 112621.38
A46: =IF(A45<$C$28,A45+1,"") -> 5 | B46: =IF(A46="","",IF($L$32=26,(A46-1)*14+Start_Payment_SM,IF($L$32=52,(A46-1)*7+Start_Payment_SM,DATE(YEAR(Start_Payment_SM),MONTH(Start_Payment_SM)+(A46-1)*$M$32,IF($L$32=24,IF((MOD(A46-1,2))=1,DAY(Start_Payment_SM)+15,DAY(Start_Payment_SM)),DAY(Start_Payment_SM)))))) -> 43378 | D46: =IF(period2<>"",E46+G46,"") -> 7916.918 | E46: =IF(period2<>"",IF(G46<0,(H45*$C$27),0),"") -> 0 | G46: =IF(period2<>"",IF(ROUND(H45,5)>0,C$29,0),"") -> 7916.918 | H46: =IF(period2<>"",IF(ROUND(H44,5)>0,(D46-(-H45)),0),"") -> 120538.3
A47: =IF(A46<$C$28,A46+1,"") -> 6 | B47: =IF(A47="","",IF($L$32=26,(A47-1)*14+Start_Payment_SM,IF($L$32=52,(A47-1)*7+Start_Payment_SM,DATE(YEAR(Start_Payment_SM),MONTH(Start_Payment_SM)+(A47-1)*$M$32,IF($L$32=24,IF((MOD(A47-1,2))=1,DAY(Start_Payment_SM)+15,DAY(Start_Payment_SM)),DAY(Start_Payment_SM)))))) -> 43393 | D47: =IF(period2<>"",E47+G47,"") -> 7916.918 | E47: =IF(period2<>"",IF(G47<0,(H46*$C$27),0),"") -> 0 | G47: =IF(period2<>"",IF(ROUND(H46,5)>0,C$29,0),"") -> 7916.918 | H47: =IF(period2<>"",IF(ROUND(H45,5)>0,(D47-(-H46)),0),"") -> 128455.22
A48: =IF(A47<$C$28,A47+1,"") -> 7 | B48: =IF(A48="","",IF($L$32=26,(A48-1)*14+Start_Payment_SM,IF($L$32=52,(A48-1)*7+Start_Payment_SM,DATE(YEAR(Start_Payment_SM),MONTH(Start_Payment_SM)+(A48-1)*$M$32,IF($L$32=24,IF((MOD(A48-1,2))=1,DAY(Start_Payment_SM)+15,DAY(Start_Payment_SM)),DAY(Start_Payment_SM)))))) -> 43409 | D48: =IF(period2<>"",E48+G48,"") -> 7916.918 | E48: =IF(period2<>"",IF(G48<0,(H47*$C$27),0),"") -> 0 | G48: =IF(period2<>"",IF(ROUND(H47,5)>0,C$29,0),"") -> 7916.918 | H48: =IF(period2<>"",IF(ROUND(H46,5)>0,(D48-(-H47)),0),"") -> 136372.14
A49: =IF(A48<$C$28,A48+1,"") -> 8 | B49: =IF(A49="","",IF($L$32=26,(A49-1)*14+Start_Payment_SM,IF($L$32=52,(A49-1)*7+Start_Payment_SM,DATE(YEAR(Start_Payment_SM),MONTH(Start_Payment_SM)+(A49-1)*$M$32,IF($L$32=24,IF((MOD(A49-1,2))=1,DAY(Start_Payment_SM)+15,DAY(Start_Payment_SM)),DAY(Start_Payment_SM)))))) -> 43424 | D49: =IF(period2<>"",E49+G49,"") -> 7916.918 | E49: =IF(period2<>"",IF(G49<0,(H48*$C$27),0),"") -> 0 | G49: =IF(period2<>"",IF(ROUND(H48,5)>0,C$29,0),"") -> 7916.918 | H49: =IF(period2<>"",IF(ROUND(H47,5)>0,(D49-(-H48)),0),"") -> 144289.05
A50: =IF(A49<$C$28,A49+1,"") -> 9 | B50: =IF(A50="","",IF($L$32=26,(A50-1)*14+Start_Payment_SM,IF($L$32=52,(A50-1)*7+Start_Payment_SM,DATE(YEAR(Start_Payment_SM),MONTH(Start_Payment_SM)+(A50-1)*$M$32,IF($L$32=24,IF((MOD(A50-1,2))=1,DAY(Start_Payment_SM)+15,DAY(Start_Payment_SM)),DAY(Start_Payment_SM)))))) -> 43439 | D50: =IF(period2<>"",E50+G50,"") -> 7916.918 | E50: =IF(period2<>"",IF(G50<0,(H49*$C$27),0),"") -> 0 | G50: =IF(period2<>"",IF(ROUND(H49,5)>0,C$29,0),"") -> 7916.918 | H50: =IF(period2<>"",IF(ROUND(H48,5)>0,(D50-(-H49)),0),"") -> 152205.97
A51: =IF(A50<$C$28,A50+1,"") -> 10 | B51: =IF(A51="","",IF($L$32=26,(A51-1)*14+Start_Payment_SM,IF($L$32=52,(A51-1)*7+Start_Payment_SM,DATE(YEAR(Start_Payment_SM),MONTH(Start_Payment_SM)+(A51-1)*$M$32,IF($L$32=24,IF((MOD(A51-1,2))=1,DAY(Start_Payment_SM)+15,DAY(Start_Payment_SM)),DAY(Start_Payment_SM)))))) -> 43454 | D51: =IF(period2<>"",E51+G51,"") -> 7916.918 | E51: =IF(period2<>"",IF(G51<0,(H50*$C$27),0),"") -> 0 | G51: =IF(period2<>"",IF(ROUND(H50,5)>0,C$29,0),"") -> 7916.918 | H51: =IF(period2<>"",IF(ROUND(H49,5)>0,(D51-(-H50)),0),"") -> 160122.89
A52: =IF(A51<$C$28,A51+1,"") -> 11 | B52: =IF(A52="","",IF($L$32=26,(A52-1)*14+Start_Payment_SM,IF($L$32=52,(A52-1)*7+Start_Payment_SM,DATE(YEAR(Start_Payment_SM),MONTH(Start_Payment_SM)+(A52-1)*$M$32,IF($L$32=24,IF((MOD(A52-1,2))=1,DAY(Start_Payment_SM)+15,DAY(Start_Payment_SM)),DAY(Start_Payment_SM)))))) -> 43470 | D52: =IF(period2<>"",E52+G52,"") -> 7916.918 | E52: =IF(period2<>"",IF(G52<0,(H51*$C$27),0),"") -> 0 | G52: =IF(period2<>"",IF(ROUND(H51,5)>0,C$29,0),"") -> 7916.918 | H52: =IF(period2<>"",IF(ROUND(H50,5)>0,(D52-(-H51)),0),"") -> 168039.81
A53: =IF(A52<$C$28,A52+1,"") -> 12 | B53: =IF(A53="","",IF($L$32=26,(A53-1)*14+Start_Payment_SM,IF($L$32=52,(A53-1)*7+Start_Payment_SM,DATE(YEAR(Start_Payment_SM),MONTH(Start_Payment_SM)+(A53-1)*$M$32,IF($L$32=24,IF((MOD(A53-1,2))=1,DAY(Start_Payment_SM)+15,DAY(Start_Payment_SM)),DAY(Start_Payment_SM)))))) -> 43485 | D53: =IF(period2<>"",E53+G53,"") -> 7916.918 | E53: =IF(period2<>"",IF(G53<0,(H52*$C$27),0),"") -> 0 | G53: =IF(period2<>"",IF(ROUND(H52,5)>0,C$29,0),"") -> 7916.918 | H53: =IF(period2<>"",IF(ROUND(H51,5)>0,(D53-(-H52)),0),"") -> 175956.73
A54: =IF(A53<$C$28,A53+1,"") | B54: =IF(A54="","",IF($L$32=26,(A54-1)*14+Start_Payment_SM,IF($L$32=52,(A54-1)*7+Start_Payment_SM,DATE(YEAR(Start_Payment_SM),MONTH(Start_Payment_SM)+(A54-1)*$M$32,IF($L$32=24,IF((MOD(A54-1,2))=1,DAY(Start_Payment_SM)+15,DAY(Start_Payment_SM)),DAY(Start_Payment_SM)))))) | D54: =IF(period2<>"",E54+G54,"") | E54: =IF(period2<>"",IF(G54<0,(H53*$C$27),0),"") | G54: =IF(period2<>"",IF(ROUND(H53,5)>0,C$29,0),"") | H54: =IF(period2<>"",IF(ROUND(H52,5)>0,(D54-(-H53)),0),"")
... A59: =IF(A58<$C$28,A58+1,"") | B59: =IF(A59="","",IF($L$32=26,(A59-1)*14+Start_Payment_SM,IF($L$32=52,(A59-1)*7+Start_Payment_SM,DATE(YEAR(Start_Payment_SM),MONTH(Start_Payment_SM)+(A59-1)*$M$32,IF($L$32=24,IF((MOD(A59-1,2))=1,DAY(Start_Payment_SM)+15,DAY(Start_Payment_SM)),DAY(Start_Payment_SM)))))) | D59: =IF(period2<>"",E59+G59,"") | E59: =IF(period2<>"",IF(G59<0,(H58*$C$27),0),"") | G59: =IF(period2<>"",IF(ROUND(H58,5)>0,C$29,0),"") | H59: =IF(period2<>"",IF(ROUND(H57,5)>0,(D59-(-H58)),0),"")
A61: ="Interest Rate of " & (Contractual_Rate*100) &"% is equivalent to the Add On Rate of " & ROUND((((((Total_InterestRate/C26)/Monthly_Inst))))*100,2) & "% per Month" -> Interest Rate of 3.7% is equivalent to the Add On Rate of 1.45% per Month
A63: Prepared / Verified by: | E63: Noted by:
A66: Released by: | E66: Received Copy:

Sheet Semi Monthly 3 SL
A4: 9th Floor Times Plaza Bldg., UN Ave. Cor. Taft Ave. Ermita Manila
A5: Manila, Philippines
A6: 353-85-24/25
A8: =UPPER("Computation Sheet and Payment Schedule") -> COMPUTATION SHEET AND PAYMENT SCHEDULE
A9: NAME | C9: ADDRESS | E9: TYPE OF LOAN | H9: TERMS
A10: =IF(OR_NAME<>"",Client_Name &" or " & OR_NAME,Client_Name) -> ** or ** | C10: =PROPER('Master data Input'!C8) -> ** | F10: =Type_of_Loan&TEXT(IF(Express="YES","-EXPRESS",""),"") -> SML | H10: In months | I10: =Term_masterdatainput -> 8 | J10: =Terms -> 8
F11: Interest/mo | G11: =Interest -> 0.03 | H11: from | I11: to
A12: =IF(UPPER(OR_NAME)<>" ",UPPER(OR_NAME),".") -> ** | H12: =Date_Released -> 46083 | I12: =MaturityDate_data_input -> 46342 | M12: ='Master data Input'!F30 -> 46342 | N12: end of term | O12: =I10 -> 8
F13: # of payments | G13: ='Semi Monthly SL'!Monthly_Inst -> 12
M14: =IF(U27<H12,H12,U27) -> 46083
A15: COMPUTATION OF NET PROCEEDS
W16: 7
A17: Principal/ Amount Financed | F17: =IF(get_loan_amount="NET AMOUNT",get_gross_amount,Loan_Amount) -> 80953.71
A19: Less Interest and Other Charges | G19: New | I19: =IF(I20>0,"NO", "YES") -> NO
A20: Interest | B20: =Interest -> 0.03 | C20: ="from"&TEXT(Date_Released," mm/dd/yyyy")&" to "&TEXT(Date_released2," mm/dd/yyyy") -> from 03/02/2026 to 03/02/2026 | E20: =IF(Type_of_Loan="BL-SA",0,ROUND(Principal_Amount*(Interest/30)*DATEDIF(Date_Released,Date_released2,"d"),2)) -> 0 | G20: Renewal Nth loan | I20: ='Master data Input'!C18 -> No | J20: =E20+D43/B43-(360/DATEDIF(H12,I12,"d")) -> #DIV/0! | L20: =DATEDIF(H12,C45,"d") -> #NUM! | M20: days from loan release and 1st payment
A21: Processing Fee | C21: =Processing_Fee_in_Percentage -> 0.075 | E21: =Principal_Amount*Percent_processingfee -> 6071.5283 | G21: Installment Type | I21: =Installment_Type -> Monthly | L21: =DATEDIF(H12,M14,"D") -> 0
A22: Account Management Fee | E22: =Account_Management_fee -> Auto compute**
A23: Notarial fee | E23: =Notarial_Fee -> 500
A24: Doc fee | E24: =Docfee_Yes_or_No -> 500
A25: ='Master data Input'!B42 -> MLRI -Insurance | E25: =Insurance -> Auto compute**
A26: ='Master data Input'!B45 -> Miscellaneous | E26: ='Master data Input'!C45 -> 500 | G26: Check No. | L26: =DATEDIF(M14,M12,"D") -> 259
A27: Total Finance charge | E27: =SUM(E20:E26) -> 7571.5283 | L27: =DATEDIF(H12,M12,"D") -> 259 | U27: =DATE(YEAR(C45),MONTH(C45),DAY(C45)-30) -> 42621
A28: Others: | G28: PN no. | H28: ="PN-"&TEXT('Master data Input'!F10,"0000- ")&TEXT(" "," ")&'Master data Input'!C14 -> PN-. SML
A29: ='Master data Input'!B12 -> Outstanding Balance from previous loan | E29: =Outstanding_Balance_from_previous_loan -> 0 | P29: =TEXT($L$20,"0")&"/"&TEXT($L$21,"0")&"/"&TEXT($L$26,"0")&"/"&TEXT($L$27,"0") -> #NUM! | X29: =45000*0.15*(305/360) -> 5718.75
A30: Cash Advance | E30: =Advanced_Payment -> 0 | L30: =DATEDIF(M14,C45,"d") -> #NUM!
F33: =ROUNDUP(Total_Finance_Charge+SUM($E$29:$E$33),0) -> 7572 | G33: MODE OF PAYMENT: | I33: ='Master data Input'!F42 -> 0
A35: Net Proceeds | F35: =ROUNDUP(Principal_Amount-Total_Deduction,0) -> 73382 | M35: IF('Master data Input'!B35="YES",ROUNDUP(F16*0.0015,0),"0") | U35: DATEDIF(H11,I11,"D")
A37: Effective Rate (per month) | F37: ='Monthly -client copy'!F33 -> 0.037 | M37: IF(1200>O27,1200,O27)
A38: % of Finance charges to Total Amount Financed | F38: ='Monthly -client copy'!F32 -> 0.10852916 | G38: Release Date: | I38: =Date_Released -> 46083
G39: Agent: | H39: =UPPER(Agents)
A40: SCHEDULE OF AMORTIZATION
N41: =D43+E20 -> 14049.306 | O41: 11667
B42: Principal / Amount of Loan | D42: Interest Due on Loans | F42: Total Amount Payable | Z42: =DATE(YEAR(U21),MONTH(U21)+1,DAY(U21)) -> 31
C43: ='Monthly -client copy'!F67 -> 80953.71 | D43: =Total_InterestRate -> 14049.306 | F43: =C43+Total_UII -> 95003.016 | L43: =DATE(YEAR($C$45),MONTH($C$45)+($G$13-1),DAY($C$45)) -> 42986 | M43: w/out adjustment
B44: Period | C44: Due Date | D44: amortization | E44: Interest | G44: Principal | J44: Balance
B45: 1 | C45: 42651 | D45: =IF(PERIOD<>"",($F$43/$B$70),"") -> 7916.918 | E45: =IF(NOT(B45=AA27),$D$43*(($B$70-(B45-1))/((($B$70+1)/2)*$B$70)),"") -> 2161.4317 | G45: =D45-E45 -> 5755.4863 | J45: =C43-G45 -> 75198.224 | K45: =IF(WEEKDAY(L45,2)=1,"Monday",IF(WEEKDAY(L45,2)=2,"Tuesday",IF(WEEKDAY(L45,2)=3,"Wednesday",IF(WEEKDAY(L45,2)=4,"Thursday",IF(WEEKDAY(L45,2)=5,"Friday",IF(WEEKDAY(L45,2)=6,"Saturday",IF(WEEKDAY(L45,2)=7,"Sunday"))))))) -> Thursday | L45: ='Master data Input'!C30 -> 46128
B46: =IF(B45<$G$13,B45+1,"") -> 2 | C46: 42666 | D46: =IF(PERIOD<>"",($F$43/$B$70),"") -> 7916.918 | E46: =IF(NOT(B46=AA28),$D$43*(($B$70-(B46-1))/((($B$70+1)/2)*$B$70)),"") -> 1981.3124 | G46: =IF(NOT(B46=AA31),D46-E46,"") -> 5935.6056 | J46: =J45-G46 -> 69262.618 | K46: =IF(WEEKDAY(L46,2)=1,"Monday",IF(WEEKDAY(L46,2)=2,"Tuesday",IF(WEEKDAY(L46,2)=3,"Wednesday",IF(WEEKDAY(L46,2)=4,"Thursday",IF(WEEKDAY(L46,2)=5,"Friday",IF(WEEKDAY(L46,2)=6,"Saturday",IF(WEEKDAY(L46,2)=7,"Sunday"))))))) -> #VALUE! | L46: =IF(PERIOD<>"",IF(DATE(YEAR(L45),MONTH(L45),DAY(L45))<=$L$43,DATE(YEAR(L45),MONTH(L45)+1,DAY(L45)),""),"")
B47: =IF(B46<$G$13,B46+1,"") -> 3 | C47: 42682 | D47: =IF(PERIOD<>"",($F$43/$B$70),"") -> 7916.918 | E47: =IF(NOT(B47=AA31),$D$43*(($B$70-(B47-1))/((($B$70+1)/2)*$B$70)),"") -> 1801.1931 | G47: =IF(NOT(B47=AA33),D47-E47,"") -> 6115.7249 | J47: =J46-G47 -> 63146.893 | K47: =IF(WEEKDAY(L47,2)=1,"Monday",IF(WEEKDAY(L47,2)=2,"Tuesday",IF(WEEKDAY(L47,2)=3,"Wednesday",IF(WEEKDAY(L47,2)=4,"Thursday",IF(WEEKDAY(L47,2)=5,"Friday",IF(WEEKDAY(L47,2)=6,"Saturday",IF(WEEKDAY(L47,2)=7,"Sunday"))))))) -> #VALUE! | L47: =IF(PERIOD<>"",IF(DATE(YEAR(L46),MONTH(L46),DAY(L46))<=$L$43,DATE(YEAR(L46),MONTH(L46)+1,DAY(L46)),""),"") -> #VALUE!
B48: =IF(B47<$G$13,B47+1,"") -> 4 | C48: 42697 | D48: =IF(PERIOD<>"",($F$43/$B$70),"") -> 7916.918 | E48: =IF(NOT(B48=AA33),$D$43*(($B$70-(B48-1))/((($B$70+1)/2)*$B$70)),"") -> 1621.0738 | G48: =IF(NOT(B48=AA34),D48-E48,"") -> 6295.8442 | J48: =J47-G48 -> 56851.049 | K48: =IF(WEEKDAY(L48,2)=1,"Monday",IF(WEEKDAY(L48,2)=2,"Tuesday",IF(WEEKDAY(L48,2)=3,"Wednesday",IF(WEEKDAY(L48,2)=4,"Thursday",IF(WEEKDAY(L48,2)=5,"Friday",IF(WEEKDAY(L48,2)=6,"Saturday",IF(WEEKDAY(L48,2)=7,"Sunday"))))))) -> #VALUE! | L48: =IF(PERIOD<>"",IF(DATE(YEAR(L47),MONTH(L47),DAY(L47))<=$L$43,DATE(YEAR(L47),MONTH(L47)+1,DAY(L47)),""),"") -> #VALUE!
B49: =IF(B48<$G$13,B48+1,"") -> 5 | C49: 42712 | D49: =IF(PERIOD<>"",($F$43/$B$70),"") -> 7916.918 | E49: =IF(NOT(B49=AA34),$D$43*(($B$70-(B49-1))/((($B$70+1)/2)*$B$70)),"") -> 1440.9545 | G49: =IF(NOT(B49=AA35),D49-E49,"") -> 6475.9635 | J49: =J48-G49 -> 50375.085 | K49: =IF(WEEKDAY(L49,2)=1,"Monday",IF(WEEKDAY(L49,2)=2,"Tuesday",IF(WEEKDAY(L49,2)=3,"Wednesday",IF(WEEKDAY(L49,2)=4,"Thursday",IF(WEEKDAY(L49,2)=5,"Friday",IF(WEEKDAY(L49,2)=6,"Saturday",IF(WEEKDAY(L49,2)=7,"Sunday"))))))) -> #VALUE! | L49: =IF(PERIOD<>"",IF(DATE(YEAR(L48),MONTH(L48),DAY(L48))<=$L$43,DATE(YEAR(L48),MONTH(L48)+1,DAY(L48)),""),"") -> #VALUE!
B50: =IF(B49<$G$13,B49+1,"") -> 6 | C50: 42727 | D50: =IF(PERIOD<>"",($F$43/$B$70),"") -> 7916.918 | E50: =IF(NOT(B50=AA35),$D$43*(($B$70-(B50-1))/((($B$70+1)/2)*$B$70)),"") -> 1260.8352 | G50: =IF(NOT(B50=AA36),D50-E50,"") -> 6656.0828 | J50: =J49-G50 -> 43719.003 | K50: =IF(WEEKDAY(L50,2)=1,"Monday",IF(WEEKDAY(L50,2)=2,"Tuesday",IF(WEEKDAY(L50,2)=3,"Wednesday",IF(WEEKDAY(L50,2)=4,"Thursday",IF(WEEKDAY(L50,2)=5,"Friday",IF(WEEKDAY(L50,2)=6,"Saturday",IF(WEEKDAY(L50,2)=7,"Sunday"))))))) -> #VALUE! | L50: =IF(PERIOD<>"",IF(DATE(YEAR(L49),MONTH(L49),DAY(L49))<=$L$43,DATE(YEAR(L49),MONTH(L49)+1,DAY(L49)),""),"") -> #VALUE!
B51: =IF(B50<$G$13,B50+1,"") -> 7 | C51: ='Semi Monthly -client copy'!B52 -> 42750 | D51: =IF(PERIOD<>"",($F$43/$B$70),"") -> 7916.918 | E51: =IF(NOT(B51=AA36),$D$43*(($B$70-(B51-1))/((($B$70+1)/2)*$B$70)),"") -> 1080.7159 | G51: =IF(NOT(B51=AA37),D51-E51,"") -> 6836.2022 | J51: =J50-G51 -> 36882.8 | K51: =IF(WEEKDAY(L51,2)=1,"Monday",IF(WEEKDAY(L51,2)=2,"Tuesday",IF(WEEKDAY(L51,2)=3,"Wednesday",IF(WEEKDAY(L51,2)=4,"Thursday",IF(WEEKDAY(L51,2)=5,"Friday",IF(WEEKDAY(L51,2)=6,"Saturday",IF(WEEKDAY(L51,2)=7,"Sunday"))))))) -> #VALUE! | L51: =IF(PERIOD<>"",IF(DATE(YEAR(L50),MONTH(L50),DAY(L50))<=$L$43,DATE(YEAR(L50),MONTH(L50)+1,DAY(L50)),""),"") -> #VALUE!
B52: =IF(B51<$G$13,B51+1,"") -> 8 | C52: ='Semi Monthly -client copy'!B53 -> 42765 | D52: =IF(PERIOD<>"",($F$43/$B$70),"") -> 7916.918 | E52: =IF(NOT(B52=AA37),$D$43*(($B$70-(B52-1))/((($B$70+1)/2)*$B$70)),"") -> 900.59656 | G52: =IF(NOT(B52=AA38),D52-E52,"") -> 7016.3215 | J52: =J51-G52 -> 29866.479 | K52: =IF(WEEKDAY(L52,2)=1,"Monday",IF(WEEKDAY(L52,2)=2,"Tuesday",IF(WEEKDAY(L52,2)=3,"Wednesday",IF(WEEKDAY(L52,2)=4,"Thursday",IF(WEEKDAY(L52,2)=5,"Friday",IF(WEEKDAY(L52,2)=6,"Saturday",IF(WEEKDAY(L52,2)=7,"Sunday"))))))) -> #VALUE! | L52: =IF(PERIOD<>"",IF(DATE(YEAR(L51),MONTH(L51),DAY(L51))<=$L$43,DATE(YEAR(L51),MONTH(L51)+1,DAY(L51)),""),"") -> #VALUE!
B53: =IF(B52<$G$13,B52+1,"") -> 9 | C53: ='Semi Monthly -client copy'!B54 -> 42781 | D53: =IF(PERIOD<>"",($F$43/$B$70),"") -> 7916.918 | E53: =IF(NOT(B53=AA38),$D$43*(($B$70-(B53-1))/((($B$70+1)/2)*$B$70)),"") -> 720.47725 | G53: =IF(NOT(B53=AA39),D53-E53,"") -> 7196.4408 | J53: =J52-G53 -> 22670.038 | K53: =IF(WEEKDAY(L53,2)=1,"Monday",IF(WEEKDAY(L53,2)=2,"Tuesday",IF(WEEKDAY(L53,2)=3,"Wednesday",IF(WEEKDAY(L53,2)=4,"Thursday",IF(WEEKDAY(L53,2)=5,"Friday",IF(WEEKDAY(L53,2)=6,"Saturday",IF(WEEKDAY(L53,2)=7,"Sunday"))))))) -> #VALUE! | L53: =IF(PERIOD<>"",IF(DATE(YEAR(L52),MONTH(L52),DAY(L52))<=$L$43,DATE(YEAR(L52),MONTH(L52)+1,DAY(L52)),""),"") -> #VALUE!
B54: =IF(B53<$G$13,B53+1,"") -> 10 | C54: ='Semi Monthly -client copy'!B55 -> 42794 | D54: =IF(PERIOD<>"",($F$43/$B$70),"") -> 7916.918 | E54: =IF(NOT(B54=AA39),$D$43*(($B$70-(B54-1))/((($B$70+1)/2)*$B$70)),"") -> 540.35794 | G54: =IF(NOT(B54=AA40),D54-E54,"") -> 7376.5601 | J54: =J53-G54 -> 15293.478 | K54: =IF(WEEKDAY(L54,2)=1,"Monday",IF(WEEKDAY(L54,2)=2,"Tuesday",IF(WEEKDAY(L54,2)=3,"Wednesday",IF(WEEKDAY(L54,2)=4,"Thursday",IF(WEEKDAY(L54,2)=5,"Friday",IF(WEEKDAY(L54,2)=6,"Saturday",IF(WEEKDAY(L54,2)=7,"Sunday"))))))) -> #VALUE! | L54: =IF(PERIOD<>"",IF(DATE(YEAR(L53),MONTH(L53),DAY(L53))<=$L$43,DATE(YEAR(L53),MONTH(L53)+1,DAY(L53)),""),"") -> #VALUE!
B55: =IF(B54<$G$13,B54+1,"") -> 11 | C55: ='Semi Monthly -client copy'!B56 -> 42809 | D55: =IF(PERIOD<>"",($F$43/$B$70),"") -> 7916.918 | E55: =IF(NOT(B55=AA40),$D$43*(($B$70-(B55-1))/((($B$70+1)/2)*$B$70)),"") -> 360.23862 | G55: =IF(NOT(B55=AA41),D55-E55,"") -> 7556.6794 | J55: =J54-G55 -> 7736.7987 | K55: =IF(WEEKDAY(L55,2)=1,"Monday",IF(WEEKDAY(L55,2)=2,"Tuesday",IF(WEEKDAY(L55,2)=3,"Wednesday",IF(WEEKDAY(L55,2)=4,"Thursday",IF(WEEKDAY(L55,2)=5,"Friday",IF(WEEKDAY(L55,2)=6,"Saturday",IF(WEEKDAY(L55,2)=7,"Sunday"))))))) -> #VALUE! | L55: =IF(PERIOD<>"",IF(DATE(YEAR(L54),MONTH(L54),DAY(L54))<=$L$43,DATE(YEAR(L54),MONTH(L54)+1,DAY(L54)),""),"") -> #VALUE!
B56: =IF(B55<$G$13,B55+1,"") -> 12 | C56: ='Semi Monthly -client copy'!B57 -> 42824 | D56: =IF(PERIOD<>"",($F$43/$B$70),"") -> 7916.918 | E56: =IF(NOT(B56=AA41),$D$43*(($B$70-(B56-1))/((($B$70+1)/2)*$B$70)),"") -> 180.11931 | G56: =IF(NOT(B56=AB42),D56-E56,"") -> 7736.7987 | J56: =J55-G56 -> 8.1854523e-12 | K56: =IF(WEEKDAY(L56,2)=1,"Monday",IF(WEEKDAY(L56,2)=2,"Tuesday",IF(WEEKDAY(L56,2)=3,"Wednesday",IF(WEEKDAY(L56,2)=4,"Thursday",IF(WEEKDAY(L56,2)=5,"Friday",IF(WEEKDAY(L56,2)=6,"Saturday",IF(WEEKDAY(L56,2)=7,"Sunday"))))))) -> #VALUE! | L56: =IF(PERIOD<>"",IF(DATE(YEAR(L55),MONTH(L55),DAY(L55))<=$L$43,DATE(YEAR(L55),MONTH(L55)+1,DAY(L55)),""),"") -> #VALUE!
B57: =IF(B56<$G$13,B56+1,"") | D57: =IF(PERIOD<>"",($F$43/$B$70),"") | E57: =IF(NOT(B57=AB42),$D$43*(($B$70-(B57-1))/((($B$70+1)/2)*$B$70)),"") | G57: =IF(NOT(B57=AB43),D57-F57,"") | J57: =J56-G57 -> #VALUE! | K57: =IF(WEEKDAY(L57,2)=1,"Monday",IF(WEEKDAY(L57,2)=2,"Tuesday",IF(WEEKDAY(L57,2)=3,"Wednesday",IF(WEEKDAY(L57,2)=4,"Thursday",IF(WEEKDAY(L57,2)=5,"Friday",IF(WEEKDAY(L57,2)=6,"Saturday",IF(WEEKDAY(L57,2)=7,"Sunday"))))))) -> #VALUE! | L57: =IF(PERIOD<>"",IF(DATE(YEAR(L56),MONTH(L56),DAY(L56))<=$L$43,DATE(YEAR(L56),MONTH(L56)+1,DAY(L56)),""),"")
B58: =IF(B57<$G$13,B57+1,"") | D58: =IF(PERIOD<>"",($F$43/$B$70),"") | E58: =IF(NOT(B58=AB43),$D$43*(($B$70-(B58-1))/((($B$70+1)/2)*$B$70)),"") | G58: =IF(NOT(B58=M44),D58-F58,"") | J58: =J57-G58 -> #VALUE! | K58: =IF(WEEKDAY(L58,2)=1,"Monday",IF(WEEKDAY(L58,2)=2,"Tuesday",IF(WEEKDAY(L58,2)=3,"Wednesday",IF(WEEKDAY(L58,2)=4,"Thursday",IF(WEEKDAY(L58,2)=5,"Friday",IF(WEEKDAY(L58,2)=6,"Saturday",IF(WEEKDAY(L58,2)=7,"Sunday"))))))) -> #VALUE! | L58: =IF(PERIOD<>"",IF(DATE(YEAR(L57),MONTH(L57),DAY(L57))<=$L$43,DATE(YEAR(L57),MONTH(L57)+1,DAY(L57)),""),"")
B59: =IF(B58<$G$13,B58+1,"") | D59: =IF(PERIOD<>"",($F$43/$B$70),"") | E59: =IF(NOT(B59=M44),$D$43*(($B$70-(B59-1))/((($B$70+1)/2)*$B$70)),"") | G59: =IF(NOT(B59=M45),D59-F59,"") | J59: =J58-G59 -> #VALUE! | K59: =IF(WEEKDAY(L59,2)=1,"Monday",IF(WEEKDAY(L59,2)=2,"Tuesday",IF(WEEKDAY(L59,2)=3,"Wednesday",IF(WEEKDAY(L59,2)=4,"Thursday",IF(WEEKDAY(L59,2)=5,"Friday",IF(WEEKDAY(L59,2)=6,"Saturday",IF(WEEKDAY(L59,2)=7,"Sunday"))))))) -> #VALUE! | L59: =IF(PERIOD<>"",IF(DATE(YEAR(L58),MONTH(L58),DAY(L58))<=$L$43,DATE(YEAR(L58),MONTH(L58)+1,DAY(L58)),""),"")
B60: =IF(B59<$G$13,B59+1,"") | D60: =IF(PERIOD<>"",($F$43/$B$70),"") | E60: =IF(NOT(B60=M45),$D$43*(($B$70-(B60-1))/((($B$70+1)/2)*$B$70)),"") | G60: =IF(NOT(B60=M46),D60-F60,"") | J60: =J59-G60 -> #VALUE! | K60: =IF(WEEKDAY(L60,2)=1,"Monday",IF(WEEKDAY(L60,2)=2,"Tuesday",IF(WEEKDAY(L60,2)=3,"Wednesday",IF(WEEKDAY(L60,2)=4,"Thursday",IF(WEEKDAY(L60,2)=5,"Friday",IF(WEEKDAY(L60,2)=6,"Saturday",IF(WEEKDAY(L60,2)=7,"Sunday"))))))) -> #VALUE! | L60: =IF(PERIOD<>"",IF(DATE(YEAR(L59),MONTH(L59),DAY(L59))<=$L$43,DATE(YEAR(L59),MONTH(L59)+1,DAY(L59)),""),"")
B61: =IF(B60<$G$13,B60+1,"") | D61: =IF(PERIOD<>"",($F$43/$B$70),"") | E61: =IF(NOT(B61=M46),$D$43*(($B$70-(B61-1))/((($B$70+1)/2)*$B$70)),"") | G61: =IF(NOT(B61=M47),D61-F61,"") | J61: =J60-G61 -> #VALUE! | K61: =IF(WEEKDAY(L61,2)=1,"Monday",IF(WEEKDAY(L61,2)=2,"Tuesday",IF(WEEKDAY(L61,2)=3,"Wednesday",IF(WEEKDAY(L61,2)=4,"Thursday",IF(WEEKDAY(L61,2)=5,"Friday",IF(WEEKDAY(L61,2)=6,"Saturday",IF(WEEKDAY(L61,2)=7,"Sunday"))))))) -> #VALUE! | L61: =IF(PERIOD<>"",IF(DATE(YEAR(L60),MONTH(L60),DAY(L60))<=$L$43,DATE(YEAR(L60),MONTH(L60)+1,DAY(L60)),""),"")
B62: =IF(B61<$G$13,B61+1,"") | D62: =IF(PERIOD<>"",($F$43/$B$70),"") | E62: =IF(NOT(B62=M47),$D$43*(($B$70-(B62-1))/((($B$70+1)/2)*$B$70)),"") | G62: =IF(NOT(B62=M48),D62-F62,"") | J62: =J61-G62 -> #VALUE! | K62: =IF(WEEKDAY(L62,2)=1,"Monday",IF(WEEKDAY(L62,2)=2,"Tuesday",IF(WEEKDAY(L62,2)=3,"Wednesday",IF(WEEKDAY(L62,2)=4,"Thursday",IF(WEEKDAY(L62,2)=5,"Friday",IF(WEEKDAY(L62,2)=6,"Saturday",IF(WEEKDAY(L62,2)=7,"Sunday"))))))) -> #VALUE! | L62: =IF(PERIOD<>"",IF(DATE(YEAR(L61),MONTH(L61),DAY(L61))<=$L$43,DATE(YEAR(L61),MONTH(L61)+1,DAY(L61)),""),"")
B63: =IF(B62<$G$13,B62+1,"") | D63: =IF(PERIOD<>"",($F$43/$B$70),"") | E63: =IF(NOT(B63=M48),$D$43*(($B$70-(B63-1))/((($B$70+1)/2)*$B$70)),"") | G63: =IF(NOT(B63=M49),D63-F63,"") | J63: =J62-G63 -> #VALUE! | K63: =IF(WEEKDAY(L63,2)=1,"Monday",IF(WEEKDAY(L63,2)=2,"Tuesday",IF(WEEKDAY(L63,2)=3,"Wednesday",IF(WEEKDAY(L63,2)=4,"Thursday",IF(WEEKDAY(L63,2)=5,"Friday",IF(WEEKDAY(L63,2)=6,"Saturday",IF(WEEKDAY(L63,2)=7,"Sunday"))))))) -> #VALUE! | L63: =IF(PERIOD<>"",IF(DATE(YEAR(L62),MONTH(L62),DAY(L62))<=$L$43,DATE(YEAR(L62),MONTH(L62)+1,DAY(L62)),""),"")
B64: =IF(B63<$G$13,B63+1,"") | D64: =IF(PERIOD<>"",($F$43/$B$70),"") | E64: =IF(NOT(B64=M49),$D$43*(($B$70-(B64-1))/((($B$70+1)/2)*$B$70)),"") | G64: =IF(NOT(B64=M50),D64-F64,"") | J64: =J63-G64 -> #VALUE! | K64: =IF(WEEKDAY(L64,2)=1,"Monday",IF(WEEKDAY(L64,2)=2,"Tuesday",IF(WEEKDAY(L64,2)=3,"Wednesday",IF(WEEKDAY(L64,2)=4,"Thursday",IF(WEEKDAY(L64,2)=5,"Friday",IF(WEEKDAY(L64,2)=6,"Saturday",IF(WEEKDAY(L64,2)=7,"Sunday"))))))) -> #VALUE! | L64: =IF(PERIOD<>"",IF(DATE(YEAR(L63),MONTH(L63),DAY(L63))<=$L$43,DATE(YEAR(L63),MONTH(L63)+1,DAY(L63)),""),"")
B65: =IF(B64<$G$13,B64+1,"") | D65: =IF(PERIOD<>"",($F$43/$B$70),"") | E65: =IF(NOT(B65=M50),$D$43*(($B$70-(B65-1))/((($B$70+1)/2)*$B$70)),"") | G65: =IF(NOT(B65=M51),D65-F65,"") | J65: =J64-G65 -> #VALUE! | K65: =IF(WEEKDAY(L65,2)=1,"Monday",IF(WEEKDAY(L65,2)=2,"Tuesday",IF(WEEKDAY(L65,2)=3,"Wednesday",IF(WEEKDAY(L65,2)=4,"Thursday",IF(WEEKDAY(L65,2)=5,"Friday",IF(WEEKDAY(L65,2)=6,"Saturday",IF(WEEKDAY(L65,2)=7,"Sunday"))))))) -> #VALUE! | L65: =IF(PERIOD<>"",IF(DATE(YEAR(L64),MONTH(L64),DAY(L64))<=$L$43,DATE(YEAR(L64),MONTH(L64)+1,DAY(L64)),""),"")
B66: =IF(B65<$G$13,B65+1,"") | D66: =IF(PERIOD<>"",($F$43/$B$70),"") | E66: =IF(NOT(B66=M51),$D$43*(($B$70-(B66-1))/((($B$70+1)/2)*$B$70)),"") | G66: =IF(NOT(B66=M52),D66-F66,"") | J66: =J65-G66 -> #VALUE! | K66: =IF(WEEKDAY(L66,2)=1,"Monday",IF(WEEKDAY(L66,2)=2,"Tuesday",IF(WEEKDAY(L66,2)=3,"Wednesday",IF(WEEKDAY(L66,2)=4,"Thursday",IF(WEEKDAY(L66,2)=5,"Friday",IF(WEEKDAY(L66,2)=6,"Saturday",IF(WEEKDAY(L66,2)=7,"Sunday"))))))) -> #VALUE! | L66: =IF(PERIOD<>"",IF(DATE(YEAR(L65),MONTH(L65),DAY(L65))<=$L$43,DATE(YEAR(L65),MONTH(L65)+1,DAY(L65)),""),"")
B67: =IF(B66<$G$13,B66+1,"") | D67: =IF(PERIOD<>"",($F$43/$B$70),"") | E67: =IF(NOT(B67=M52),$D$43*(($B$70-(B67-1))/((($B$70+1)/2)*$B$70)),"") | G67: =IF(NOT(B67=M53),D67-F67,"") | J67: =J66-G67 -> #VALUE! | K67: =IF(WEEKDAY(L67,2)=1,"Monday",IF(WEEKDAY(L67,2)=2,"Tuesday",IF(WEEKDAY(L67,2)=3,"Wednesday",IF(WEEKDAY(L67,2)=4,"Thursday",IF(WEEKDAY(L67,2)=5,"Friday",IF(WEEKDAY(L67,2)=6,"Saturday",IF(WEEKDAY(L67,2)=7,"Sunday"))))))) -> #VALUE! | L67: =IF(PERIOD<>"",IF(DATE(YEAR(L66),MONTH(L66),DAY(L66))<=$L$43,DATE(YEAR(L66),MONTH(L66)+1,DAY(L66)),""),"")
B68: =IF(B67<$G$13,B67+1,"") | D68: =IF(PERIOD<>"",($F$43/$B$70),"") | E68: =IF(NOT(B68=M53),$D$43*(($B$70-(B68-1))/((($B$70+1)/2)*$B$70)),"") | G68: =IF(NOT(B68=M54),D68-F68,"") | J68: =J67-G68 -> #VALUE! | K68: =IF(WEEKDAY(L68,2)=1,"Monday",IF(WEEKDAY(L68,2)=2,"Tuesday",IF(WEEKDAY(L68,2)=3,"Wednesday",IF(WEEKDAY(L68,2)=4,"Thursday",IF(WEEKDAY(L68,2)=5,"Friday",IF(WEEKDAY(L68,2)=6,"Saturday",IF(WEEKDAY(L68,2)=7,"Sunday"))))))) -> #VALUE! | L68: =IF(PERIOD<>"",IF(DATE(YEAR(L67),MONTH(L67),DAY(L67))<=$L$43,DATE(YEAR(L67),MONTH(L67)+1,DAY(L67)),""),"")
B69: =IF(B68<$G$13,B68+1,"") | D69: =IF(PERIOD<>"",($F$43/$B$70),"") | E69: =IF(NOT(B69=M45),$D$43*(($B$70-(B69-1))/((($B$70+1)/2)*$B$70)),"") | G69: =IF(NOT(B69=M46),D69-F69,"") | J69: =J68-G69 -> #VALUE! | L69: =IF(PERIOD<>"",IF(DATE(YEAR(L59),MONTH(L59),DAY(L59))<=$L$43,DATE(YEAR(L59),MONTH(L59)+1,DAY(L59)),""),"")
B70: =G13 -> 12 | D70: =F43 -> 95003.016 | E70: =SUM(E45:F69) -> 14049.306 | G70: =SUM(G45:H69) -> 80953.71
B72: IMPORTANT REMINDERS:

Sheet Semi Monthly -client copy
A4: =UPPER("Computation Sheet and Payment Schedule") -> COMPUTATION SHEET AND PAYMENT SCHEDULE | K4: =DATEDIF(H8,Maturitydate,"D") -> 386 | L4: =Terms*30 -> 360
A5: NAME | C5: ADDRESS | E5: TYPE OF LOAN | H5: TERMS
A6: =IF(OR_NAME<>"",Client_Name &" or " & OR_NAME,Client_Name) -> ** or ** | C6: =PROPER('Master data Input'!C8) -> ** | F6: =Type_of_Loan&TEXT(IF(Express="YES","-EXPRESS",""),"") -> SML | H6: In months | I6: ='Master data Input'!K10 -> 12 | J6: =Terms -> 12
H7: from | I7: to
H8: =Date_Released_SM -> 43265 | I8: =Maturitydate_SM -> 43651 | M8: ='Master data Input'!F30 -> 46342 | N8: end of term | O8: =I6 -> 12
F9: # of payments | H9: ='Master data Input'!K12 -> 12
M10: =IF(U23<H8,H8,U23) -> 43265
A11: COMPUTATION OF NET PROCEEDS
W12: 7
A13: Principal/ Amount Financed | F13: =IF(get_loan_amount="NET AMOUNT",get_gross_amount,Loan_Amount) -> 80953.71
A14: Less: Deduction
A15: Interest | G15: New | I15: =Renewal -> No
B16: =Interest -> 0.03 | C16: ="from"&TEXT(Date_Released," mm/dd/yyyy")&" to "&TEXT(Date_released2," mm/dd/yyyy") -> from 03/02/2026 to 06/14/2018 | E16: =IF(upfront="YES",'Master data Input'!K24,IF(Type_of_Loan="BL-SA",0,ROUND(Principal_Amount*(Interest/30)*DATEDIF(Date_Released,'Monthly -client copy'!Date_released2,"d"),2))) -> 1214.31 | G16: Renewal Nth loan | I16: ='Master data Input'!F18 -> 0 | J16: =E16+C41/A41-(360/DATEDIF(H8,I8,"d")) -> 1213.5509 | L16: =DATEDIF(H8,B46,"d") -> #NUM! | M16: days from loan release and 1st payment
A17: Processing Fee | C17: =Processing_Fee_in_Percentage -> 0.075 | E17: =Principal_Amount*Percent_processingfee -> 6071.5283 | G17: Installment Type | I17: =Semi_Monthly_SM -> Monthly | L17: =DATEDIF(H8,M10,"D") -> 0
A18: Account Management Fee | E18: =Account_Management_fee -> Auto compute**
A19: Doc fee | E19: =Docfee_Yes_or_No -> 500
A20: Notarial fee | C20: =IF(L4<K4," NUMBER OF DAYS EXCEEDS","") -> NUMBER OF DAYS EXCEEDS | E20: =Notarial_Fee -> 500 | G20: Check No.
A21: ='Master data Input'!B42 -> MLRI -Insurance | E21: =Insurance -> Auto compute**
A22: ='Master data Input'!B45 -> Miscellaneous | E22: ='Master data Input'!C45 -> 500 | L22: =DATEDIF(M10,M8,"D") -> 3077
A23: Total Finance charge | E23: =SUM(E16:E22) -> 8785.8383 | G23: PN no. | H23: ="PN-"&TEXT('Master data Input'!F10,"0000- ")&TEXT(" "," ")&'Master data Input'!C14 -> PN-. SML | L23: =DATEDIF(H8,M8,"D") -> 3077 | U23: =DATE(YEAR(B46),MONTH(B46),DAY(B46)-30) -> 42643
A25: Others: | G25: Branch: | H25: ='Master data Input'!F38 -> 0 | P25: =TEXT($L$16,"0")&"/"&TEXT($L$17,"0")&"/"&TEXT($L$22,"0")&"/"&TEXT($L$23,"0") -> #NUM! | X25: =45000*0.15*(305/360) -> 5718.75
A26: =Cash_Advance -> Cash Advance | E26: =Advanced_Payment -> 0 | L26: =DATEDIF(M10,B46,"d") -> #NUM!
A27: ='Master data Input'!B12 -> Outstanding Balance from previous loan | E27: =Outstanding_Balance_from_previous_loan -> 0
F28: =Total_Finance_Charge+SUM($E$26:$E$28) -> 8785.8383
G29: MODE OF PAYMENT: | I29: ='Master data Input'!F42 -> 0
A30: Net Proceeds | F30: =Principal_Amount-Total_Deduction -> 72167.872
M31: IF('Master data Input'!B35="YES",ROUNDUP(F16*0.0015,0),"0") | U31: DATEDIF(H11,I11,"D")
A32: % of Finance charges to Total Amount Financed | F32: =Total_Finance_Charge/Principal_Amount -> 0.10852916
A33: Contractual Interest Rate per Month | F33: =Contractual_Rate -> 0.037
A34: Equivalent Add-on Interest Rate per Month | F34: =Interest -> 0.03
A35: Effective Annual Rate (EIR) | F35: =EIR -> 0.661088 | M35: IF(1200>O27,1200,O27)
A36: Effective Monthly Interest Rate (MIR) | F36: =MIR -> 0.065489269 | G36: Release Date: | I36: =Date_Released -> 46083
G37: Agent: | H37: =UPPER(Agents)
A38: SCHEDULE OF PAYMENT
N39: =C41+E16 -> 15263.616 | O39: 11667
A40: Principal / Amount of Loan | C40: Interest Due on Loans | E40: Total Amount Payable | X40: =DATE(YEAR(U17),MONTH(U17)+1,DAY(U17)) -> 31
A41: =Principal_Amount -> 80953.71 | C41: ='computation sheet'!C37 -> 14049.306 | E41: =IF(Type_of_Loan="BL-SA",Amount_of_Loan,Loan_Amount+Total_UII) -> 95003.016 | J41: =DATE(YEAR($B$46),MONTH($B$46)+($H$9-1),DAY($B$46)) -> 43008 | K41: w/out adjustment
A43: Period | B43: Due Date | C43: Gross Loan | D43: Amortization | E43: Interest | F43: Principal | G43: Other Charges | I43: Balance
C44: =Loan_Amount -> 80953.71 | I44: =Loan_Amount -> 80953.71
A45: 0 | G45: ='Semi Monthly -client copy'!Total_Deduction -> 8785.8383 | I45: =Loan_Amount -> 80953.71 | N45: =D61/12 -> 7916.918
A46: 1 | B46: 42673 | D46: =IF(B46<>"",(-'computation sheet'!$C$36/$H$9),"") -> 7916.918 | E46: ='Semi Monthly 3 SL'!E45:F45 -> 2161.4317 | F46: =IF(NOT(A46=AA24),D46-E46,"") -> 5755.4863 | I46: =IF(PERIOD<>"",(I45-F46),"") -> 75198.224 | K46: =IF(WEEKDAY(L46,2)=1,"Monday",IF(WEEKDAY(L46,2)=2,"Tuesday",IF(WEEKDAY(L46,2)=3,"Wednesday",IF(WEEKDAY(L46,2)=4,"Thursday",IF(WEEKDAY(L46,2)=5,"Friday",IF(WEEKDAY(L46,2)=6,"Saturday",IF(WEEKDAY(L46,2)=7,"Sunday"))))))) -> Thursday | L46: ='Master data Input'!C30 -> 46128 | N46: =D62/12 -> 0
A47: =IF(A46<$H$9,A46+1,"") -> 2 | B47: 42673 | D47: =IF(B47<>"",(-'computation sheet'!$C$36/$H$9),"") -> 7916.918 | E47: ='Semi Monthly 3 SL'!E46:F46 -> 1981.3124 | F47: =IF(NOT(A47=AA27),D47-E47,"") -> 5935.6056 | I47: =IF(PERIOD<>"",(I46-F47),"") -> 69262.618 | K47: =IF(WEEKDAY(L47,2)=1,"Monday",IF(WEEKDAY(L47,2)=2,"Tuesday",IF(WEEKDAY(L47,2)=3,"Wednesday",IF(WEEKDAY(L47,2)=4,"Thursday",IF(WEEKDAY(L47,2)=5,"Friday",IF(WEEKDAY(L47,2)=6,"Saturday",IF(WEEKDAY(L47,2)=7,"Sunday"))))))) -> #VALUE! | L47: =IF(PERIOD<>"",IF(DATE(YEAR(L46),MONTH(L46),DAY(L46))<=$J$41,DATE(YEAR(L46),MONTH(L46)+1,DAY(L46)),""),"")
A48: =IF(A47<$H$9,A47+1,"") -> 3 | B48: 42689 | D48: =IF(B48<>"",(-'computation sheet'!$C$36/$H$9),"") -> 7916.918 | E48: ='Semi Monthly 3 SL'!E47:F47 -> 1801.1931 | F48: =IF(NOT(A48=AA29),D48-E48,"") -> 6115.7249 | I48: =IF(PERIOD<>"",(I47-F48),"") -> 63146.893 | K48: =IF(WEEKDAY(L48,2)=1,"Monday",IF(WEEKDAY(L48,2)=2,"Tuesday",IF(WEEKDAY(L48,2)=3,"Wednesday",IF(WEEKDAY(L48,2)=4,"Thursday",IF(WEEKDAY(L48,2)=5,"Friday",IF(WEEKDAY(L48,2)=6,"Saturday",IF(WEEKDAY(L48,2)=7,"Sunday"))))))) -> #VALUE! | L48: =IF(PERIOD<>"",IF(DATE(YEAR(L47),MONTH(L47),DAY(L47))<=$J$41,DATE(YEAR(L47),MONTH(L47)+1,DAY(L47)),""),"") -> #VALUE!
A49: =IF(A48<$H$9,A48+1,"") -> 4 | B49: 42704 | D49: =IF(B49<>"",(-'computation sheet'!$C$36/$H$9),"") -> 7916.918 | E49: ='Semi Monthly 3 SL'!E48:F48 -> 1621.0738 | F49: =IF(NOT(A49=AA30),D49-E49,"") -> 6295.8442 | I49: =IF(PERIOD<>"",(I48-F49),"") -> 56851.049 | K49: =IF(WEEKDAY(L49,2)=1,"Monday",IF(WEEKDAY(L49,2)=2,"Tuesday",IF(WEEKDAY(L49,2)=3,"Wednesday",IF(WEEKDAY(L49,2)=4,"Thursday",IF(WEEKDAY(L49,2)=5,"Friday",IF(WEEKDAY(L49,2)=6,"Saturday",IF(WEEKDAY(L49,2)=7,"Sunday"))))))) -> #VALUE! | L49: =IF(PERIOD<>"",IF(DATE(YEAR(L48),MONTH(L48),DAY(L48))<=$J$41,DATE(YEAR(L48),MONTH(L48)+1,DAY(L48)),""),"") -> #VALUE!
A50: =IF(A49<$H$9,A49+1,"") -> 5 | B50: 42719 | D50: =IF(B50<>"",(-'computation sheet'!$C$36/$H$9),"") -> 7916.918 | E50: ='Semi Monthly 3 SL'!E49:F49 -> 1440.9545 | F50: =IF(NOT(A50=AA31),D50-E50,"") -> 6475.9635 | I50: =IF(PERIOD<>"",(I49-F50),"") -> 50375.085 | K50: =IF(WEEKDAY(L50,2)=1,"Monday",IF(WEEKDAY(L50,2)=2,"Tuesday",IF(WEEKDAY(L50,2)=3,"Wednesday",IF(WEEKDAY(L50,2)=4,"Thursday",IF(WEEKDAY(L50,2)=5,"Friday",IF(WEEKDAY(L50,2)=6,"Saturday",IF(WEEKDAY(L50,2)=7,"Sunday"))))))) -> #VALUE! | L50: =IF(PERIOD<>"",IF(DATE(YEAR(L49),MONTH(L49),DAY(L49))<=$J$41,DATE(YEAR(L49),MONTH(L49)+1,DAY(L49)),""),"") -> #VALUE!
A51: =IF(A50<$H$9,A50+1,"") -> 6 | B51: 42734 | D51: =IF(B51<>"",(-'computation sheet'!$C$36/$H$9),"") -> 7916.918 | E51: ='Semi Monthly 3 SL'!E50:F50 -> 1260.8352 | F51: =IF(NOT(A51=AA32),D51-E51,"") -> 6656.0828 | I51: =IF(PERIOD<>"",(I50-F51),"") -> 43719.003 | K51: =IF(WEEKDAY(L51,2)=1,"Monday",IF(WEEKDAY(L51,2)=2,"Tuesday",IF(WEEKDAY(L51,2)=3,"Wednesday",IF(WEEKDAY(L51,2)=4,"Thursday",IF(WEEKDAY(L51,2)=5,"Friday",IF(WEEKDAY(L51,2)=6,"Saturday",IF(WEEKDAY(L51,2)=7,"Sunday"))))))) -> #VALUE! | L51: =IF(PERIOD<>"",IF(DATE(YEAR(L50),MONTH(L50),DAY(L50))<=$J$41,DATE(YEAR(L50),MONTH(L50)+1,DAY(L50)),""),"") -> #VALUE!
A52: =IF(A51<$H$9,A51+1,"") -> 7 | B52: 42750 | D52: =IF(B52<>"",(-'computation sheet'!$C$36/$H$9),"") -> 7916.918 | E52: ='Semi Monthly 3 SL'!E51:F51 -> 1080.7159 | F52: =IF(NOT(A52=AA35),D52-E52,"") -> 6836.2022 | I52: =IF(PERIOD<>"",(I51-F52),"") -> 36882.8 | K52: =IF(WEEKDAY(L52,2)=1,"Monday",IF(WEEKDAY(L52,2)=2,"Tuesday",IF(WEEKDAY(L52,2)=3,"Wednesday",IF(WEEKDAY(L52,2)=4,"Thursday",IF(WEEKDAY(L52,2)=5,"Friday",IF(WEEKDAY(L52,2)=6,"Saturday",IF(WEEKDAY(L52,2)=7,"Sunday"))))))) -> #VALUE! | L52: =IF(PERIOD<>"",IF(DATE(YEAR(L51),MONTH(L51),DAY(L51))<=$J$41,DATE(YEAR(L51),MONTH(L51)+1,DAY(L51)),""),"") -> #VALUE!
A53: =IF(A52<$H$9,A52+1,"") -> 8 | B53: 42765 | D53: =IF(B53<>"",(-'computation sheet'!$C$36/$H$9),"") -> 7916.918 | E53: ='Semi Monthly 3 SL'!E52:F52 -> 900.59656 | F53: =IF(NOT(A53=AA36),D53-E53,"") -> 7016.3215 | I53: =IF(PERIOD<>"",(I52-F53),"") -> 29866.479 | K53: =IF(WEEKDAY(L53,2)=1,"Monday",IF(WEEKDAY(L53,2)=2,"Tuesday",IF(WEEKDAY(L53,2)=3,"Wednesday",IF(WEEKDAY(L53,2)=4,"Thursday",IF(WEEKDAY(L53,2)=5,"Friday",IF(WEEKDAY(L53,2)=6,"Saturday",IF(WEEKDAY(L53,2)=7,"Sunday"))))))) -> #VALUE! | L53: =IF(PERIOD<>"",IF(DATE(YEAR(L52),MONTH(L52),DAY(L52))<=$J$41,DATE(YEAR(L52),MONTH(L52)+1,DAY(L52)),""),"") -> #VALUE!
A54: =IF(A53<$H$9,A53+1,"") -> 9 | B54: 42781 | D54: =IF(B54<>"",(-'computation sheet'!$C$36/$H$9),"") -> 7916.918 | E54: ='Semi Monthly 3 SL'!E53:F53 -> 720.47725 | F54: =IF(NOT(A54=AA37),D54-E54,"") -> 7196.4408 | I54: =IF(PERIOD<>"",(I53-F54),"") -> 22670.038 | K54: =IF(WEEKDAY(L54,2)=1,"Monday",IF(WEEKDAY(L54,2)=2,"Tuesday",IF(WEEKDAY(L54,2)=3,"Wednesday",IF(WEEKDAY(L54,2)=4,"Thursday",IF(WEEKDAY(L54,2)=5,"Friday",IF(WEEKDAY(L54,2)=6,"Saturday",IF(WEEKDAY(L54,2)=7,"Sunday"))))))) -> #VALUE! | L54: =IF(PERIOD<>"",IF(DATE(YEAR(L53),MONTH(L53),DAY(L53))<=$J$41,DATE(YEAR(L53),MONTH(L53)+1,DAY(L53)),""),"") -> #VALUE!
A55: =IF(A54<$H$9,A54+1,"") -> 10 | B55: 42794 | D55: =IF(B55<>"",(-'computation sheet'!$C$36/$H$9),"") -> 7916.918 | E55: ='Semi Monthly 3 SL'!E54:F54 -> 540.35794 | F55: =IF(NOT(A55=AA38),D55-E55,"") -> 7376.5601 | I55: =IF(PERIOD<>"",(I54-F55),"") -> 15293.478 | K55: =IF(WEEKDAY(L55,2)=1,"Monday",IF(WEEKDAY(L55,2)=2,"Tuesday",IF(WEEKDAY(L55,2)=3,"Wednesday",IF(WEEKDAY(L55,2)=4,"Thursday",IF(WEEKDAY(L55,2)=5,"Friday",IF(WEEKDAY(L55,2)=6,"Saturday",IF(WEEKDAY(L55,2)=7,"Sunday"))))))) -> #VALUE! | L55: =IF(PERIOD<>"",IF(DATE(YEAR(L54),MONTH(L54),DAY(L54))<=$J$41,DATE(YEAR(L54),MONTH(L54)+1,DAY(L54)),""),"") -> #VALUE!
A56: =IF(A55<$H$9,A55+1,"") -> 11 | B56: 42809 | D56: =IF(B56<>"",(-'computation sheet'!$C$36/$H$9),"") -> 7916.918 | E56: ='Semi Monthly 3 SL'!E55:F55 -> 360.23862 | F56: =IF(NOT(A56=AA39),D56-E56,"") -> 7556.6794 | I56: =IF(PERIOD<>"",(I55-F56),"") -> 7736.7987 | K56: =IF(WEEKDAY(L56,2)=1,"Monday",IF(WEEKDAY(L56,2)=2,"Tuesday",IF(WEEKDAY(L56,2)=3,"Wednesday",IF(WEEKDAY(L56,2)=4,"Thursday",IF(WEEKDAY(L56,2)=5,"Friday",IF(WEEKDAY(L56,2)=6,"Saturday",IF(WEEKDAY(L56,2)=7,"Sunday"))))))) -> #VALUE! | L56: =IF(PERIOD<>"",IF(DATE(YEAR(L55),MONTH(L55),DAY(L55))<=$J$41,DATE(YEAR(L55),MONTH(L55)+1,DAY(L55)),""),"") -> #VALUE!
A57: =IF(A56<$H$9,A56+1,"") -> 12 | B57: 42824 | D57: =IF(B57<>"",(-'computation sheet'!$C$36/$H$9),"") -> 7916.918 | E57: ='Semi Monthly 3 SL'!E56:F56 -> 180.11931 | F57: =IF(NOT(A57=AA40),D57-E57,"") -> 7736.7987 | I57: =IF(PERIOD<>"",(I56-F57),"") -> -4.5474735e-12 | K57: =IF(WEEKDAY(L57,2)=1,"Monday",IF(WEEKDAY(L57,2)=2,"Tuesday",IF(WEEKDAY(L57,2)=3,"Wednesday",IF(WEEKDAY(L57,2)=4,"Thursday",IF(WEEKDAY(L57,2)=5,"Friday",IF(WEEKDAY(L57,2)=6,"Saturday",IF(WEEKDAY(L57,2)=7,"Sunday"))))))) -> #VALUE! | L57: =IF(PERIOD<>"",IF(DATE(YEAR(L56),MONTH(L56),DAY(L56))<=$J$41,DATE(YEAR(L56),MONTH(L56)+1,DAY(L56)),""),"") -> #VALUE!
A58: =IF(A57<$H$9,A57+1,"") | B58: ='Semi Monthly SL'!B54 | D58: =IF(B58<>"",(-'computation sheet'!$C$36/$H$9),"") | E58: ='Semi Monthly SL'!E54 | F58: =IF(NOT(A58=AA41),D58-E58,"") | I58: =IF(PERIOD<>"",(I57-F58),"") | K58: =IF(WEEKDAY(L58,2)=1,"Monday",IF(WEEKDAY(L58,2)=2,"Tuesday",IF(WEEKDAY(L58,2)=3,"Wednesday",IF(WEEKDAY(L58,2)=4,"Thursday",IF(WEEKDAY(L58,2)=5,"Friday",IF(WEEKDAY(L58,2)=6,"Saturday",IF(WEEKDAY(L58,2)=7,"Sunday"))))))) -> #VALUE! | L58: =IF(PERIOD<>"",IF(DATE(YEAR(L57),MONTH(L57),DAY(L57))<=$J$41,DATE(YEAR(L57),MONTH(L57)+1,DAY(L57)),""),"")
A59: =IF(A58<$H$9,A58+1,"") | B59: ='Semi Monthly SL'!B55 | D59: =IF(B59<>"",(-'computation sheet'!$C$36/$H$9),"") | E59: ='Semi Monthly SL'!E55 | F59: =IF(NOT(A59=AA42),D59-E59,"") | I59: =IF(PERIOD<>"",(I58-F59),"") | K59: =IF(WEEKDAY(L59,2)=1,"Monday",IF(WEEKDAY(L59,2)=2,"Tuesday",IF(WEEKDAY(L59,2)=3,"Wednesday",IF(WEEKDAY(L59,2)=4,"Thursday",IF(WEEKDAY(L59,2)=5,"Friday",IF(WEEKDAY(L59,2)=6,"Saturday",IF(WEEKDAY(L59,2)=7,"Sunday"))))))) -> #VALUE! | L59: =IF(PERIOD<>"",IF(DATE(YEAR(L58),MONTH(L58),DAY(L58))<=$J$41,DATE(YEAR(L58),MONTH(L58)+1,DAY(L58)),""),"")
A60: =IF(A59<$H$9,A59+1,"") | B60: ='Semi Monthly SL'!B56 | D60: =IF(B60<>"",(-'computation sheet'!$C$36/$H$9),"") | E60: ='Semi Monthly SL'!E56 | F60: =IF(NOT(A60=AA43),D60-E60,"") | I60: =IF(PERIOD<>"",(I59-F60),"") | K60: =IF(WEEKDAY(L60,2)=1,"Monday",IF(WEEKDAY(L60,2)=2,"Tuesday",IF(WEEKDAY(L60,2)=3,"Wednesday",IF(WEEKDAY(L60,2)=4,"Thursday",IF(WEEKDAY(L60,2)=5,"Friday",IF(WEEKDAY(L60,2)=6,"Saturday",IF(WEEKDAY(L60,2)=7,"Sunday"))))))) -> #VALUE! | L60: =IF(PERIOD<>"",IF(DATE(YEAR(L59),MONTH(L59),DAY(L59))<=$J$41,DATE(YEAR(L59),MONTH(L59)+1,DAY(L59)),""),"")
A61: =H9 -> 12 | D61: =SUM(D46:D60) -> 95003.016 | E61: =SUM(E46:E60) -> 14049.306 | F61: =SUM(F46:F60) -> 80953.71
A63: ="Interest Rate of " & (Contractual_Rate*100) &"% is equivalent to the Add On Rate of " & ROUND((((((Total_InterestRate/Principal_Amount)/Monthly_Inst))))*100,2) & "% per Month" -> Interest Rate of 3.7% is equivalent to the Add On Rate of 2.17% per Month
A65: Prepared / Verified by: | E65: Noted by:
A68: Released by: | E68: Received Copy:
A72: IMPORTANT REMINDERS:

Sheet Semi Monthly
A8: =UPPER("Computation Sheet and Payment Schedule") -> COMPUTATION SHEET AND PAYMENT SCHEDULE
A9: NAME | C9: ADDRESS | E9: TYPE OF LOAN | H9: TERMS
A10: =IF(OR_NAME<>"",Client_Name &" or " & OR_NAME,Client_Name) -> ** or ** | C10: =PROPER('Master data Input'!C8) -> ** | F10: =Type_of_Loan&TEXT(IF(Express="YES","-EXPRESS",""),"") -> SML | H10: In months | I10: =DATEDIF(Start_Payment,Maturitydate,"d")/30 -> 7.1333333 | J10: =Terms -> 7.1333333
F11: Interest/mo | G11: =Interest -> 0.03 | H11: from | I11: to
A12: =IF(UPPER(OR_NAME)<>" ",UPPER(OR_NAME),".") -> ** | H12: =Date_Released -> 46083 | I12: =MaturityDate_data_input -> 46342 | M12: ='Master data Input'!F30 -> 46342 | N12: end of term | O12: =I10 -> 7.1333333
F13: # of payments | G13: =Number_of_Amortization -> 8
M14: =IF(U27<H12,H12,U27) -> 46098
A15: COMPUTATION OF NET PROCEEDS
W16: 7
A17: Principal/ Amount Financed | F17: =Loan_Amount -> 80953.71
A19: Less Interest and Other Charges | G19: New | I19: =IF(I20>0,"NO", "YES") -> NO
A20: Interest | B20: =Interest -> 0.03 | C20: ="from"&TEXT(Date_Released," mm/dd/yyyy")&" to "&TEXT(Date_released2," mm/dd/yyyy") -> from 03/02/2026 to 03/17/2026 | E20: =IF(Type_of_Loan="BL-SA",ROUND(Principal_Amount*(Interest/30)*DATEDIF(Date_Released,MaturityDate1,"D"),0),ROUND(Principal_Amount*(Interest/30)*DATEDIF(Date_Released,Date_released2,"d"),0)) -> 1214 | G20: Renewal Nth loan | I20: ='Master data Input'!C18 -> No | J20: =E20+D43/B43-(360/DATEDIF(H12,I12,"d")) -> 1212.854 | L20: =DATEDIF(H12,C45,"d") -> 45 | M20: days from loan release and 1st payment
A21: Processing Fee | C21: =Processing_Fee_in_Percentage -> 0.075 | E21: =Processing_Fee_in_Percentage*Principal_Amount -> 6071.5283 | G21: Installment Type | I21: =Installment_Type -> Monthly | L21: =DATEDIF(H12,M14,"D") -> 15
A22: Account Management Fee | E22: =Account_Management_fee -> Auto compute**
A23: Notarial fee | E23: =Notarial_Fee -> 500
A24: Doc fee | E24: =IF(Docfee_Yes_or_No="YES",ROUNDUP(Principal_Amount/200,0),0) -> 0
A25: ='Master data Input'!B42 -> MLRI -Insurance | E25: =Insurance -> Auto compute**
A26: ='Master data Input'!B45 -> Miscellaneous | E26: ='Master data Input'!C45 -> 500 | G26: Check No. | L26: =DATEDIF(M14,M12,"D") -> 244
A27: Total Finance charge | E27: =SUM(E20:E26) -> 8285.5282 | L27: =DATEDIF(H12,M12,"D") -> 259 | U27: =DATE(YEAR(C45),MONTH(C45),DAY(C45)-30) -> 46098
A28: Others: | G28: PN no. | H28: ="PN-"&TEXT('Master data Input'!F10,"0000- ")&TEXT(" "," ")&'Master data Input'!C14 -> PN-. SML
A29: ='Master data Input'!B12 -> Outstanding Balance from previous loan | E29: =Outstanding_Balance_from_previous_loan -> 0 | P29: =TEXT($L$20,"0")&"/"&TEXT($L$21,"0")&"/"&TEXT($L$26,"0")&"/"&TEXT($L$27,"0") -> 45/15/244/259 | X29: =45000*0.15*(305/360) -> 5718.75
A30: Cash Advanced | E30: =Advanced_Payment -> 0 | L30: =DATEDIF(M14,C45,"d") -> 30
F33: =Total_Finance_Charge+SUM($E$29:$E$33) -> 8285.5282 | G33: MODE OF PAYMENT: | I33: ='Master data Input'!F42 -> 0
A35: Net Proceeds | F35: =Principal_Amount-Total_Deduction -> 72668.182 | M35: IF('Master data Input'!B35="YES",ROUNDUP(F16*0.0015,0),"0") | U35: DATEDIF(H11,I11,"D")
A37: Effective Rate (per month) | F37: =IF(Grace_Period_Interest=0,(Grace_Period_Interest+Total_UII)/Amount_of_Loan/(DATEDIF(Date_Released,MaturityDate1,"d")/30),(Grace_Period_Interest+Total_UII)/Amount_of_Loan/Term_masterdatainput) -> 0.032374983 | M37: IF(1200>O27,1200,O27)
A38: % of Finance charges to Total Amount Financed | F38: =Total_Finance_Charge/Principal_Amount -> 0.10234896 | G38: Release Date: | I38: =Date_Released -> 46083
G39: Agent: | H39: =UPPER(Agents)
A40: SCHEDULE OF AMORTIZATION
N41: =D43+E20 -> 20967 | O41: 11667
B42: Principal / Amount of Loan | D42: Interest Due on Loans | F42: Total Amount Payable | Y42: =DATE(YEAR(U21),MONTH(U21)+1,DAY(U21)) -> 31
B43: =Principal_Amount -> 80953.71 | D43: =IF(Type_of_Loan="BL-SA",0,IF(Type_of_Loan="QCL",(Principal_Amount*Interest*Term_masterdatainput),ROUND(Principal_Amount*(Interest/30)*DATEDIF(Date_released2,MaturityDate1,"d"),0))) -> 19753 | F43: =IF(Type_of_Loan="BL-SA",Amount_of_Loan,Loan_Amount+Total_UII) -> 100706.71 | K43: =DATE(YEAR($C$45),MONTH($C$45)+($G$13-1),DAY($C$45)) -> 46342 | L43: w/out adjustment
B44: Period | C44: Due Date | D44: amortization | E44: Prepared/ Verified by: | S44: Interest | U44: Principal
B45: 1 | C45: =Start_Payment -> 46128 | D45: =D70-SUM(D46:D69) -> 12590.71 | S45: =IF(NOT(B45=AA27),$D$43*(($B$70-(B45-1))/((($B$70+1)/2)*$B$70)),"") -> 4389.5556 | U45: =IF(NOT(B45=AA28),D45-S45,"") -> 8201.1544 | X45: =IF(WEEKDAY(Y45,2)=1,"Monday",IF(WEEKDAY(Y45,2)=2,"Tuesday",IF(WEEKDAY(Y45,2)=3,"Wednesday",IF(WEEKDAY(Y45,2)=4,"Thursday",IF(WEEKDAY(Y45,2)=5,"Friday",IF(WEEKDAY(Y45,2)=6,"Saturday",IF(WEEKDAY(Y45,2)=7,"Sunday"))))))) -> Thursday | Y45: ='Master data Input'!C30 -> 46128
B46: =IF(B45<$G$13,B45+1,"") -> 2 | C46: =IF(PERIOD<>"",DATE(YEAR(C45),MONTH(C45),DAY(C45)+15),"") -> 46143 | D46: =IF(PERIOD<>"",ROUNDDOWN($F$43/$B$70,0),"") -> 12588 | S46: =IF(NOT(B46=AA28),$D$43*(($B$70-(B46-1))/((($B$70+1)/2)*$B$70)),"") -> 3840.8611 | U46: =IF(NOT(B46=AA31),D46-S46,"") -> 8747.1389 | X46: =IF(WEEKDAY(Y46,2)=1,"Monday",IF(WEEKDAY(Y46,2)=2,"Tuesday",IF(WEEKDAY(Y46,2)=3,"Wednesday",IF(WEEKDAY(Y46,2)=4,"Thursday",IF(WEEKDAY(Y46,2)=5,"Friday",IF(WEEKDAY(Y46,2)=6,"Saturday",IF(WEEKDAY(Y46,2)=7,"Sunday"))))))) -> Saturday | Y46: =IF(PERIOD<>"",IF(DATE(YEAR(Y45),MONTH(Y45),DAY(Y45))<=$K$43,DATE(YEAR(Y45),MONTH(Y45)+1,DAY(Y45)),""),"") -> 46158
B47: =IF(B46<$G$13,B46+1,"") -> 3 | C47: 40918 | D47: =IF(PERIOD<>"",ROUNDDOWN($F$43/$B$70,0),"") -> 12588 | E47: Noted by: | S47: =IF(NOT(B47=AA31),$D$43*(($B$70-(B47-1))/((($B$70+1)/2)*$B$70)),"") -> 3292.1667 | U47: =IF(NOT(B47=AA33),D47-S47,"") -> 9295.8333 | X47: =IF(WEEKDAY(Y47,2)=1,"Monday",IF(WEEKDAY(Y47,2)=2,"Tuesday",IF(WEEKDAY(Y47,2)=3,"Wednesday",IF(WEEKDAY(Y47,2)=4,"Thursday",IF(WEEKDAY(Y47,2)=5,"Friday",IF(WEEKDAY(Y47,2)=6,"Saturday",IF(WEEKDAY(Y47,2)=7,"Sunday"))))))) -> Tuesday | Y47: =IF(PERIOD<>"",IF(DATE(YEAR(Y46),MONTH(Y46),DAY(Y46))<=$K$43,DATE(YEAR(Y46),MONTH(Y46)+1,DAY(Y46)),""),"") -> 46189
B48: =IF(B47<$G$13,B47+1,"") -> 4 | C48: 40933 | D48: =IF(PERIOD<>"",ROUNDDOWN($F$43/$B$70,0),"") -> 12588 | S48: =IF(NOT(B48=AA33),$D$43*(($B$70-(B48-1))/((($B$70+1)/2)*$B$70)),"") -> 2743.4722 | U48: =IF(NOT(B48=AA34),D48-S48,"") -> 9844.5278 | X48: =IF(WEEKDAY(Y48,2)=1,"Monday",IF(WEEKDAY(Y48,2)=2,"Tuesday",IF(WEEKDAY(Y48,2)=3,"Wednesday",IF(WEEKDAY(Y48,2)=4,"Thursday",IF(WEEKDAY(Y48,2)=5,"Friday",IF(WEEKDAY(Y48,2)=6,"Saturday",IF(WEEKDAY(Y48,2)=7,"Sunday"))))))) -> Thursday | Y48: =IF(PERIOD<>"",IF(DATE(YEAR(Y47),MONTH(Y47),DAY(Y47))<=$K$43,DATE(YEAR(Y47),MONTH(Y47)+1,DAY(Y47)),""),"") -> 46219
B49: =IF(B48<$G$13,B48+1,"") -> 5 | C49: =IF(PERIOD<>"",DATE(YEAR(C48),MONTH(C48),DAY(C48)+15),"") -> 40948 | D49: =IF(PERIOD<>"",ROUNDDOWN($F$43/$B$70,0),"") -> 12588 | S49: =IF(NOT(B49=AA34),$D$43*(($B$70-(B49-1))/((($B$70+1)/2)*$B$70)),"") -> 2194.7778 | U49: =IF(NOT(B49=AA35),D49-S49,"") -> 10393.222 | X49: =IF(WEEKDAY(Y49,2)=1,"Monday",IF(WEEKDAY(Y49,2)=2,"Tuesday",IF(WEEKDAY(Y49,2)=3,"Wednesday",IF(WEEKDAY(Y49,2)=4,"Thursday",IF(WEEKDAY(Y49,2)=5,"Friday",IF(WEEKDAY(Y49,2)=6,"Saturday",IF(WEEKDAY(Y49,2)=7,"Sunday"))))))) -> Sunday | Y49: =IF(PERIOD<>"",IF(DATE(YEAR(Y48),MONTH(Y48),DAY(Y48))<=$K$43,DATE(YEAR(Y48),MONTH(Y48)+1,DAY(Y48)),""),"") -> 46250
B50: =IF(B49<$G$13,B49+1,"") -> 6 | C50: =IF(PERIOD<>"",DATE(YEAR(C49),MONTH(C49),DAY(C49)+15),"") -> 40963 | D50: =IF(PERIOD<>"",ROUNDDOWN($F$43/$B$70,0),"") -> 12588 | E50: Released by: | S50: =IF(NOT(B50=AA35),$D$43*(($B$70-(B50-1))/((($B$70+1)/2)*$B$70)),"") -> 1646.0833 | U50: =IF(NOT(B50=AA36),D50-S50,"") -> 10941.917 | X50: =IF(WEEKDAY(Y50,2)=1,"Monday",IF(WEEKDAY(Y50,2)=2,"Tuesday",IF(WEEKDAY(Y50,2)=3,"Wednesday",IF(WEEKDAY(Y50,2)=4,"Thursday",IF(WEEKDAY(Y50,2)=5,"Friday",IF(WEEKDAY(Y50,2)=6,"Saturday",IF(WEEKDAY(Y50,2)=7,"Sunday"))))))) -> Wednesday | Y50: =IF(PERIOD<>"",IF(DATE(YEAR(Y49),MONTH(Y49),DAY(Y49))<=$K$43,DATE(YEAR(Y49),MONTH(Y49)+1,DAY(Y49)),""),"") -> 46281
B51: =IF(B50<$G$13,B50+1,"") -> 7 | C51: =IF(PERIOD<>"",DATE(YEAR(C50),MONTH(C50),DAY(C50)+15),"") -> 40978 | D51: =IF(PERIOD<>"",ROUNDDOWN($F$43/$B$70,0),"") -> 12588 | S51: =IF(NOT(B51=AA36),$D$43*(($B$70-(B51-1))/((($B$70+1)/2)*$B$70)),"") -> 1097.3889 | U51: =IF(NOT(B51=AA37),D51-S51,"") -> 11490.611 | X51: =IF(WEEKDAY(Y51,2)=1,"Monday",IF(WEEKDAY(Y51,2)=2,"Tuesday",IF(WEEKDAY(Y51,2)=3,"Wednesday",IF(WEEKDAY(Y51,2)=4,"Thursday",IF(WEEKDAY(Y51,2)=5,"Friday",IF(WEEKDAY(Y51,2)=6,"Saturday",IF(WEEKDAY(Y51,2)=7,"Sunday"))))))) -> Friday | Y51: =IF(PERIOD<>"",IF(DATE(YEAR(Y50),MONTH(Y50),DAY(Y50))<=$K$43,DATE(YEAR(Y50),MONTH(Y50)+1,DAY(Y50)),""),"") -> 46311
B52: =IF(B51<$G$13,B51+1,"") -> 8 | C52: =IF(PERIOD<>"",DATE(YEAR(C51),MONTH(C51),DAY(C51)+15),"") -> 40993 | D52: =IF(PERIOD<>"",ROUNDDOWN($F$43/$B$70,0),"") -> 12588 | S52: =IF(NOT(B52=AA37),$D$43*(($B$70-(B52-1))/((($B$70+1)/2)*$B$70)),"") -> 548.69444 | U52: =IF(NOT(B52=AA38),D52-S52,"") -> 12039.306 | X52: =IF(WEEKDAY(Y52,2)=1,"Monday",IF(WEEKDAY(Y52,2)=2,"Tuesday",IF(WEEKDAY(Y52,2)=3,"Wednesday",IF(WEEKDAY(Y52,2)=4,"Thursday",IF(WEEKDAY(Y52,2)=5,"Friday",IF(WEEKDAY(Y52,2)=6,"Saturday",IF(WEEKDAY(Y52,2)=7,"Sunday"))))))) -> Monday | Y52: =IF(PERIOD<>"",IF(DATE(YEAR(Y51),MONTH(Y51),DAY(Y51))<=$K$43,DATE(YEAR(Y51),MONTH(Y51)+1,DAY(Y51)),""),"") -> 46342
B53: =IF(B52<$G$13,B52+1,"") | C53: =IF(PERIOD<>"",DATE(YEAR(C52),MONTH(C52),DAY(C52)+15),"") | D53: =IF(PERIOD<>"",ROUNDDOWN($F$43/$B$70,0),"") | E53: Received Copy: | S53: =IF(NOT(B53=AA38),$D$43*(($B$70-(B53-1))/((($B$70+1)/2)*$B$70)),"") | U53: =IF(NOT(B53=AA39),D53-S53,"") | X53: =IF(WEEKDAY(Y53,2)=1,"Monday",IF(WEEKDAY(Y53,2)=2,"Tuesday",IF(WEEKDAY(Y53,2)=3,"Wednesday",IF(WEEKDAY(Y53,2)=4,"Thursday",IF(WEEKDAY(Y53,2)=5,"Friday",IF(WEEKDAY(Y53,2)=6,"Saturday",IF(WEEKDAY(Y53,2)=7,"Sunday"))))))) -> #VALUE! | Y53: =IF(PERIOD<>"",IF(DATE(YEAR(Y52),MONTH(Y52),DAY(Y52))<=$K$43,DATE(YEAR(Y52),MONTH(Y52)+1,DAY(Y52)),""),"")
B54: =IF(B53<$G$13,B53+1,"") | C54: =IF(PERIOD<>"",DATE(YEAR(C53),MONTH(C53),DAY(C53)+15),"") | D54: =IF(PERIOD<>"",ROUNDDOWN($F$43/$B$70,0),"") | S54: =IF(NOT(B54=AA39),$D$43*(($B$70-(B54-1))/((($B$70+1)/2)*$B$70)),"") | U54: =IF(NOT(B54=AA40),D54-S54,"") | X54: =IF(WEEKDAY(Y54,2)=1,"Monday",IF(WEEKDAY(Y54,2)=2,"Tuesday",IF(WEEKDAY(Y54,2)=3,"Wednesday",IF(WEEKDAY(Y54,2)=4,"Thursday",IF(WEEKDAY(Y54,2)=5,"Friday",IF(WEEKDAY(Y54,2)=6,"Saturday",IF(WEEKDAY(Y54,2)=7,"Sunday"))))))) -> #VALUE! | Y54: =IF(PERIOD<>"",IF(DATE(YEAR(Y53),MONTH(Y53),DAY(Y53))<=$K$43,DATE(YEAR(Y53),MONTH(Y53)+1,DAY(Y53)),""),"")
B55: =IF(B54<$G$13,B54+1,"") | C55: =IF(PERIOD<>"",DATE(YEAR(C54),MONTH(C54),DAY(C54)+15),"") | D55: =IF(PERIOD<>"",ROUNDDOWN($F$43/$B$70,0),"") | S55: =IF(NOT(B55=AA40),$D$43*(($B$70-(B55-1))/((($B$70+1)/2)*$B$70)),"") | U55: =IF(NOT(B55=AA41),D55-T55,"") | X55: =IF(WEEKDAY(Y55,2)=1,"Monday",IF(WEEKDAY(Y55,2)=2,"Tuesday",IF(WEEKDAY(Y55,2)=3,"Wednesday",IF(WEEKDAY(Y55,2)=4,"Thursday",IF(WEEKDAY(Y55,2)=5,"Friday",IF(WEEKDAY(Y55,2)=6,"Saturday",IF(WEEKDAY(Y55,2)=7,"Sunday"))))))) -> #VALUE! | Y55: =IF(PERIOD<>"",IF(DATE(YEAR(Y54),MONTH(Y54),DAY(Y54))<=$K$43,DATE(YEAR(Y54),MONTH(Y54)+1,DAY(Y54)),""),"")
B56: =IF(B55<$G$13,B55+1,"") | C56: =IF(PERIOD<>"",DATE(YEAR(C55),MONTH(C55),DAY(C55)+15),"") | D56: =IF(PERIOD<>"",ROUNDDOWN($F$43/$B$70,0),"") | E56: Date: | G56: =Date_Released -> 46083 | S56: =IF(NOT(B56=AA41),$D$43*(($B$70-(B56-1))/((($B$70+1)/2)*$B$70)),"") | U56: =IF(NOT(B56=AA42),D56-T56,"") | X56: =IF(WEEKDAY(Y56,2)=1,"Monday",IF(WEEKDAY(Y56,2)=2,"Tuesday",IF(WEEKDAY(Y56,2)=3,"Wednesday",IF(WEEKDAY(Y56,2)=4,"Thursday",IF(WEEKDAY(Y56,2)=5,"Friday",IF(WEEKDAY(Y56,2)=6,"Saturday",IF(WEEKDAY(Y56,2)=7,"Sunday"))))))) -> #VALUE! | Y56: =IF(PERIOD<>"",IF(DATE(YEAR(Y55),MONTH(Y55),DAY(Y55))<=$K$43,DATE(YEAR(Y55),MONTH(Y55)+1,DAY(Y55)),""),"")
B57: =IF(B56<$G$13,B56+1,"") | C57: =IF(PERIOD<>"",DATE(YEAR(C56),MONTH(C56),DAY(C56)+15),"") | D57: =IF(PERIOD<>"",ROUNDDOWN($F$43/$B$70,0),"") | E57: Remarks | S57: =IF(NOT(B57=AA42),$D$43*(($B$70-(B57-1))/((($B$70+1)/2)*$B$70)),"") | U57: =IF(NOT(B57=AA43),D57-T57,"") | X57: =IF(WEEKDAY(Y57,2)=1,"Monday",IF(WEEKDAY(Y57,2)=2,"Tuesday",IF(WEEKDAY(Y57,2)=3,"Wednesday",IF(WEEKDAY(Y57,2)=4,"Thursday",IF(WEEKDAY(Y57,2)=5,"Friday",IF(WEEKDAY(Y57,2)=6,"Saturday",IF(WEEKDAY(Y57,2)=7,"Sunday"))))))) -> #VALUE! | Y57: =IF(PERIOD<>"",IF(DATE(YEAR(Y56),MONTH(Y56),DAY(Y56))<=$K$43,DATE(YEAR(Y56),MONTH(Y56)+1,DAY(Y56)),""),"")
B58: =IF(B57<$G$13,B57+1,"") | C58: =IF(PERIOD<>"",DATE(YEAR(C57),MONTH(C57),DAY(C57)+15),"") | D58: =IF(PERIOD<>"",ROUNDDOWN($F$43/$B$70,0),"") | S58: =IF(NOT(B58=AA43),$D$43*(($B$70-(B58-1))/((($B$70+1)/2)*$B$70)),"") | U58: =IF(NOT(B58=AA44),D58-T58,"") | X58: =IF(WEEKDAY(Y58,2)=1,"Monday",IF(WEEKDAY(Y58,2)=2,"Tuesday",IF(WEEKDAY(Y58,2)=3,"Wednesday",IF(WEEKDAY(Y58,2)=4,"Thursday",IF(WEEKDAY(Y58,2)=5,"Friday",IF(WEEKDAY(Y58,2)=6,"Saturday",IF(WEEKDAY(Y58,2)=7,"Sunday"))))))) -> #VALUE! | Y58: =IF(PERIOD<>"",IF(DATE(YEAR(Y57),MONTH(Y57),DAY(Y57))<=$K$43,DATE(YEAR(Y57),MONTH(Y57)+1,DAY(Y57)),""),"")
B59: =IF(B58<$G$13,B58+1,"") | C59: =IF(PERIOD<>"",DATE(YEAR(C58),MONTH(C58),DAY(C58)+15),"") | D59: =IF(PERIOD<>"",ROUNDDOWN($F$43/$B$70,0),"") | E59: =IF(Advanced_Payment=0,"","With Advance Payment of P "& Advanced_Payment) | S59: =IF(NOT(B59=AA44),$D$43*(($B$70-(B59-1))/((($B$70+1)/2)*$B$70)),"") | U59: =IF(NOT(B59=AA45),D59-T59,"") | X59: =IF(WEEKDAY(Y59,2)=1,"Monday",IF(WEEKDAY(Y59,2)=2,"Tuesday",IF(WEEKDAY(Y59,2)=3,"Wednesday",IF(WEEKDAY(Y59,2)=4,"Thursday",IF(WEEKDAY(Y59,2)=5,"Friday",IF(WEEKDAY(Y59,2)=6,"Saturday",IF(WEEKDAY(Y59,2)=7,"Sunday"))))))) -> #VALUE! | Y59: =IF(PERIOD<>"",IF(DATE(YEAR(Y58),MONTH(Y58),DAY(Y58))<=$K$43,DATE(YEAR(Y58),MONTH(Y58)+1,DAY(Y58)),""),"")
B60: =IF(B59<$G$13,B59+1,"") | C60: =IF(PERIOD<>"",DATE(YEAR(C59),MONTH(C59),DAY(C59)+15),"") | D60: =IF(PERIOD<>"",ROUNDDOWN($F$43/$B$70,0),"") | S60: =IF(NOT(B60=AA45),$D$43*(($B$70-(B60-1))/((($B$70+1)/2)*$B$70)),"") | U60: =IF(NOT(B60=AA46),D60-T60,"") | X60: =IF(WEEKDAY(Y60,2)=1,"Monday",IF(WEEKDAY(Y60,2)=2,"Tuesday",IF(WEEKDAY(Y60,2)=3,"Wednesday",IF(WEEKDAY(Y60,2)=4,"Thursday",IF(WEEKDAY(Y60,2)=5,"Friday",IF(WEEKDAY(Y60,2)=6,"Saturday",IF(WEEKDAY(Y60,2)=7,"Sunday"))))))) -> #VALUE! | Y60: =IF(PERIOD<>"",IF(DATE(YEAR(Y59),MONTH(Y59),DAY(Y59))<=$K$43,DATE(YEAR(Y59),MONTH(Y59)+1,DAY(Y59)),""),"")
B61: =IF(B60<$G$13,B60+1,"") | C61: =IF(PERIOD<>"",DATE(YEAR(C60),MONTH(C60),DAY(C60)+15),"") | D61: =IF(PERIOD<>"",ROUNDDOWN($F$43/$B$70,0),"") | S61: =IF(NOT(B61=AA46),$D$43*(($B$70-(B61-1))/((($B$70+1)/2)*$B$70)),"") | U61: =IF(NOT(B61=AA47),D61-T61,"") | X61: =IF(WEEKDAY(Y61,2)=1,"Monday",IF(WEEKDAY(Y61,2)=2,"Tuesday",IF(WEEKDAY(Y61,2)=3,"Wednesday",IF(WEEKDAY(Y61,2)=4,"Thursday",IF(WEEKDAY(Y61,2)=5,"Friday",IF(WEEKDAY(Y61,2)=6,"Saturday",IF(WEEKDAY(Y61,2)=7,"Sunday"))))))) -> #VALUE! | Y61: =IF(PERIOD<>"",IF(DATE(YEAR(Y60),MONTH(Y60),DAY(Y60))<=$K$43,DATE(YEAR(Y60),MONTH(Y60)+1,DAY(Y60)),""),"")
B62: =IF(B61<$G$13,B61+1,"") | C62: =IF(PERIOD<>"",DATE(YEAR(C61),MONTH(C61),DAY(C61)+15),"") | D62: =IF(PERIOD<>"",ROUNDDOWN($F$43/$B$70,0),"") | S62: =IF(NOT(B62=AA47),$D$43*(($B$70-(B62-1))/((($B$70+1)/2)*$B$70)),"") | U62: =IF(NOT(B62=AA48),D62-T62,"") | X62: =IF(WEEKDAY(Y62,2)=1,"Monday",IF(WEEKDAY(Y62,2)=2,"Tuesday",IF(WEEKDAY(Y62,2)=3,"Wednesday",IF(WEEKDAY(Y62,2)=4,"Thursday",IF(WEEKDAY(Y62,2)=5,"Friday",IF(WEEKDAY(Y62,2)=6,"Saturday",IF(WEEKDAY(Y62,2)=7,"Sunday"))))))) -> #VALUE! | Y62: =IF(PERIOD<>"",IF(DATE(YEAR(Y61),MONTH(Y61),DAY(Y61))<=$K$43,DATE(YEAR(Y61),MONTH(Y61)+1,DAY(Y61)),""),"")
B63: =IF(B62<$G$13,B62+1,"") | C63: =IF(PERIOD<>"",DATE(YEAR(C62),MONTH(C62),DAY(C62)+15),"") | D63: =IF(PERIOD<>"",ROUNDDOWN($F$43/$B$70,0),"") | S63: =IF(NOT(B63=AA48),$D$43*(($B$70-(B63-1))/((($B$70+1)/2)*$B$70)),"") | U63: =IF(NOT(B63=AA49),D63-T63,"") | X63: =IF(WEEKDAY(Y63,2)=1,"Monday",IF(WEEKDAY(Y63,2)=2,"Tuesday",IF(WEEKDAY(Y63,2)=3,"Wednesday",IF(WEEKDAY(Y63,2)=4,"Thursday",IF(WEEKDAY(Y63,2)=5,"Friday",IF(WEEKDAY(Y63,2)=6,"Saturday",IF(WEEKDAY(Y63,2)=7,"Sunday"))))))) -> #VALUE! | Y63: =IF(PERIOD<>"",IF(DATE(YEAR(Y62),MONTH(Y62),DAY(Y62))<=$K$43,DATE(YEAR(Y62),MONTH(Y62)+1,DAY(Y62)),""),"")
B64: =IF(B63<$G$13,B63+1,"") | C64: =IF(PERIOD<>"",DATE(YEAR(C63),MONTH(C63),DAY(C63)+15),"") | D64: =IF(PERIOD<>"",ROUNDDOWN($F$43/$B$70,0),"") | S64: =IF(NOT(B64=AA49),$D$43*(($B$70-(B64-1))/((($B$70+1)/2)*$B$70)),"") | U64: =IF(NOT(B64=AA50),D64-T64,"") | X64: =IF(WEEKDAY(Y64,2)=1,"Monday",IF(WEEKDAY(Y64,2)=2,"Tuesday",IF(WEEKDAY(Y64,2)=3,"Wednesday",IF(WEEKDAY(Y64,2)=4,"Thursday",IF(WEEKDAY(Y64,2)=5,"Friday",IF(WEEKDAY(Y64,2)=6,"Saturday",IF(WEEKDAY(Y64,2)=7,"Sunday"))))))) -> #VALUE! | Y64: =IF(PERIOD<>"",IF(DATE(YEAR(Y63),MONTH(Y63),DAY(Y63))<=$K$43,DATE(YEAR(Y63),MONTH(Y63)+1,DAY(Y63)),""),"")
B65: =IF(B64<$G$13,B64+1,"") | C65: =IF(PERIOD<>"",DATE(YEAR(C64),MONTH(C64),DAY(C64)+15),"") | D65: =IF(PERIOD<>"",ROUNDDOWN($F$43/$B$70,0),"") | S65: =IF(NOT(B65=AA50),$D$43*(($B$70-(B65-1))/((($B$70+1)/2)*$B$70)),"") | U65: =IF(NOT(B65=AA51),D65-T65,"") | X65: =IF(WEEKDAY(Y65,2)=1,"Monday",IF(WEEKDAY(Y65,2)=2,"Tuesday",IF(WEEKDAY(Y65,2)=3,"Wednesday",IF(WEEKDAY(Y65,2)=4,"Thursday",IF(WEEKDAY(Y65,2)=5,"Friday",IF(WEEKDAY(Y65,2)=6,"Saturday",IF(WEEKDAY(Y65,2)=7,"Sunday"))))))) -> #VALUE! | Y65: =IF(PERIOD<>"",IF(DATE(YEAR(Y64),MONTH(Y64),DAY(Y64))<=$K$43,DATE(YEAR(Y64),MONTH(Y64)+1,DAY(Y64)),""),"")
B66: =IF(B65<$G$13,B65+1,"") | C66: =IF(PERIOD<>"",DATE(YEAR(C65),MONTH(C65),DAY(C65)+15),"") | D66: =IF(PERIOD<>"",ROUNDDOWN($F$43/$B$70,0),"") | S66: =IF(NOT(B66=AA51),$D$43*(($B$70-(B66-1))/((($B$70+1)/2)*$B$70)),"") | U66: =IF(NOT(B66=AA52),D66-T66,"") | X66: =IF(WEEKDAY(Y66,2)=1,"Monday",IF(WEEKDAY(Y66,2)=2,"Tuesday",IF(WEEKDAY(Y66,2)=3,"Wednesday",IF(WEEKDAY(Y66,2)=4,"Thursday",IF(WEEKDAY(Y66,2)=5,"Friday",IF(WEEKDAY(Y66,2)=6,"Saturday",IF(WEEKDAY(Y66,2)=7,"Sunday"))))))) -> #VALUE! | Y66: =IF(PERIOD<>"",IF(DATE(YEAR(Y65),MONTH(Y65),DAY(Y65))<=$K$43,DATE(YEAR(Y65),MONTH(Y65)+1,DAY(Y65)),""),"")
B67: =IF(B66<$G$13,B66+1,"") | C67: =IF(PERIOD<>"",DATE(YEAR(C66),MONTH(C66),DAY(C66)+15),"") | D67: =IF(PERIOD<>"",ROUNDDOWN($F$43/$B$70,0),"") | S67: =IF(NOT(B67=AA52),$D$43*(($B$70-(B67-1))/((($B$70+1)/2)*$B$70)),"") | U67: =IF(NOT(B67=AA53),D67-T67,"") | X67: =IF(WEEKDAY(Y67,2)=1,"Monday",IF(WEEKDAY(Y67,2)=2,"Tuesday",IF(WEEKDAY(Y67,2)=3,"Wednesday",IF(WEEKDAY(Y67,2)=4,"Thursday",IF(WEEKDAY(Y67,2)=5,"Friday",IF(WEEKDAY(Y67,2)=6,"Saturday",IF(WEEKDAY(Y67,2)=7,"Sunday"))))))) -> #VALUE! | Y67: =IF(PERIOD<>"",IF(DATE(YEAR(Y66),MONTH(Y66),DAY(Y66))<=$K$43,DATE(YEAR(Y66),MONTH(Y66)+1,DAY(Y66)),""),"")
B68: =IF(B67<$G$13,B67+1,"") | C68: =IF(PERIOD<>"",DATE(YEAR(C67),MONTH(C67),DAY(C67)+15),"") | D68: =IF(PERIOD<>"",ROUNDDOWN($F$43/$B$70,0),"") | S68: =IF(NOT(B68=AA53),$D$43*(($B$70-(B68-1))/((($B$70+1)/2)*$B$70)),"") | U68: =IF(NOT(B68=AA54),D68-T68,"") | X68: =IF(WEEKDAY(Y68,2)=1,"Monday",IF(WEEKDAY(Y68,2)=2,"Tuesday",IF(WEEKDAY(Y68,2)=3,"Wednesday",IF(WEEKDAY(Y68,2)=4,"Thursday",IF(WEEKDAY(Y68,2)=5,"Friday",IF(WEEKDAY(Y68,2)=6,"Saturday",IF(WEEKDAY(Y68,2)=7,"Sunday"))))))) -> #VALUE! | Y68: =IF(PERIOD<>"",IF(DATE(YEAR(Y67),MONTH(Y67),DAY(Y67))<=$K$43,DATE(YEAR(Y67),MONTH(Y67)+1,DAY(Y67)),""),"")
B69: =IF(B68<$G$13,B68+1,"") | C69: =IF(PERIOD<>"",DATE(YEAR(C68),MONTH(C68),DAY(C68)+15),"") | D69: =IF(PERIOD<>"",ROUNDDOWN($F$43/$B$70,0),"") | S69: =IF(NOT(B69=AA45),$D$43*(($B$70-(B69-1))/((($B$70+1)/2)*$B$70)),"") | U69: =IF(NOT(B69=AA46),D69-T69,"") | Y69: =IF(PERIOD<>"",IF(DATE(YEAR(Y59),MONTH(Y59),DAY(Y59))<=$K$43,DATE(YEAR(Y59),MONTH(Y59)+1,DAY(Y59)),""),"")
B70: =G13 -> 8 | D70: =F43 -> 100706.71 | S70: =SUM(S45:T69) -> 19753 | U70: =SUM(U45:V69) -> 80953.71
B72: IMPORTANT REMINDERS:

Sheet 48 payments (computation)semi
A4: 9th Floor Times Plaza Bldg., UN Ave. Cor. Taft Ave. Ermita Manila
A5: Manila, Philippines
A6: 353-85-24/25
A7: =UPPER("Computation Sheet and Payment Schedule") -> COMPUTATION SHEET AND PAYMENT SCHEDULE
A8: NAME | C8: ADDRESS | E8: TYPE OF LOAN | H8: TERMS
A9: =IF(OR_NAME<>"",Client_Name &" or " & OR_NAME,Client_Name) -> ** or ** | C9: =PROPER('Master data Input'!C8) -> ** | F9: =Type_of_Loan&TEXT(IF(Express="YES","-EXPRESS",""),"") -> SML | H9: In months | I9: =DATEDIF(Start_Payment,Maturitydate,"d")/30 -> 7.1333333 | J9: =Terms -> 7.1333333
F10: Interest/mo | G10: =Interest -> 0.03 | H10: from | I10: to
A11: =IF(UPPER(OR_NAME)<>" ",UPPER(OR_NAME),".") -> ** | H11: =Date_Released -> 46083 | I11: =MaturityDate_data_input -> 46342 | M11: ='Master data Input'!F30 -> 46342 | N11: end of term | O11: =I9 -> 7.1333333
F12: # of payments | G12: =Number_of_Amortization -> 8
M13: =IF(U26<H11,H11,U26) -> 46098
A14: COMPUTATION OF NET PROCEEDS
W15: 7
A16: Principal/ Amount Financed | F16: =Loan_Amount -> 80953.71
A18: Less Interest and Other Charges | G18: New | I18: =IF(I19>0,"NO", "YES") -> NO
A19: Interest | B19: =Interest -> 0.03 | C19: ="from"&TEXT(Date_Released," mm/dd/yyyy")&" to "&TEXT(Date_released2," mm/dd/yyyy") -> from 03/02/2026 to 03/17/2026 | E19: =IF(Type_of_Loan="BL-SA",ROUND(Principal_Amount*(Interest/30)*DATEDIF(Date_Released,MaturityDate1,"D"),0),ROUND(Principal_Amount*(Interest/30)*DATEDIF(Date_Released,Date_released2,"d"),0)) -> 1214 | G19: Renewal Nth loan | I19: ='Master data Input'!C18 -> No | J19: =E19+D42/B42-(360/DATEDIF(H11,I11,"d")) -> 1212.854 | L19: =DATEDIF(H11,C44,"d") -> 45 | M19: days from loan release and 1st payment
A20: Processing Fee | C20: =Processing_Fee_in_Percentage -> 0.075 | E20: =Processing_Fee_in_Percentage*Principal_Amount -> 6071.5283 | G20: Installment Type | I20: =Installment_Type -> Monthly | L20: =DATEDIF(H11,M13,"D") -> 15
A21: Account Management Fee | E21: =Account_Management_fee -> Auto compute**
A22: Notarial fee | E22: =Notarial_Fee -> 500
A23: Doc fee | E23: =IF(Docfee_Yes_or_No="YES",ROUNDUP(Principal_Amount/200,0),0) -> 0
A24: ='Master data Input'!B42 -> MLRI -Insurance | E24: =Insurance -> Auto compute**
A25: ='Master data Input'!B45 -> Miscellaneous | E25: ='Master data Input'!C45 -> 500 | G25: Check No. | L25: =DATEDIF(M13,M11,"D") -> 244
A26: Total Finance charge | E26: =SUM(E19:E25) -> 8285.5282 | L26: =DATEDIF(H11,M11,"D") -> 259 | U26: =DATE(YEAR(C44),MONTH(C44),DAY(C44)-30) -> 46098
G27: PN no. | H27: ="PN-"&TEXT('Master data Input'!F10,"0000- ")&TEXT(" "," ")&'Master data Input'!C14 -> PN-. SML
A28: Others: | P28: =TEXT($L$19,"0")&"/"&TEXT($L$20,"0")&"/"&TEXT($L$25,"0")&"/"&TEXT($L$26,"0") -> 45/15/244/259 | X28: =45000*0.15*(305/360) -> 5718.75
A29: ='Master data Input'!B12 -> Outstanding Balance from previous loan | E29: =Outstanding_Balance_from_previous_loan -> 0 | L29: =DATEDIF(M13,C44,"d") -> 30
A30: Cash Advanced | E30: =Advanced_Payment -> 0
F32: =Total_Finance_Charge+SUM($E$29:$E$32) -> 8285.5282 | G32: MODE OF PAYMENT: | I32: ='Master data Input'!F42 -> 0
A34: Net Proceeds | F34: =Principal_Amount-Total_Deduction -> 72668.182 | M34: IF('Master data Input'!B35="YES",ROUNDUP(F16*0.0015,0),"0") | U34: DATEDIF(H11,I11,"D")
A36: Effective Rate (per month) | F36: =IF(Grace_Period_Interest=0,(Grace_Period_Interest+Total_UII)/Amount_of_Loan/(DATEDIF(Date_Released,MaturityDate1,"d")/30),(Grace_Period_Interest+Total_UII)/Amount_of_Loan/Term_masterdatainput) -> 0.032374983 | M36: IF(1200>O27,1200,O27)
A37: % of Finance charges to Total Amount Financed | F37: =Total_Finance_Charge/Principal_Amount -> 0.10234896 | G37: Release Date: | I37: =Date_Released -> 46083
G38: Agent: | H38: =UPPER(Agents)
A39: SCHEDULE OF AMORTIZATION
N40: =D42+E19 -> 20967 | O40: 11667
B41: Principal / Amount of Loan | D41: Interest Due on Loans | F41: Total Amount Payable | Y41: =DATE(YEAR(U20),MONTH(U20)+1,DAY(U20)) -> 31
B42: =Principal_Amount -> 80953.71 | D42: =IF(Type_of_Loan="BL-SA","",IF(Type_of_Loan="QCL",(Principal_Amount*Interest*Term_masterdatainput),ROUND(Principal_Amount*(Interest/30)*DATEDIF(Date_released2,MaturityDate1,"d"),0))) -> 19753 | F42: =IF(Type_of_Loan="BL-SA",Amount_of_Loan,Loan_Amount+Total_UII) -> 100706.71 | K42: =DATE(YEAR($C$44),MONTH($C$44)+($G$12-1),DAY($C$44)) -> 46342 | L42: w/out adjustment
B43: Period | C43: Due Date | D43: amortization | E43: Prepared/ Verified by: | S43: Interest | U43: Principal
B44: 1 | C44: =Start_Payment -> 46128 | D44: =D92-SUM(D45:D91) -> 12590.71 | S44: =IF(NOT(B44=AA26),$D$42*(($B$92-(B44-1))/((($B$92+1)/2)*$B$92)),"") -> 4389.5556 | U44: =IF(NOT(B44=AA27),D44-S44,"") -> 8201.1544 | X44: =IF(WEEKDAY(Y44,2)=1,"Monday",IF(WEEKDAY(Y44,2)=2,"Tuesday",IF(WEEKDAY(Y44,2)=3,"Wednesday",IF(WEEKDAY(Y44,2)=4,"Thursday",IF(WEEKDAY(Y44,2)=5,"Friday",IF(WEEKDAY(Y44,2)=6,"Saturday",IF(WEEKDAY(Y44,2)=7,"Sunday"))))))) -> Thursday | Y44: ='Master data Input'!C30 -> 46128
B45: =IF(B44<$G$12,B44+1,"") -> 2 | C45: =IF(PERIOD<>"",DATE(YEAR(C44),MONTH(C44),DAY(C44)+15),"") -> 46143 | D45: =IF(PERIOD<>"",ROUNDDOWN($F$42/$B$92,0),"") -> 12588 | S45: =IF(NOT(B45=AA27),$D$42*(($B$92-(B45-1))/((($B$92+1)/2)*$B$92)),"") -> 3840.8611 | U45: =IF(NOT(B45=AA30),D45-S45,"") -> 8747.1389 | X45: =IF(WEEKDAY(Y45,2)=1,"Monday",IF(WEEKDAY(Y45,2)=2,"Tuesday",IF(WEEKDAY(Y45,2)=3,"Wednesday",IF(WEEKDAY(Y45,2)=4,"Thursday",IF(WEEKDAY(Y45,2)=5,"Friday",IF(WEEKDAY(Y45,2)=6,"Saturday",IF(WEEKDAY(Y45,2)=7,"Sunday"))))))) -> Friday | Y45: =IF(PERIOD<>"",IF(DATE(YEAR(Y44),MONTH(Y44),DAY(Y44))<=$K$42,DATE(YEAR(Y44),MONTH(Y44),DAY(Y44)+15),""),"") -> 46143
B46: =IF(B45<$G$12,B45+1,"") -> 3 | C46: =IF(PERIOD<>"",DATE(YEAR(C45),MONTH(C45),DAY(C45)+15),"") -> 46158 | D46: =IF(PERIOD<>"",ROUNDDOWN($F$42/$B$92,0),"") -> 12588 | E46: Noted by: | S46: =IF(NOT(B46=AA30),$D$42*(($B$92-(B46-1))/((($B$92+1)/2)*$B$92)),"") -> 3292.1667 | U46: =IF(NOT(B46=AA32),D46-S46,"") -> 9295.8333 | X46: =IF(WEEKDAY(Y46,2)=1,"Monday",IF(WEEKDAY(Y46,2)=2,"Tuesday",IF(WEEKDAY(Y46,2)=3,"Wednesday",IF(WEEKDAY(Y46,2)=4,"Thursday",IF(WEEKDAY(Y46,2)=5,"Friday",IF(WEEKDAY(Y46,2)=6,"Saturday",IF(WEEKDAY(Y46,2)=7,"Sunday"))))))) -> Saturday | Y46: =IF(PERIOD<>"",IF(DATE(YEAR(Y45),MONTH(Y45),DAY(Y45))<=$K$42,DATE(YEAR(Y45),MONTH(Y45),DAY(Y45)+15),""),"") -> 46158
B47: =IF(B46<$G$12,B46+1,"") -> 4 | C47: =IF(PERIOD<>"",DATE(YEAR(C46),MONTH(C46),DAY(C46)+15),"") -> 46173 | D47: =IF(PERIOD<>"",ROUNDDOWN($F$42/$B$92,0),"") -> 12588 | S47: =IF(NOT(B47=AA32),$D$42*(($B$92-(B47-1))/((($B$92+1)/2)*$B$92)),"") -> 2743.4722 | U47: =IF(NOT(B47=AA33),D47-S47,"") -> 9844.5278 | X47: =IF(WEEKDAY(Y47,2)=1,"Monday",IF(WEEKDAY(Y47,2)=2,"Tuesday",IF(WEEKDAY(Y47,2)=3,"Wednesday",IF(WEEKDAY(Y47,2)=4,"Thursday",IF(WEEKDAY(Y47,2)=5,"Friday",IF(WEEKDAY(Y47,2)=6,"Saturday",IF(WEEKDAY(Y47,2)=7,"Sunday"))))))) -> Sunday | Y47: =IF(PERIOD<>"",IF(DATE(YEAR(Y46),MONTH(Y46),DAY(Y46))<=$K$42,DATE(YEAR(Y46),MONTH(Y46),DAY(Y46)+15),""),"") -> 46173
B48: =IF(B47<$G$12,B47+1,"") -> 5 | C48: =IF(PERIOD<>"",DATE(YEAR(C47),MONTH(C47),DAY(C47)+15),"") -> 46188 | D48: =IF(PERIOD<>"",ROUNDDOWN($F$42/$B$92,0),"") -> 12588 | S48: =IF(NOT(B48=AA33),$D$42*(($B$92-(B48-1))/((($B$92+1)/2)*$B$92)),"") -> 2194.7778 | U48: =IF(NOT(B48=AA34),D48-S48,"") -> 10393.222 | X48: =IF(WEEKDAY(Y48,2)=1,"Monday",IF(WEEKDAY(Y48,2)=2,"Tuesday",IF(WEEKDAY(Y48,2)=3,"Wednesday",IF(WEEKDAY(Y48,2)=4,"Thursday",IF(WEEKDAY(Y48,2)=5,"Friday",IF(WEEKDAY(Y48,2)=6,"Saturday",IF(WEEKDAY(Y48,2)=7,"Sunday"))))))) -> Monday | Y48: =IF(PERIOD<>"",IF(DATE(YEAR(Y47),MONTH(Y47),DAY(Y47))<=$K$42,DATE(YEAR(Y47),MONTH(Y47),DAY(Y47)+15),""),"") -> 46188
B49: =IF(B48<$G$12,B48+1,"") -> 6 | C49: =IF(PERIOD<>"",DATE(YEAR(C48),MONTH(C48),DAY(C48)+15),"") -> 46203 | D49: =IF(PERIOD<>"",ROUNDDOWN($F$42/$B$92,0),"") -> 12588 | E49: Released by: | S49: =IF(NOT(B49=AA34),$D$42*(($B$92-(B49-1))/((($B$92+1)/2)*$B$92)),"") -> 1646.0833 | U49: =IF(NOT(B49=AA35),D49-S49,"") -> 10941.917 | X49: =IF(WEEKDAY(Y49,2)=1,"Monday",IF(WEEKDAY(Y49,2)=2,"Tuesday",IF(WEEKDAY(Y49,2)=3,"Wednesday",IF(WEEKDAY(Y49,2)=4,"Thursday",IF(WEEKDAY(Y49,2)=5,"Friday",IF(WEEKDAY(Y49,2)=6,"Saturday",IF(WEEKDAY(Y49,2)=7,"Sunday"))))))) -> Tuesday | Y49: =IF(PERIOD<>"",IF(DATE(YEAR(Y48),MONTH(Y48),DAY(Y48))<=$K$42,DATE(YEAR(Y48),MONTH(Y48),DAY(Y48)+15),""),"") -> 46203
B50: =IF(B49<$G$12,B49+1,"") -> 7 | C50: =IF(PERIOD<>"",DATE(YEAR(C49),MONTH(C49),DAY(C49)+15),"") -> 46218 | D50: =IF(PERIOD<>"",ROUNDDOWN($F$42/$B$92,0),"") -> 12588 | S50: =IF(NOT(B50=AA35),$D$42*(($B$92-(B50-1))/((($B$92+1)/2)*$B$92)),"") -> 1097.3889 | U50: =IF(NOT(B50=AA36),D50-S50,"") -> 11490.611 | X50: =IF(WEEKDAY(Y50,2)=1,"Monday",IF(WEEKDAY(Y50,2)=2,"Tuesday",IF(WEEKDAY(Y50,2)=3,"Wednesday",IF(WEEKDAY(Y50,2)=4,"Thursday",IF(WEEKDAY(Y50,2)=5,"Friday",IF(WEEKDAY(Y50,2)=6,"Saturday",IF(WEEKDAY(Y50,2)=7,"Sunday"))))))) -> Wednesday | Y50: =IF(PERIOD<>"",IF(DATE(YEAR(Y49),MONTH(Y49),DAY(Y49))<=$K$42,DATE(YEAR(Y49),MONTH(Y49),DAY(Y49)+15),""),"") -> 46218
B51: =IF(B50<$G$12,B50+1,"") -> 8 | C51: =IF(PERIOD<>"",DATE(YEAR(C50),MONTH(C50),DAY(C50)+15),"") -> 46233 | D51: =IF(PERIOD<>"",ROUNDDOWN($F$42/$B$92,0),"") -> 12588 | S51: =IF(NOT(B51=AA36),$D$42*(($B$92-(B51-1))/((($B$92+1)/2)*$B$92)),"") -> 548.69444 | U51: =IF(NOT(B51=AA37),D51-S51,"") -> 12039.306 | X51: =IF(WEEKDAY(Y51,2)=1,"Monday",IF(WEEKDAY(Y51,2)=2,"Tuesday",IF(WEEKDAY(Y51,2)=3,"Wednesday",IF(WEEKDAY(Y51,2)=4,"Thursday",IF(WEEKDAY(Y51,2)=5,"Friday",IF(WEEKDAY(Y51,2)=6,"Saturday",IF(WEEKDAY(Y51,2)=7,"Sunday"))))))) -> Thursday | Y51: =IF(PERIOD<>"",IF(DATE(YEAR(Y50),MONTH(Y50),DAY(Y50))<=$K$42,DATE(YEAR(Y50),MONTH(Y50),DAY(Y50)+15),""),"") -> 46233
B52: =IF(B51<$G$12,B51+1,"") | C52: =IF(PERIOD<>"",DATE(YEAR(C51),MONTH(C51),DAY(C51)+15),"") | D52: =IF(PERIOD<>"",ROUNDDOWN($F$42/$B$92,0),"") | E52: Received Copy: | S52: =IF(NOT(B52=AA37),$D$42*(($B$92-(B52-1))/((($B$92+1)/2)*$B$92)),"") | U52: =IF(NOT(B52=AA38),D52-S52,"") | X52: =IF(WEEKDAY(Y52,2)=1,"Monday",IF(WEEKDAY(Y52,2)=2,"Tuesday",IF(WEEKDAY(Y52,2)=3,"Wednesday",IF(WEEKDAY(Y52,2)=4,"Thursday",IF(WEEKDAY(Y52,2)=5,"Friday",IF(WEEKDAY(Y52,2)=6,"Saturday",IF(WEEKDAY(Y52,2)=7,"Sunday"))))))) -> #VALUE! | Y52: =IF(PERIOD<>"",IF(DATE(YEAR(Y51),MONTH(Y51),DAY(Y51))<=$K$42,DATE(YEAR(Y51),MONTH(Y51),DAY(Y51)+15),""),"")
B53: =IF(B52<$G$12,B52+1,"") | C53: =IF(PERIOD<>"",DATE(YEAR(C52),MONTH(C52),DAY(C52)+15),"") | D53: =IF(PERIOD<>"",ROUNDDOWN($F$42/$B$92,0),"") | S53: =IF(NOT(B53=AA38),$D$42*(($B$92-(B53-1))/((($B$92+1)/2)*$B$92)),"") | U53: =IF(NOT(B53=AA39),D53-S53,"") | X53: =IF(WEEKDAY(Y53,2)=1,"Monday",IF(WEEKDAY(Y53,2)=2,"Tuesday",IF(WEEKDAY(Y53,2)=3,"Wednesday",IF(WEEKDAY(Y53,2)=4,"Thursday",IF(WEEKDAY(Y53,2)=5,"Friday",IF(WEEKDAY(Y53,2)=6,"Saturday",IF(WEEKDAY(Y53,2)=7,"Sunday"))))))) -> #VALUE! | Y53: =IF(PERIOD<>"",IF(DATE(YEAR(Y52),MONTH(Y52),DAY(Y52))<=$K$42,DATE(YEAR(Y52),MONTH(Y52),DAY(Y52)+15),""),"")
B54: =IF(B53<$G$12,B53+1,"") | C54: =IF(PERIOD<>"",DATE(YEAR(C53),MONTH(C53),DAY(C53)+15),"") | D54: =IF(PERIOD<>"",ROUNDDOWN($F$42/$B$92,0),"") | S54: =IF(NOT(B54=AA39),$D$42*(($B$92-(B54-1))/((($B$92+1)/2)*$B$92)),"") | U54: =IF(NOT(B54=AA40),D54-T54,"") | X54: =IF(WEEKDAY(Y54,2)=1,"Monday",IF(WEEKDAY(Y54,2)=2,"Tuesday",IF(WEEKDAY(Y54,2)=3,"Wednesday",IF(WEEKDAY(Y54,2)=4,"Thursday",IF(WEEKDAY(Y54,2)=5,"Friday",IF(WEEKDAY(Y54,2)=6,"Saturday",IF(WEEKDAY(Y54,2)=7,"Sunday"))))))) -> #VALUE! | Y54: =IF(PERIOD<>"",IF(DATE(YEAR(Y53),MONTH(Y53),DAY(Y53))<=$K$42,DATE(YEAR(Y53),MONTH(Y53),DAY(Y53)+15),""),"")
B55: =IF(B54<$G$12,B54+1,"") | C55: =IF(PERIOD<>"",DATE(YEAR(C54),MONTH(C54),DAY(C54)+15),"") | D55: =IF(PERIOD<>"",ROUNDDOWN($F$42/$B$92,0),"") | E55: Date: | G55: =Date_Released -> 46083 | S55: =IF(NOT(B55=AA40),$D$42*(($B$92-(B55-1))/((($B$92+1)/2)*$B$92)),"") | U55: =IF(NOT(B55=AA41),D55-T55,"") | X55: =IF(WEEKDAY(Y55,2)=1,"Monday",IF(WEEKDAY(Y55,2)=2,"Tuesday",IF(WEEKDAY(Y55,2)=3,"Wednesday",IF(WEEKDAY(Y55,2)=4,"Thursday",IF(WEEKDAY(Y55,2)=5,"Friday",IF(WEEKDAY(Y55,2)=6,"Saturday",IF(WEEKDAY(Y55,2)=7,"Sunday"))))))) -> #VALUE! | Y55: =IF(PERIOD<>"",IF(DATE(YEAR(Y54),MONTH(Y54),DAY(Y54))<=$K$42,DATE(YEAR(Y54),MONTH(Y54),DAY(Y54)+15),""),"")
B56: =IF(B55<$G$12,B55+1,"") | C56: =IF(PERIOD<>"",DATE(YEAR(C55),MONTH(C55),DAY(C55)+15),"") | D56: =IF(PERIOD<>"",ROUNDDOWN($F$42/$B$92,0),"") | E56: REMARKS | S56: =IF(NOT(B56=AA41),$D$42*(($B$92-(B56-1))/((($B$92+1)/2)*$B$92)),"") | U56: =IF(NOT(B56=AA42),D56-T56,"") | X56: =IF(WEEKDAY(Y56,2)=1,"Monday",IF(WEEKDAY(Y56,2)=2,"Tuesday",IF(WEEKDAY(Y56,2)=3,"Wednesday",IF(WEEKDAY(Y56,2)=4,"Thursday",IF(WEEKDAY(Y56,2)=5,"Friday",IF(WEEKDAY(Y56,2)=6,"Saturday",IF(WEEKDAY(Y56,2)=7,"Sunday"))))))) -> #VALUE! | Y56: =IF(PERIOD<>"",IF(DATE(YEAR(Y55),MONTH(Y55),DAY(Y55))<=$K$42,DATE(YEAR(Y55),MONTH(Y55),DAY(Y55)+15),""),"")
B57: =IF(B56<$G$12,B56+1,"") | C57: =IF(PERIOD<>"",DATE(YEAR(C56),MONTH(C56),DAY(C56)+15),"") | D57: =IF(PERIOD<>"",ROUNDDOWN($F$42/$B$92,0),"") | S57: =IF(NOT(B57=AA42),$D$42*(($B$92-(B57-1))/((($B$92+1)/2)*$B$92)),"") | U57: =IF(NOT(B57=AA43),D57-T57,"") | X57: =IF(WEEKDAY(Y57,2)=1,"Monday",IF(WEEKDAY(Y57,2)=2,"Tuesday",IF(WEEKDAY(Y57,2)=3,"Wednesday",IF(WEEKDAY(Y57,2)=4,"Thursday",IF(WEEKDAY(Y57,2)=5,"Friday",IF(WEEKDAY(Y57,2)=6,"Saturday",IF(WEEKDAY(Y57,2)=7,"Sunday"))))))) -> #VALUE! | Y57: =IF(PERIOD<>"",IF(DATE(YEAR(Y56),MONTH(Y56),DAY(Y56))<=$K$42,DATE(YEAR(Y56),MONTH(Y56),DAY(Y56)+15),""),"")
B58: =IF(B57<$G$12,B57+1,"") | C58: =IF(PERIOD<>"",DATE(YEAR(C57),MONTH(C57),DAY(C57)+15),"") | D58: =IF(PERIOD<>"",ROUNDDOWN($F$42/$B$92,0),"") | E58: =IF(Advanced_Payment=0,"","With Advance Payment of P "& Advanced_Payment) | S58: =IF(NOT(B58=AA43),$D$42*(($B$92-(B58-1))/((($B$92+1)/2)*$B$92)),"") | U58: =IF(NOT(B58=AA44),D58-T58,"") | X58: =IF(WEEKDAY(Y58,2)=1,"Monday",IF(WEEKDAY(Y58,2)=2,"Tuesday",IF(WEEKDAY(Y58,2)=3,"Wednesday",IF(WEEKDAY(Y58,2)=4,"Thursday",IF(WEEKDAY(Y58,2)=5,"Friday",IF(WEEKDAY(Y58,2)=6,"Saturday",IF(WEEKDAY(Y58,2)=7,"Sunday"))))))) -> #VALUE! | Y58: =IF(PERIOD<>"",IF(DATE(YEAR(Y57),MONTH(Y57),DAY(Y57))<=$K$42,DATE(YEAR(Y57),MONTH(Y57),DAY(Y57)+15),""),"")
B59: =IF(B58<$G$12,B58+1,"") | C59: =IF(PERIOD<>"",DATE(YEAR(C58),MONTH(C58),DAY(C58)+15),"") | D59: =IF(PERIOD<>"",ROUNDDOWN($F$42/$B$92,0),"") | S59: =IF(NOT(B59=AA44),$D$42*(($B$92-(B59-1))/((($B$92+1)/2)*$B$92)),"") | U59: =IF(NOT(B59=AA45),D59-T59,"") | X59: =IF(WEEKDAY(Y59,2)=1,"Monday",IF(WEEKDAY(Y59,2)=2,"Tuesday",IF(WEEKDAY(Y59,2)=3,"Wednesday",IF(WEEKDAY(Y59,2)=4,"Thursday",IF(WEEKDAY(Y59,2)=5,"Friday",IF(WEEKDAY(Y59,2)=6,"Saturday",IF(WEEKDAY(Y59,2)=7,"Sunday"))))))) -> #VALUE! | Y59: =IF(PERIOD<>"",IF(DATE(YEAR(Y58),MONTH(Y58),DAY(Y58))<=$K$42,DATE(YEAR(Y58),MONTH(Y58),DAY(Y58)+15),""),"")
B60: =IF(B59<$G$12,B59+1,"") | C60: =IF(PERIOD<>"",DATE(YEAR(C59),MONTH(C59),DAY(C59)+15),"") | D60: =IF(PERIOD<>"",ROUNDDOWN($F$42/$B$92,0),"") | S60: =IF(NOT(B60=AA45),$D$42*(($B$92-(B60-1))/((($B$92+1)/2)*$B$92)),"") | U60: =IF(NOT(B60=AA46),D60-T60,"") | X60: =IF(WEEKDAY(Y60,2)=1,"Monday",IF(WEEKDAY(Y60,2)=2,"Tuesday",IF(WEEKDAY(Y60,2)=3,"Wednesday",IF(WEEKDAY(Y60,2)=4,"Thursday",IF(WEEKDAY(Y60,2)=5,"Friday",IF(WEEKDAY(Y60,2)=6,"Saturday",IF(WEEKDAY(Y60,2)=7,"Sunday"))))))) -> #VALUE! | Y60: =IF(PERIOD<>"",IF(DATE(YEAR(Y59),MONTH(Y59),DAY(Y59))<=$K$42,DATE(YEAR(Y59),MONTH(Y59),DAY(Y59)+15),""),"")
B61: =IF(B60<$G$12,B60+1,"") | C61: =IF(PERIOD<>"",DATE(YEAR(C60),MONTH(C60),DAY(C60)+15),"") | D61: =IF(PERIOD<>"",ROUNDDOWN($F$42/$B$92,0),"") | S61: =IF(NOT(B61=AA46),$D$42*(($B$92-(B61-1))/((($B$92+1)/2)*$B$92)),"") | U61: =IF(NOT(B61=AA47),D61-T61,"") | X61: =IF(WEEKDAY(Y61,2)=1,"Monday",IF(WEEKDAY(Y61,2)=2,"Tuesday",IF(WEEKDAY(Y61,2)=3,"Wednesday",IF(WEEKDAY(Y61,2)=4,"Thursday",IF(WEEKDAY(Y61,2)=5,"Friday",IF(WEEKDAY(Y61,2)=6,"Saturday",IF(WEEKDAY(Y61,2)=7,"Sunday"))))))) -> #VALUE! | Y61: =IF(PERIOD<>"",IF(DATE(YEAR(Y60),MONTH(Y60),DAY(Y60))<=$K$42,DATE(YEAR(Y60),MONTH(Y60),DAY(Y60)+15),""),"")
B62: =IF(B61<$G$12,B61+1,"") | C62: =IF(PERIOD<>"",DATE(YEAR(C61),MONTH(C61),DAY(C61)+15),"") | D62: =IF(PERIOD<>"",ROUNDDOWN($F$42/$B$92,0),"") | S62: =IF(NOT(B62=AA47),$D$42*(($B$92-(B62-1))/((($B$92+1)/2)*$B$92)),"") | U62: =IF(NOT(B62=AA48),D62-T62,"") | X62: =IF(WEEKDAY(Y62,2)=1,"Monday",IF(WEEKDAY(Y62,2)=2,"Tuesday",IF(WEEKDAY(Y62,2)=3,"Wednesday",IF(WEEKDAY(Y62,2)=4,"Thursday",IF(WEEKDAY(Y62,2)=5,"Friday",IF(WEEKDAY(Y62,2)=6,"Saturday",IF(WEEKDAY(Y62,2)=7,"Sunday"))))))) -> #VALUE! | Y62: =IF(PERIOD<>"",IF(DATE(YEAR(Y61),MONTH(Y61),DAY(Y61))<=$K$42,DATE(YEAR(Y61),MONTH(Y61),DAY(Y61)+15),""),"")
B63: =IF(B62<$G$12,B62+1,"") | C63: =IF(PERIOD<>"",DATE(YEAR(C62),MONTH(C62),DAY(C62)+15),"") | D63: =IF(PERIOD<>"",ROUNDDOWN($F$42/$B$92,0),"") | S63: =IF(NOT(B63=AA48),$D$42*(($B$92-(B63-1))/((($B$92+1)/2)*$B$92)),"") | U63: =IF(NOT(B63=AA49),D63-T63,"") | X63: =IF(WEEKDAY(Y63,2)=1,"Monday",IF(WEEKDAY(Y63,2)=2,"Tuesday",IF(WEEKDAY(Y63,2)=3,"Wednesday",IF(WEEKDAY(Y63,2)=4,"Thursday",IF(WEEKDAY(Y63,2)=5,"Friday",IF(WEEKDAY(Y63,2)=6,"Saturday",IF(WEEKDAY(Y63,2)=7,"Sunday"))))))) -> #VALUE! | Y63: =IF(PERIOD<>"",IF(DATE(YEAR(Y62),MONTH(Y62),DAY(Y62))<=$K$42,DATE(YEAR(Y62),MONTH(Y62),DAY(Y62)+15),""),"")
B64: =IF(B63<$G$12,B63+1,"") | C64: =IF(PERIOD<>"",DATE(YEAR(C63),MONTH(C63),DAY(C63)+15),"") | D64: =IF(PERIOD<>"",ROUNDDOWN($F$42/$B$92,0),"") | S64: =IF(NOT(B64=AA49),$D$42*(($B$92-(B64-1))/((($B$92+1)/2)*$B$92)),"") | U64: =IF(NOT(B64=AA50),D64-T64,"") | X64: =IF(WEEKDAY(Y64,2)=1,"Monday",IF(WEEKDAY(Y64,2)=2,"Tuesday",IF(WEEKDAY(Y64,2)=3,"Wednesday",IF(WEEKDAY(Y64,2)=4,"Thursday",IF(WEEKDAY(Y64,2)=5,"Friday",IF(WEEKDAY(Y64,2)=6,"Saturday",IF(WEEKDAY(Y64,2)=7,"Sunday"))))))) -> #VALUE! | Y64: =IF(PERIOD<>"",IF(DATE(YEAR(Y63),MONTH(Y63),DAY(Y63))<=$K$42,DATE(YEAR(Y63),MONTH(Y63),DAY(Y63)+15),""),"")
B65: =IF(B64<$G$12,B64+1,"") | C65: =IF(PERIOD<>"",DATE(YEAR(C64),MONTH(C64),DAY(C64)+15),"") | D65: =IF(PERIOD<>"",ROUNDDOWN($F$42/$B$92,0),"") | S65: =IF(NOT(B65=AA50),$D$42*(($B$92-(B65-1))/((($B$92+1)/2)*$B$92)),"") | U65: =IF(NOT(B65=AA51),D65-T65,"") | X65: =IF(WEEKDAY(Y65,2)=1,"Monday",IF(WEEKDAY(Y65,2)=2,"Tuesday",IF(WEEKDAY(Y65,2)=3,"Wednesday",IF(WEEKDAY(Y65,2)=4,"Thursday",IF(WEEKDAY(Y65,2)=5,"Friday",IF(WEEKDAY(Y65,2)=6,"Saturday",IF(WEEKDAY(Y65,2)=7,"Sunday"))))))) -> #VALUE! | Y65: =IF(PERIOD<>"",IF(DATE(YEAR(Y64),MONTH(Y64),DAY(Y64))<=$K$42,DATE(YEAR(Y64),MONTH(Y64),DAY(Y64)+15),""),"")
B66: =IF(B65<$G$12,B65+1,"") | C66: =IF(PERIOD<>"",DATE(YEAR(C65),MONTH(C65),DAY(C65)+15),"") | D66: =IF(PERIOD<>"",ROUNDDOWN($F$42/$B$92,0),"") | S66: =IF(NOT(B66=AA51),$D$42*(($B$92-(B66-1))/((($B$92+1)/2)*$B$92)),"") | U66: =IF(NOT(B66=AA52),D66-T66,"") | X66: =IF(WEEKDAY(Y66,2)=1,"Monday",IF(WEEKDAY(Y66,2)=2,"Tuesday",IF(WEEKDAY(Y66,2)=3,"Wednesday",IF(WEEKDAY(Y66,2)=4,"Thursday",IF(WEEKDAY(Y66,2)=5,"Friday",IF(WEEKDAY(Y66,2)=6,"Saturday",IF(WEEKDAY(Y66,2)=7,"Sunday"))))))) -> #VALUE! | Y66: =IF(PERIOD<>"",IF(DATE(YEAR(Y65),MONTH(Y65),DAY(Y65))<=$K$42,DATE(YEAR(Y65),MONTH(Y65),DAY(Y65)+15),""),"")
B67: =IF(B66<$G$12,B66+1,"") | C67: =IF(PERIOD<>"",DATE(YEAR(C66),MONTH(C66),DAY(C66)+15),"") | D67: =IF(PERIOD<>"",ROUNDDOWN($F$42/$B$92,0),"") | S67: =IF(NOT(B67=AA52),$D$42*(($B$92-(B67-1))/((($B$92+1)/2)*$B$92)),"") | U67: =IF(NOT(B67=AA53),D67-T67,"") | X67: =IF(WEEKDAY(Y67,2)=1,"Monday",IF(WEEKDAY(Y67,2)=2,"Tuesday",IF(WEEKDAY(Y67,2)=3,"Wednesday",IF(WEEKDAY(Y67,2)=4,"Thursday",IF(WEEKDAY(Y67,2)=5,"Friday",IF(WEEKDAY(Y67,2)=6,"Saturday",IF(WEEKDAY(Y67,2)=7,"Sunday"))))))) -> #VALUE! | Y67: =IF(PERIOD<>"",IF(DATE(YEAR(Y66),MONTH(Y66),DAY(Y66))<=$K$42,DATE(YEAR(Y66),MONTH(Y66),DAY(Y66)+15),""),"")
B68: =IF(B67<$G$12,B67+1,"") | C68: =IF(PERIOD<>"",DATE(YEAR(C67),MONTH(C67),DAY(C67)+15),"") | D68: =IF(PERIOD<>"",ROUNDDOWN($F$42/$B$92,0),"") | S68: =IF(NOT(B68=AA53),$D$42*(($B$92-(B68-1))/((($B$92+1)/2)*$B$92)),"") | U68: =IF(NOT(B68=AA54),D68-T68,"") | X68: =IF(WEEKDAY(Y68,2)=1,"Monday",IF(WEEKDAY(Y68,2)=2,"Tuesday",IF(WEEKDAY(Y68,2)=3,"Wednesday",IF(WEEKDAY(Y68,2)=4,"Thursday",IF(WEEKDAY(Y68,2)=5,"Friday",IF(WEEKDAY(Y68,2)=6,"Saturday",IF(WEEKDAY(Y68,2)=7,"Sunday"))))))) -> #VALUE! | Y68: =IF(PERIOD<>"",IF(DATE(YEAR(Y67),MONTH(Y67),DAY(Y67))<=$K$42,DATE(YEAR(Y67),MONTH(Y67),DAY(Y67)+15),""),"")
B69: =IF(B68<$G$12,B68+1,"") | C69: =IF(PERIOD<>"",DATE(YEAR(C68),MONTH(C68),DAY(C68)+15),"") | D69: =IF(PERIOD<>"",ROUNDDOWN($F$42/$B$92,0),"") | S69: =IF(NOT(B69=AA54),$D$42*(($B$92-(B69-1))/((($B$92+1)/2)*$B$92)),"") | U69: =IF(NOT(B69=AA55),D69-T69,"") | X69: =IF(WEEKDAY(Y69,2)=1,"Monday",IF(WEEKDAY(Y69,2)=2,"Tuesday",IF(WEEKDAY(Y69,2)=3,"Wednesday",IF(WEEKDAY(Y69,2)=4,"Thursday",IF(WEEKDAY(Y69,2)=5,"Friday",IF(WEEKDAY(Y69,2)=6,"Saturday",IF(WEEKDAY(Y69,2)=7,"Sunday"))))))) -> #VALUE! | Y69: =IF(PERIOD<>"",IF(DATE(YEAR(Y68),MONTH(Y68),DAY(Y68))<=$K$42,DATE(YEAR(Y68),MONTH(Y68),DAY(Y68)+15),""),"")
B70: =IF(B69<$G$12,B69+1,"") | C70: =IF(PERIOD<>"",DATE(YEAR(C69),MONTH(C69),DAY(C69)+15),"") | D70: =IF(PERIOD<>"",ROUNDDOWN($F$42/$B$92,0),"") | S70: =IF(NOT(B70=AA55),$D$42*(($B$92-(B70-1))/((($B$92+1)/2)*$B$92)),"") | U70: =IF(NOT(B70=AA56),D70-T70,"") | X70: =IF(WEEKDAY(Y70,2)=1,"Monday",IF(WEEKDAY(Y70,2)=2,"Tuesday",IF(WEEKDAY(Y70,2)=3,"Wednesday",IF(WEEKDAY(Y70,2)=4,"Thursday",IF(WEEKDAY(Y70,2)=5,"Friday",IF(WEEKDAY(Y70,2)=6,"Saturday",IF(WEEKDAY(Y70,2)=7,"Sunday"))))))) -> #VALUE! | Y70: =IF(PERIOD<>"",IF(DATE(YEAR(Y69),MONTH(Y69),DAY(Y69))<=$K$42,DATE(YEAR(Y69),MONTH(Y69),DAY(Y69)+15),""),"")
... B91: =IF(B90<$G$12,B90+1,"") | C91: =IF(PERIOD<>"",DATE(YEAR(C90),MONTH(C90),DAY(C90)+15),"") | D91: =IF(PERIOD<>"",ROUNDDOWN($F$42/$B$92,0),"") | S91: =IF(NOT(B91=AA76),$D$42*(($B$92-(B91-1))/((($B$92+1)/2)*$B$92)),"") | U91: =IF(NOT(B91=AA77),D91-T91,"") | X91: =IF(WEEKDAY(Y91,2)=1,"Monday",IF(WEEKDAY(Y91,2)=2,"Tuesday",IF(WEEKDAY(Y91,2)=3,"Wednesday",IF(WEEKDAY(Y91,2)=4,"Thursday",IF(WEEKDAY(Y91,2)=5,"Friday",IF(WEEKDAY(Y91,2)=6,"Saturday",IF(WEEKDAY(Y91,2)=7,"Sunday"))))))) -> #VALUE! | Y91: =IF(PERIOD<>"",IF(DATE(YEAR(Y90),MONTH(Y90),DAY(Y90))<=$K$42,DATE(YEAR(Y90),MONTH(Y90),DAY(Y90)+15),""),"")
B92: =G12 -> 8 | D92: =F42 -> 100706.71
B94: IMPORTANT REMINDERS:

Sheet Sheet3
A1: 1 | B1: ='Semi Monthly 3 SL'!G13 -> 12 | I1: sheet
A2: 2 | B2: =B1-1 -> 11
A3: 3 | B3: =B2-1 -> 10
A4: 4 | B4: =B3-1 -> 9
A5: 5 | B5: =B4-1 -> 8
A6: 6 | B6: =B5-1 -> 7
A7: 7 | B7: =B6-1 -> 6
A8: 8 | B8: =B7-1 -> 5
A9: 9 | B9: =B8-1 -> 4
A10: 10 | B10: =B9-1 -> 3
A11: 11 | B11: =B10-1 -> 2
A12: 12 | B12: =B11-1 -> 1
A13: 13 | B13: =B12-1 -> 0
... A29: 29 | B29: =B28-1 -> -16
A30: 30
A31: 31
A32: 32
A33: 33
A34: 34
A35: 35
A36: 36
A37: 37
A38: 38
A39: 39
A40: 40
A41: 41
... A99: 99

Sheet Agent
A1: ONLINE (WEBSITE)
A2: WALK IN
A3: ALICIA SAAVEDRA
A4: CARMELITA DUMA
A5: DELIA OLARTE
A6: EDGAR LAGUITAN
A7: ELISA LAGUITAN
A8: EMELINDA PARAISO
A9: ERMELITO NAPOLEON
A10: EVANGELINE DETERA
A11: FABIOLITA BASAY
A12: FREDERICK MARCELO
... A30: ZENAIDA CABRIDO

Sheet Sheet1
A2: LIST OF AGENTS

Sheet parameter
A1: GROSS AMOUNT | C1: Add amount | K1: TERM | L1: ADD ON | M1: CONTRACTUAL | N1: x12
A2: NET AMOUNT | C2: MLRI | D2: AMF(reg) | E2: DOCUMENTATION FEE | G2: AMF(bl-sa) | H2: %AMF(reg) | I2: NOTARIAL | K2: 1 | L2: 3 | M2: 3 | N2: =M2*12 -> 36
C3: 400 | D3: 500 | E3: 400 | G3: 1000 | H3: 0.02 | I3: 500 | K3: 2 | L3: 3 | M3: 3.98 | N3: =M3*12 -> 47.76
K4: 3 | L4: 3 | M4: 4.43 | N4: =M4*12 -> 53.16
K5: 4 | L5: 3 | M5: 4.7 | N5: =M5*12 -> 56.4
K6: 5 | L6: 3 | M6: 4.85 | N6: =M6*12 -> 58.2
K7: 6 | L7: 3 | M7: 4.95 | N7: =M7*12 -> 59.4
K8: 7 | L8: 3 | M8: 5.01 | N8: =M8*12 -> 60.12
K9: 8 | L9: 3 | M9: 5.05 | N9: =M9*12 -> 60.6
K10: 9 | L10: 3 | M10: 5.07 | N10: =M10*12 -> 60.84
K11: 10 | L11: 3 | M11: 5.08 | N11: =M11*12 -> 60.96
K12: 11 | L12: 3 | M12: 5.08 | N12: =M12*12 -> 60.96
K13: 12 | L13: 3 | M13: 5.08 | N13: =M13*12 -> 60.96
K15: 1 | L15: 3.5 | M15: 3.5 | N15: =M15*12 -> 42
K16: 2 | L16: 3.5 | M16: 4.63 | N16: =M16*12 -> 55.56
... K78: 12 | L78: 2.5 | M78: 4.28 | N78: =M78*12 -> 51.36

Sheet Get Gross (2)
A2: Loan Type | D2: BL-SA
A3: Net Amount | D3: 300000
A4: Add on Rate | C4: 0.0275
A5: Processing fee | C5: 0.06
A6: Term | C6: 6
A8: Notarial | C8: =para_add_notarial -> 500
A9: Account Management fee | C9: =IF(D2="BL-SA",para_blsa_amf,2%/D20+para_add_amf_others) -> 1000
A10: MLRI Insurance | B10: Yes | C10: =IF(B10="Yes",get_gross_net_amount/1000*get_gross_term+para_add_mlri,0) -> 2200
A11: Documentation fee | C11: =get_gross_net_amount/200+para_add_doc -> 1900
A12: Others:
A16: TOTAL Charges | D16: =SUM(C8:C14) -> 5600
C17: Gross Loan = Numerator/Denominator | D17: =get_gross_net_amount+D16 -> 305600 | E17: (numerator)
D18: =100%-C5 -> 0.94 | E18: (denominator)
C20: Gross Loan = | D20: =D17/D18 -> 325106.38
C23: Total OB = | D23: =D20*C4*get_gross_term+D20 -> 378748.94

Sheet Parameter (2)
A1: Additional Fee (BLSA) | F1: Additional Fee (OTHERS)
A2: MLRI | B2: NOTARIAL | C2: DOCUMENTATION | D2: BLSA-AMF | G2: TOTAL OB | H2: Others | J2: Yes
A3: 400 | B3: 500 | C3: 400 | D3: 1000 | G3: 1000 | H3: 500 | J3: No
